Workbook

Sheet General Summary
A1: GENERAL SUMMARY (BASE BID)
A2: DIVISION NO. | B2: DESCRIPTION | C2: TOTAL DIV. COST
A3: 1000 | B3: General Requirments | C3: ='Base Bid'!Q15 -> 184000
A4: 26000 | B4: Electrical | C4: ='Base Bid'!Q277 -> 2090736.7
A5: 26000 | B5: Telecommunication | C5: ='Base Bid'!Q376 -> 295042.39
A6: 26000 | B6: Electronic & Safety Security | C6: ='Base Bid'!Q453 -> 251546.67
A7: TOTAL COST | C7: =SUM(C3:C6) -> 2821325.7
A9: CONTIGENCIES (5%) | B9: 0.05 | C9: =C7*B9 -> 141066.29
A10: MATERIAL MARKUPS (20%) | B10: 0.2 | C10: =B10*SUM('Base Bid'!O17:O454) -> 312193.46
A11: LABOR MARKUPS (31%) | B11: 0.31 | C11: =B11*SUM('Base Bid'!M17:M454) -> 333671.12
A12: OVERHEAD (10%) | B12: 0.1 | C12: =C7*B12 -> 282132.57
A13: PROFIT (10%) | B13: 0.1 | C13: =C7*B13 -> 282132.57
A14: TAX (9.2%) | B14: 0.092 | C14: =C7*B14 -> 259561.97
A15: PERFORMANCE AND PAYMENT BONDS | B15: 0.015 | C15: =C7*B15 -> 42319.886
A16: TOTAL BASEBID | C16: =SUM(C7,C9:C15) -> 4474403.6
A18: GENERAL SUMMARY (ADD ALTERNATE)
A19: DIVISION NO. | B19: DESCRIPTION | C19: TOTAL DIV. COST
A20: 1000 | B20: General Requirments | C20: ='Add Alternate'!Q15 -> 1500
A21: 26000 | B21: Pedestrain Gate Card Reader | C21: ='Add Alternate'!Q46 -> 10338.246
A22: TOTAL COST | C22: =SUM(C20:C21) -> 11838.246
A24: CONTIGENCIES (5%) | B24: 0.05 | C24: =C22*B24 -> 591.9123
A25: MATERIAL MARKUPS (20%) | B25: 0.2 | C25: =B25*SUM('Add Alternate'!O17:O46) -> 639.9293
A26: LABOR MARKUPS (31%) | B26: 0.31 | C26: =B26*SUM('Add Alternate'!M17:M46) -> 2212.9659
A27: OVERHEAD (10%) | B27: 0.1 | C27: =C22*B27 -> 1183.8246
A28: PROFIT (10%) | B28: 0.1 | C28: =C22*B28 -> 1183.8246
A29: TAX (9.2%) | B29: 0.092 | C29: =C22*B29 -> 1089.1186
A30: PERFORMANCE AND PAYMENT BONDS | B30: 0.015 | C30: =C22*B30 -> 177.57369
A31: TOTAL BASEBID | C31: =SUM(C22,C24:C30) -> 18917.395

Sheet Base Bid
A2: DETAILED BREAKDOWN OF ITEMS
B3: Project Name | D3: Joint Public Safety Facility
B4: Project Address | D4: 2100 w edgewood dr. port angeles, wa 98363
B5: Scope: | D5: Electrical
A6: S# | B6: Dwg. | C6: CSI NO | D6: DESCRIPTION | E6: QTY. | F6: Wastage | G6: Qty w/ Waste | H6: UNIT | I6: UNIT LABOR HOUR | J6: TOTAL LABOR HOUR | K6: LABOR WAGE/ HOUR | L6: UNIT LABOR COST | M6: TOTAL LABOR COST | N6: UNIT MATERIAL COST | O6: TOTAL MATERIAL COST | P6: UNIT PRICE (Labor & Material) | Q6: TRADE TOTAL
C7: 1 | D7: DIVISION 01-GENERAL REQUIREMENTS
A8: =IF(F8<>"",1+MAX($A$2:A7),"") -> 1 | D8: Permits | E8: 1 | F8: 0 | G8: =(F8*E8)+E8 -> 1 | H8: LS | I8: 0 | J8: =+I8*G8 -> 0 | K8: 0 | L8: =I8*K8 -> 0 | M8: =K8*J8 -> 0 | N8: 0 | O8: =N8*G8 -> 0 | P8: =(I8*K8)+N8 -> 0 | Q8: 184000
A9: =IF(F9<>"",1+MAX($A$2:A8),"") -> 2 | D9: Supervision and Coordination | E9: 1 | F9: 0 | G9: =(F9*E9)+E9 -> 1 | H9: LS | I9: 0 | J9: =+I9*G9 -> 0 | K9: 0 | L9: =I9*K9 -> 0 | M9: =K9*J9 -> 0 | N9: 0 | O9: =N9*G9 -> 0 | P9: =(I9*K9)+N9 -> 0
A10: =IF(F10<>"",1+MAX($A$2:A9),"") -> 3 | D10: Submittals and Shop drawings | E10: 1 | F10: 0 | G10: =(F10*E10)+E10 -> 1 | H10: LS | I10: 0 | J10: =+I10*G10 -> 0 | K10: 0 | L10: =I10*K10 -> 0 | M10: =K10*J10 -> 0 | N10: 0 | O10: =N10*G10 -> 0 | P10: =(I10*K10)+N10 -> 0
A11: =IF(F11<>"",1+MAX($A$2:A10),"") -> 4 | D11: Final Cleaning | E11: 1 | F11: 0 | G11: =(F11*E11)+E11 -> 1 | H11: LS | I11: 0 | J11: =+I11*G11 -> 0 | K11: 0 | L11: =I11*K11 -> 0 | M11: =K11*J11 -> 0 | N11: 0 | O11: =N11*G11 -> 0 | P11: =(I11*K11)+N11 -> 0
A12: =IF(F12<>"",1+MAX($A$2:A11),"") -> 5 | D12: Mobilization Costs | E12: 1 | F12: 0 | G12: =(F12*E12)+E12 -> 1 | H12: LS | I12: 0 | J12: =+I12*G12 -> 0 | K12: 0 | L12: =I12*K12 -> 0 | M12: =K12*J12 -> 0 | N12: 0 | O12: =N12*G12 -> 0 | P12: =(I12*K12)+N12 -> 0
A13: =IF(F13<>"",1+MAX($A$2:A12),"") -> 6 | D13: Temporary Control & Facilities | E13: 1 | F13: 0 | G13: =(F13*E13)+E13 -> 1 | H13: LS | I13: 0 | J13: =+I13*G13 -> 0 | K13: 0 | L13: =I13*K13 -> 0 | M13: =K13*J13 -> 0 | N13: 0 | O13: =N13*G13 -> 0 | P13: =(I13*K13)+N13 -> 0
A14: =IF(F14<>"",1+MAX($A$2:A13),"") -> 7 | D14: Scaffolding | E14: 1 | F14: 0 | G14: =(F14*E14)+E14 -> 1 | H14: LS | I14: 0 | J14: =+I14*G14 -> 0 | K14: 0 | L14: =I14*K14 -> 0 | M14: =K14*J14 -> 0 | N14: 0 | O14: =N14*G14 -> 0 | P14: =(I14*K14)+N14 -> 0
A15: =IF(F15<>"",1+MAX($A$2:A14),"") | D15: SUBTOTAL | Q15: =SUM(Q8:Q14) -> 184000
A16: =IF(F16<>"",1+MAX($A$2:A15),"")
A17: =IF(F17<>"",1+MAX($A$2:A16),"") | C17: 26 | D17: DIVISION 26- ELECTRICAL
A18: =IF(F18<>"",1+MAX($A$2:A17),"") | D18: DISTRIBUTION
A19: =IF(F19<>"",1+MAX($A$2:A18),"") | D19: FEEDERS
A20: =IF(F20<>"",1+MAX($A$2:A19),"") | D20: CONDUITS
A21: =IF(F21<>"",1+MAX($A$2:A20),"") -> 8 | D21: 4"C EMT | E21: 169.8 | F21: 0.05 | G21: =(F21*E21)+E21 -> 178.29 | H21: LF | I21: 0.146 | J21: =+I21*G21 -> 26.03034 | K21: ='LABOR SHEET'!C$3 -> 128 | L21: =I21*K21 -> 18.688 | M21: =K21*J21 -> 3331.8835 | N21: =138.78/10+1 -> 14.878 | O21: =N21*G21 -> 2652.5986 | P21: =(I21*K21)+N21 -> 33.566 | Q21: =P21*G21 -> 5984.4821
A22: =IF(F22<>"",1+MAX($A$2:A21),"") -> 9 | D22: 4"C PVC | E22: 3840.06 | F22: 0.05 | G22: =(F22*E22)+E22 -> 4032.063 | H22: LF | I22: 0.115 | J22: =+I22*G22 -> 463.68725 | K22: ='LABOR SHEET'!C$3 -> 128 | L22: =I22*K22 -> 14.72 | M22: =K22*J22 -> 59351.967 | N22: 9.27 | O22: =N22*G22 -> 37377.224 | P22: =(I22*K22)+N22 -> 23.99 | Q22: =P22*G22 -> 96729.191
A23: =IF(F23<>"",1+MAX($A$2:A22),"") -> 10 | D23: 3"C EMT | E23: 1079.76 | F23: 0.05 | G23: =(F23*E23)+E23 -> 1133.748 | H23: LF | I23: 0.138 | J23: =+I23*G23 -> 156.45722 | K23: ='LABOR SHEET'!C$3 -> 128 | L23: =I23*K23 -> 17.664 | M23: =K23*J23 -> 20026.525 | N23: =103.68/10+0.85 -> 11.218 | O23: =N23*G23 -> 12718.385 | P23: =(I23*K23)+N23 -> 28.882 | Q23: =P23*G23 -> 32744.91
A24: =IF(F24<>"",1+MAX($A$2:A23),"") -> 11 | D24: 2"C EMT | E24: 234.75 | F24: 0.05 | G24: =(F24*E24)+E24 -> 246.4875 | H24: LF | I24: 0.11 | J24: =+I24*G24 -> 27.113625 | K24: ='LABOR SHEET'!C$3 -> 128 | L24: =I24*K24 -> 14.08 | M24: =K24*J24 -> 3470.544 | N24: =40.48/10+0.55 -> 4.598 | O24: =N24*G24 -> 1133.3495 | P24: =(I24*K24)+N24 -> 18.678 | Q24: =P24*G24 -> 4603.8935
A25: =IF(F25<>"",1+MAX($A$2:A24),"") -> 12 | D25: 1 1/2"C EMT | E25: 601.29 | F25: 0.05 | G25: =(F25*E25)+E25 -> 631.3545 | H25: LF | I25: 0.1 | J25: =+I25*G25 -> 63.13545 | K25: ='LABOR SHEET'!C$3 -> 128 | L25: =I25*K25 -> 12.8 | M25: =K25*J25 -> 8081.3376 | N25: =34/10+0.35 -> 3.75 | O25: =N25*G25 -> 2367.5794 | P25: =(I25*K25)+N25 -> 16.55 | Q25: =P25*G25 -> 10448.917
A26: =IF(F26<>"",1+MAX($A$2:A25),"") -> 13 | D26: PULLSTRING | E26: 3357.45 | F26: 0.05 | G26: =(F26*E26)+E26 -> 3525.3225 | H26: LF | I26: 0.01 | J26: =+I26*G26 -> 35.253225 | K26: ='LABOR SHEET'!C$3 -> 128 | L26: =I26*K26 -> 1.28 | M26: =K26*J26 -> 4512.4128 | N26: 0.35 | O26: =N26*G26 -> 1233.8629 | P26: =(I26*K26)+N26 -> 1.63 | Q26: =P26*G26 -> 5746.2757
A27: =IF(F27<>"",1+MAX($A$2:A26),"")
A28: =IF(F28<>"",1+MAX($A$2:A27),"") | D28: CONDUTORS
A29: =IF(F29<>"",1+MAX($A$2:A28),"") -> 14 | D29: #600 THHN | E29: 3548.64 | F29: 0.05 | G29: =(F29*E29)+E29 -> 3726.072 | H29: LF | I29: 0.1 | J29: =+I29*G29 -> 372.6072 | K29: ='LABOR SHEET'!C$3 -> 128 | L29: =I29*K29 -> 12.8 | M29: =K29*J29 -> 47693.722 | N29: 22.57 | O29: =N29*G29 -> 84097.445 | P29: =(I29*K29)+N29 -> 35.37 | Q29: =P29*G29 -> 131791.17
A30: =IF(F30<>"",1+MAX($A$2:A29),"") -> 15 | D30: #350 THHN | E30: 4319.04 | F30: 0.05 | G30: =(F30*E30)+E30 -> 4534.992 | H30: LF | I30: 0.07 | J30: =+I30*G30 -> 317.44944 | K30: ='LABOR SHEET'!C$3 -> 128 | L30: =I30*K30 -> 8.96 | M30: =K30*J30 -> 40633.528 | N30: 13.24 | O30: =N30*G30 -> 60043.294 | P30: =(I30*K30)+N30 -> 22.2 | Q30: =P30*G30 -> 100676.82
A31: =IF(F31<>"",1+MAX($A$2:A30),"") -> 16 | D31: #4/0 THHN | E31: 451.56 | F31: 0.05 | G31: =(F31*E31)+E31 -> 474.138 | H31: LF | I31: 0.066 | J31: =+I31*G31 -> 31.293108 | K31: ='LABOR SHEET'!C$3 -> 128 | L31: =I31*K31 -> 8.448 | M31: =K31*J31 -> 4005.5178 | N31: 7.78 | O31: =N31*G31 -> 3688.7936 | P31: =(I31*K31)+N31 -> 16.228 | Q31: =P31*G31 -> 7694.3115
A32: =IF(F32<>"",1+MAX($A$2:A31),"") -> 17 | D32: #3/0 THHN | E32: 1079.76 | F32: 0.05 | G32: =(F32*E32)+E32 -> 1133.748 | H32: LF | I32: 0.06 | J32: =+I32*G32 -> 68.02488 | K32: ='LABOR SHEET'!C$3 -> 128 | L32: =I32*K32 -> 7.68 | M32: =K32*J32 -> 8707.1846 | N32: 6.33 | O32: =N32*G32 -> 7176.6248 | P32: =(I32*K32)+N32 -> 14.01 | Q32: =P32*G32 -> 15883.809
A33: =IF(F33<>"",1+MAX($A$2:A32),"") -> 18 | D33: #2 THHN | E33: 2523.72 | F33: 0.05 | G33: =(F33*E33)+E33 -> 2649.906 | H33: LF | I33: 0.025 | J33: =+I33*G33 -> 66.24765 | K33: ='LABOR SHEET'!C$3 -> 128 | L33: =I33*K33 -> 3.2 | M33: =K33*J33 -> 8479.6992 | N33: 2.97 | O33: =N33*G33 -> 7870.2208 | P33: =(I33*K33)+N33 -> 6.17 | Q33: =P33*G33 -> 16349.92
A34: =IF(F34<>"",1+MAX($A$2:A33),"") -> 19 | D34: #8 THHN | E34: 601.29 | F34: 0.05 | G34: =(F34*E34)+E34 -> 631.3545 | H34: LF | I34: 0.012 | J34: =+I34*G34 -> 7.576254 | K34: ='LABOR SHEET'!C$3 -> 128 | L34: =I34*K34 -> 1.536 | M34: =K34*J34 -> 969.76051 | N34: 0.82 | O34: =N34*G34 -> 517.71069 | P34: =(I34*K34)+N34 -> 2.356 | Q34: =P34*G34 -> 1487.4712
A35: =IF(F35<>"",1+MAX($A$2:A34),"")
A36: =IF(F36<>"",1+MAX($A$2:A35),"") | D36: GROUNDING
A37: =IF(F37<>"",1+MAX($A$2:A36),"") -> 20 | D37: #3/0 CU GROUND WIRE | E37: 40 | F37: 0 | G37: =(F37*E37)+E37 -> 40 | H37: LF | I37: 0.03 | J37: =+I37*G37 -> 1.2 | K37: ='LABOR SHEET'!C$3 -> 128 | L37: =I37*K37 -> 3.84 | M37: =K37*J37 -> 153.6 | N37: 5.54 | O37: =N37*G37 -> 221.6 | P37: =(I37*K37)+N37 -> 9.38 | Q37: =P37*G37 -> 375.2
A38: =IF(F38<>"",1+MAX($A$2:A37),"") -> 21 | D38: #6 CU GROUND WIRE | E38: 100 | F38: 0 | G38: =(F38*E38)+E38 -> 100 | H38: LF | I38: 0.015 | J38: =+I38*G38 -> 1.5 | K38: ='LABOR SHEET'!C$3 -> 128 | L38: =I38*K38 -> 1.92 | M38: =K38*J38 -> 192 | N38: 1.05 | O38: =N38*G38 -> 105 | P38: =(I38*K38)+N38 -> 2.97 | Q38: =P38*G38 -> 297
A39: =IF(F39<>"",1+MAX($A$2:A38),"") -> 22 | D39: 5/8"X10' GROUND ROD | E39: 10 | F39: 0.05 | G39: =(F39*E39)+E39 -> 10.5 | H39: EA | I39: 0.6 | J39: =+I39*G39 -> 6.3 | K39: ='LABOR SHEET'!C$3 -> 128 | L39: =I39*K39 -> 76.8 | M39: =K39*J39 -> 806.4 | N39: 49.99 | O39: =N39*G39 -> 524.895 | P39: =(I39*K39)+N39 -> 126.79 | Q39: =P39*G39 -> 1331.295
A40: =IF(F40<>"",1+MAX($A$2:A39),"") -> 23 | D40: EXOTHERMIC WELD | E40: 12 | F40: 0.05 | G40: =(F40*E40)+E40 -> 12.6 | H40: EA | I40: 0.25 | J40: =+I40*G40 -> 3.15 | K40: ='LABOR SHEET'!C$3 -> 128 | L40: =I40*K40 -> 32 | M40: =K40*J40 -> 403.2 | N40: 18 | O40: =N40*G40 -> 226.8 | P40: =(I40*K40)+N40 -> 50 | Q40: =P40*G40 -> 630
A41: =IF(F41<>"",1+MAX($A$2:A40),"") -> 24 | D41: GROUND BUS BAR | E41: 2 | F41: 0.05 | G41: =(F41*E41)+E41 -> 2.1 | H41: EA | I41: 1.22 | J41: =+I41*G41 -> 2.562 | K41: ='LABOR SHEET'!C$3 -> 128 | L41: =I41*K41 -> 156.16 | M41: =K41*J41 -> 327.936 | N41: 225 | O41: =N41*G41 -> 472.5 | P41: =(I41*K41)+N41 -> 381.16 | Q41: =P41*G41 -> 800.436
A42: =IF(F42<>"",1+MAX($A$2:A41),"")
A43: =IF(F43<>"",1+MAX($A$2:A42),"") | D43: DISCONNECT SWITCHES
A44: =IF(F44<>"",1+MAX($A$2:A43),"") -> 25 | D44: 60A/3P DISCONNECT SWITCH NEMA 1 | E44: 2 | F44: 0 | G44: =(F44*E44)+E44 -> 2 | H44: EA | I44: 2 | J44: =+I44*G44 -> 4 | K44: ='LABOR SHEET'!C$3 -> 128 | L44: =I44*K44 -> 256 | M44: =K44*J44 -> 512 | N44: 326 | O44: =N44*G44 -> 652 | P44: =(I44*K44)+N44 -> 582 | Q44: =P44*G44 -> 1164
A45: =IF(F45<>"",1+MAX($A$2:A44),"") -> 26 | D45: 100A/3P DISCONNECT SWITCH NEMA 3R | E45: 2 | F45: 0 | G45: =(F45*E45)+E45 -> 2 | H45: EA | I45: 3.5 | J45: =+I45*G45 -> 7 | K45: ='LABOR SHEET'!C$3 -> 128 | L45: =I45*K45 -> 448 | M45: =K45*J45 -> 896 | N45: 599.17 | O45: =N45*G45 -> 1198.34 | P45: =(I45*K45)+N45 -> 1047.17 | Q45: =P45*G45 -> 2094.34
A46: =IF(F46<>"",1+MAX($A$2:A45),"")
A47: =IF(F47<>"",1+MAX($A$2:A46),"") | D47: CIRCUIT BREAKERS
A48: =IF(F48<>"",1+MAX($A$2:A47),"") -> 27 | D48: 20A/1P CIRCUIT BREAKER | E48: 196 | F48: 0 | G48: =(F48*E48)+E48 -> 196 | H48: EA | I48: 0.25 | J48: =+I48*G48 -> 49 | K48: ='LABOR SHEET'!C$3 -> 128 | L48: =I48*K48 -> 32 | M48: =K48*J48 -> 6272 | N48: 16.98 | O48: =N48*G48 -> 3328.08 | P48: =(I48*K48)+N48 -> 48.98 | Q48: =P48*G48 -> 9600.08
A49: =IF(F49<>"",1+MAX($A$2:A48),"") -> 28 | D49: 20A/2P CIRCUIT BREAKER | E49: 8 | F49: 0 | G49: =(F49*E49)+E49 -> 8 | H49: EA | I49: 0.4 | J49: =+I49*G49 -> 3.2 | K49: ='LABOR SHEET'!C$3 -> 128 | L49: =I49*K49 -> 51.2 | M49: =K49*J49 -> 409.6 | N49: 22.4 | O49: =N49*G49 -> 179.2 | P49: =(I49*K49)+N49 -> 73.6 | Q49: =P49*G49 -> 588.8
A50: =IF(F50<>"",1+MAX($A$2:A49),"") -> 29 | D50: 30A/2P CIRCUIT BREAKER | E50: 16 | F50: 0 | G50: =(F50*E50)+E50 -> 16 | H50: EA | I50: 0.4 | J50: =+I50*G50 -> 6.4 | K50: ='LABOR SHEET'!C$3 -> 128 | L50: =I50*K50 -> 51.2 | M50: =K50*J50 -> 819.2 | N50: 28.5 | O50: =N50*G50 -> 456 | P50: =(I50*K50)+N50 -> 79.7 | Q50: =P50*G50 -> 1275.2
A51: =IF(F51<>"",1+MAX($A$2:A50),"") -> 30 | D51: 30A/3P CIRCUIT BREAKER | E51: 11 | F51: 0 | G51: =(F51*E51)+E51 -> 11 | H51: EA | I51: 0.5 | J51: =+I51*G51 -> 5.5 | K51: ='LABOR SHEET'!C$3 -> 128 | L51: =I51*K51 -> 64 | M51: =K51*J51 -> 704 | N51: =3.44*30 -> 103.2 | O51: =N51*G51 -> 1135.2 | P51: =(I51*K51)+N51 -> 167.2 | Q51: =P51*G51 -> 1839.2
A52: =IF(F52<>"",1+MAX($A$2:A51),"") -> 31 | D52: 40A/2P CIRCUIT BREAKER | E52: 4 | F52: 0 | G52: =(F52*E52)+E52 -> 4 | H52: EA | I52: 0.4 | J52: =+I52*G52 -> 1.6 | K52: ='LABOR SHEET'!C$3 -> 128 | L52: =I52*K52 -> 51.2 | M52: =K52*J52 -> 204.8 | N52: 36.63 | O52: =N52*G52 -> 146.52 | P52: =(I52*K52)+N52 -> 87.83 | Q52: =P52*G52 -> 351.32
A53: =IF(F53<>"",1+MAX($A$2:A52),"") -> 32 | D53: 40A/3P CIRCUIT BREAKER | E53: 1 | F53: 0 | G53: =(F53*E53)+E53 -> 1 | H53: EA | I53: 0.5 | J53: =+I53*G53 -> 0.5 | K53: ='LABOR SHEET'!C$3 -> 128 | L53: =I53*K53 -> 64 | M53: =K53*J53 -> 64 | N53: =3.44*40 -> 137.6 | O53: =N53*G53 -> 137.6 | P53: =(I53*K53)+N53 -> 201.6 | Q53: =P53*G53 -> 201.6
A54: =IF(F54<>"",1+MAX($A$2:A53),"") -> 33 | D54: 50A/2P CIRCUIT BREAKER | E54: 1 | F54: 0 | G54: =(F54*E54)+E54 -> 1 | H54: EA | I54: 0.4 | J54: =+I54*G54 -> 0.4 | K54: ='LABOR SHEET'!C$3 -> 128 | L54: =I54*K54 -> 51.2 | M54: =K54*J54 -> 51.2 | N54: 55 | O54: =N54*G54 -> 55 | P54: =(I54*K54)+N54 -> 106.2 | Q54: =P54*G54 -> 106.2
A55: =IF(F55<>"",1+MAX($A$2:A54),"") -> 34 | D55: 50A/3P CIRCUIT BREAKER | E55: 2 | F55: 0 | G55: =(F55*E55)+E55 -> 2 | H55: EA | I55: 0.55 | J55: =+I55*G55 -> 1.1 | K55: ='LABOR SHEET'!C$3 -> 128 | L55: =I55*K55 -> 70.4 | M55: =K55*J55 -> 140.8 | N55: =3.44*50 -> 172 | O55: =N55*G55 -> 344 | P55: =(I55*K55)+N55 -> 242.4 | Q55: =P55*G55 -> 484.8
A56: =IF(F56<>"",1+MAX($A$2:A55),"") -> 35 | D56: 60A/3P CIRCUIT BREAKER | E56: 1 | F56: 0 | G56: =(F56*E56)+E56 -> 1 | H56: EA | I56: 0.55 | J56: =+I56*G56 -> 0.55 | K56: ='LABOR SHEET'!C$3 -> 128 | L56: =I56*K56 -> 70.4 | M56: =K56*J56 -> 70.4 | N56: =3.44*60 -> 206.4 | O56: =N56*G56 -> 206.4 | P56: =(I56*K56)+N56 -> 276.8 | Q56: =P56*G56 -> 276.8
A57: =IF(F57<>"",1+MAX($A$2:A56),"") -> 36 | D57: 80A/3P CIRCUIT BREAKER | E57: 1 | F57: 0 | G57: =(F57*E57)+E57 -> 1 | H57: EA | I57: 0.6 | J57: =+I57*G57 -> 0.6 | K57: ='LABOR SHEET'!C$3 -> 128 | L57: =I57*K57 -> 76.8 | M57: =K57*J57 -> 76.8 | N57: =3.44*80 -> 275.2 | O57: =N57*G57 -> 275.2 | P57: =(I57*K57)+N57 -> 352 | Q57: =P57*G57 -> 352
A58: =IF(F58<>"",1+MAX($A$2:A57),"") -> 37 | D58: 90A/3P CIRCUIT BREAKER | E58: 1 | F58: 0 | G58: =(F58*E58)+E58 -> 1 | H58: EA | I58: 0.7 | J58: =+I58*G58 -> 0.7 | K58: ='LABOR SHEET'!C$3 -> 128 | L58: =I58*K58 -> 89.6 | M58: =K58*J58 -> 89.6 | N58: =3.44*90 -> 309.6 | O58: =N58*G58 -> 309.6 | P58: =(I58*K58)+N58 -> 399.2 | Q58: =P58*G58 -> 399.2
A59: =IF(F59<>"",1+MAX($A$2:A58),"") -> 38 | D59: 100A MAIN CIRCUIT BREAKER | E59: 4 | F59: 0 | G59: =(F59*E59)+E59 -> 4 | H59: EA | I59: 1 | J59: =+I59*G59 -> 4 | K59: ='LABOR SHEET'!C$3 -> 128 | L59: =I59*K59 -> 128 | M59: =K59*J59 -> 512 | N59: 344.8 | O59: =N59*G59 -> 1379.2 | P59: =(I59*K59)+N59 -> 472.8 | Q59: =P59*G59 -> 1891.2
A60: =IF(F60<>"",1+MAX($A$2:A59),"") -> 39 | D60: 100A/3P CIRCUIT BREAKER | E60: 12 | F60: 0 | G60: =(F60*E60)+E60 -> 12 | H60: EA | I60: 1 | J60: =+I60*G60 -> 12 | K60: ='LABOR SHEET'!C$3 -> 128 | L60: =I60*K60 -> 128 | M60: =K60*J60 -> 1536 | N60: 344.8 | O60: =N60*G60 -> 4137.6 | P60: =(I60*K60)+N60 -> 472.8 | Q60: =P60*G60 -> 5673.6
A61: =IF(F61<>"",1+MAX($A$2:A60),"") -> 40 | D61: 400A MAIN CIRCUIT BREAKER | E61: 4 | F61: 0 | G61: =(F61*E61)+E61 -> 4 | H61: EA | I61: 2.85 | J61: =+I61*G61 -> 11.4 | K61: ='LABOR SHEET'!C$3 -> 128 | L61: =I61*K61 -> 364.8 | M61: =K61*J61 -> 1459.2 | N61: 1726.92 | O61: =N61*G61 -> 6907.68 | P61: =(I61*K61)+N61 -> 2091.72 | Q61: =P61*G61 -> 8366.88
A62: =IF(F62<>"",1+MAX($A$2:A61),"") -> 41 | D62: 400A/3P CIRCUIT BREAKER | E62: 10 | F62: 0 | G62: =(F62*E62)+E62 -> 10 | H62: EA | I62: 2.85 | J62: =+I62*G62 -> 28.5 | K62: ='LABOR SHEET'!C$3 -> 128 | L62: =I62*K62 -> 364.8 | M62: =K62*J62 -> 3648 | N62: 1726.92 | O62: =N62*G62 -> 17269.2 | P62: =(I62*K62)+N62 -> 2091.72 | Q62: =P62*G62 -> 20917.2
A63: =IF(F63<>"",1+MAX($A$2:A62),"") -> 42 | D63: 1200A MAIN CIRCUIT BREAKER | E63: 2 | F63: 0 | G63: =(F63*E63)+E63 -> 2 | H63: EA | I63: 5.5 | J63: =+I63*G63 -> 11 | K63: ='LABOR SHEET'!C$3 -> 128 | L63: =I63*K63 -> 704 | M63: =K63*J63 -> 1408 | N63: 5308.35 | O63: =N63*G63 -> 10616.7 | P63: =(I63*K63)+N63 -> 6012.35 | Q63: =P63*G63 -> 12024.7
A64: =IF(F64<>"",1+MAX($A$2:A63),"") -> 43 | D64: 1200A/3P CIRCUIT BREAKER | E64: 4 | F64: 0 | G64: =(F64*E64)+E64 -> 4 | H64: EA | I64: 5.5 | J64: =+I64*G64 -> 22 | K64: ='LABOR SHEET'!C$3 -> 128 | L64: =I64*K64 -> 704 | M64: =K64*J64 -> 2816 | N64: 5308.35 | O64: =N64*G64 -> 21233.4 | P64: =(I64*K64)+N64 -> 6012.35 | Q64: =P64*G64 -> 24049.4
A65: =IF(F65<>"",1+MAX($A$2:A64),"") -> 44 | D65: 1600A MAIN CIRCUIT BREAKER | E65: 1 | F65: 0 | G65: =(F65*E65)+E65 -> 1 | H65: EA | I65: 6.6 | J65: =+I65*G65 -> 6.6 | K65: ='LABOR SHEET'!C$3 -> 128 | L65: =I65*K65 -> 844.8 | M65: =K65*J65 -> 844.8 | N65: 11600 | O65: =N65*G65 -> 11600 | P65: =(I65*K65)+N65 -> 12444.8 | Q65: =P65*G65 -> 12444.8
A66: =IF(F66<>"",1+MAX($A$2:A65),"") -> 45 | D66: 2500A MAIN CIRCUIT BREAKER | E66: 1 | F66: 0 | G66: =(F66*E66)+E66 -> 1 | H66: EA | I66: 8.5 | J66: =+I66*G66 -> 8.5 | K66: ='LABOR SHEET'!C$3 -> 128 | L66: =I66*K66 -> 1088 | M66: =K66*J66 -> 1088 | N66: 16260.86 | O66: =N66*G66 -> 16260.86 | P66: =(I66*K66)+N66 -> 17348.86 | Q66: =P66*G66 -> 17348.86
A67: =IF(F67<>"",1+MAX($A$2:A66),"")
A68: =IF(F68<>"",1+MAX($A$2:A67),"") | D68: PANELS
A69: =IF(F69<>"",1+MAX($A$2:A68),"") -> 46 | D69: PANEL GSS, 1600A MCB, 208V, 3PH, 4W, 10KAIC, SURFACE MOUNTED, NEMA 1 | E69: 1 | F69: 0 | G69: =(F69*E69)+E69 -> 1 | H69: EA | I69: 40 | J69: =+I69*G69 -> 40 | K69: ='LABOR SHEET'!C$3 -> 128 | L69: =I69*K69 -> 5120 | M69: =K69*J69 -> 5120 | N69: 19440 | O69: =N69*G69 -> 19440 | P69: =(I69*K69)+N69 -> 24560 | Q69: =P69*G69 -> 24560
A70: =IF(F70<>"",1+MAX($A$2:A69),"") -> 47 | D70: PANEL MSS, 2500A MCB, 208V, 3PH, 4W, 65KAIC, SURFACE MOUNTED, NEMA 1 | E70: 1 | F70: 0 | G70: =(F70*E70)+E70 -> 1 | H70: EA | I70: 55 | J70: =+I70*G70 -> 55 | K70: ='LABOR SHEET'!C$3 -> 128 | L70: =I70*K70 -> 7040 | M70: =K70*J70 -> 7040 | N70: 35280 | O70: =N70*G70 -> 35280 | P70: =(I70*K70)+N70 -> 42320 | Q70: =P70*G70 -> 42320
A71: =IF(F71<>"",1+MAX($A$2:A70),"") -> 48 | D71: PANEL SL1, 1200A MCB, 208V, 3PH, 4W, 65KAIC, SURFACE MOUNTED, NEMA 1 | E71: 1 | F71: 0 | G71: =(F71*E71)+E71 -> 1 | H71: EA | I71: 35 | J71: =+I71*G71 -> 35 | K71: ='LABOR SHEET'!C$3 -> 128 | L71: =I71*K71 -> 4480 | M71: =K71*J71 -> 4480 | N71: 12600.45 | O71: =N71*G71 -> 12600.45 | P71: =(I71*K71)+N71 -> 17080.45 | Q71: =P71*G71 -> 17080.45
A72: =IF(F72<>"",1+MAX($A$2:A71),"") -> 49 | D72: PANEL SL2, 400A MCB, 208V, 3PH, 4W, 65KAIC, SURFACE MOUNTED, NEMA 1 | E72: 1 | F72: 0 | G72: =(F72*E72)+E72 -> 1 | H72: EA | I72: 15 | J72: =+I72*G72 -> 15 | K72: ='LABOR SHEET'!C$3 -> 128 | L72: =I72*K72 -> 1920 | M72: =K72*J72 -> 1920 | N72: 5630.7 | O72: =N72*G72 -> 5630.7 | P72: =(I72*K72)+N72 -> 7550.7 | Q72: =P72*G72 -> 7550.7
A73: =IF(F73<>"",1+MAX($A$2:A72),"") -> 50 | D73: PANEL SL3, 400A MCB, 208V, 3PH, 4W, 65KAIC, SURFACE MOUNTED, NEMA 1 | E73: 1 | F73: 0 | G73: =(F73*E73)+E73 -> 1 | H73: EA | I73: 15 | J73: =+I73*G73 -> 15 | K73: ='LABOR SHEET'!C$3 -> 128 | L73: =I73*K73 -> 1920 | M73: =K73*J73 -> 1920 | N73: 5630.7 | O73: =N73*G73 -> 5630.7 | P73: =(I73*K73)+N73 -> 7550.7 | Q73: =P73*G73 -> 7550.7
A74: =IF(F74<>"",1+MAX($A$2:A73),"") -> 51 | D74: PANEL SL4, 400A MCB, 208V, 3PH, 4W, 65KAIC, SURFACE MOUNTED, NEMA 1 | E74: 1 | F74: 0 | G74: =(F74*E74)+E74 -> 1 | H74: EA | I74: 15 | J74: =+I74*G74 -> 15 | K74: ='LABOR SHEET'!C$3 -> 128 | L74: =I74*K74 -> 1920 | M74: =K74*J74 -> 1920 | N74: 5630.7 | O74: =N74*G74 -> 5630.7 | P74: =(I74*K74)+N74 -> 7550.7 | Q74: =P74*G74 -> 7550.7
A75: =IF(F75<>"",1+MAX($A$2:A74),"") -> 52 | D75: PANEL UPSA, 100A MCB, 208V, 3PH, 4W, 10KAIC, SURFACE MOUNTED, NEMA 1 | E75: 1 | F75: 0 | G75: =(F75*E75)+E75 -> 1 | H75: EA | I75: 8.5 | J75: =+I75*G75 -> 8.5 | K75: ='LABOR SHEET'!C$3 -> 128 | L75: =I75*K75 -> 1088 | M75: =K75*J75 -> 1088 | N75: 1076.44 | O75: =N75*G75 -> 1076.44 | P75: =(I75*K75)+N75 -> 2164.44 | Q75: =P75*G75 -> 2164.44
A76: =IF(F76<>"",1+MAX($A$2:A75),"") -> 53 | D76: PANEL UPSB, 100A MCB, 208V, 3PH, 4W, 10KAIC, SURFACE MOUNTED, NEMA 1 | E76: 1 | F76: 0 | G76: =(F76*E76)+E76 -> 1 | H76: EA | I76: 8.5 | J76: =+I76*G76 -> 8.5 | K76: ='LABOR SHEET'!C$3 -> 128 | L76: =I76*K76 -> 1088 | M76: =K76*J76 -> 1088 | N76: 1076.44 | O76: =N76*G76 -> 1076.44 | P76: =(I76*K76)+N76 -> 2164.44 | Q76: =P76*G76 -> 2164.44
A77: =IF(F77<>"",1+MAX($A$2:A76),"") -> 54 | D77: PANEL XL1, 1200A MCB, 208V, 3PH, 4W, 65KAIC, SURFACE MOUNTED, NEMA 1 | E77: 1 | F77: 0 | G77: =(F77*E77)+E77 -> 1 | H77: EA | I77: 35 | J77: =+I77*G77 -> 35 | K77: ='LABOR SHEET'!C$3 -> 128 | L77: =I77*K77 -> 4480 | M77: =K77*J77 -> 4480 | N77: 12600.45 | O77: =N77*G77 -> 12600.45 | P77: =(I77*K77)+N77 -> 17080.45 | Q77: =P77*G77 -> 17080.45
A78: =IF(F78<>"",1+MAX($A$2:A77),"") -> 55 | D78: PANEL XL2, 400A MCB, 208V, 3PH, 4W, 65KAIC, SURFACE MOUNTED, NEMA 1 | E78: 1 | F78: 0 | G78: =(F78*E78)+E78 -> 1 | H78: EA | I78: 15 | J78: =+I78*G78 -> 15 | K78: ='LABOR SHEET'!C$3 -> 128 | L78: =I78*K78 -> 1920 | M78: =K78*J78 -> 1920 | N78: 5630.7 | O78: =N78*G78 -> 5630.7 | P78: =(I78*K78)+N78 -> 7550.7 | Q78: =P78*G78 -> 7550.7
A79: =IF(F79<>"",1+MAX($A$2:A78),"") -> 56 | D79: PANEL XL3, 400A MCB, 208V, 3PH, 4W, 65KAIC, SURFACE MOUNTED, NEMA 1 | E79: 1 | F79: 0 | G79: =(F79*E79)+E79 -> 1 | H79: EA | I79: 15 | J79: =+I79*G79 -> 15 | K79: ='LABOR SHEET'!C$3 -> 128 | L79: =I79*K79 -> 1920 | M79: =K79*J79 -> 1920 | N79: 5630.7 | O79: =N79*G79 -> 5630.7 | P79: =(I79*K79)+N79 -> 7550.7 | Q79: =P79*G79 -> 7550.7
A80: =IF(F80<>"",1+MAX($A$2:A79),"") -> 57 | D80: PANEL XL4, 100A MCB, 208V, 3PH, 4W, 10KAIC, SURFACE MOUNTED, NEMA 1 | E80: 1 | F80: 0 | G80: =(F80*E80)+E80 -> 1 | H80: EA | I80: 8.5 | J80: =+I80*G80 -> 8.5 | K80: ='LABOR SHEET'!C$3 -> 128 | L80: =I80*K80 -> 1088 | M80: =K80*J80 -> 1088 | N80: 1076.44 | O80: =N80*G80 -> 1076.44 | P80: =(I80*K80)+N80 -> 2164.44 | Q80: =P80*G80 -> 2164.44
A81: =IF(F81<>"",1+MAX($A$2:A80),"") -> 58 | D81: PANEL XL5, 100A MCB, 208V, 3PH, 4W, 10KAIC, SURFACE MOUNTED, NEMA 1 | E81: 1 | F81: 0 | G81: =(F81*E81)+E81 -> 1 | H81: EA | I81: 8.5 | J81: =+I81*G81 -> 8.5 | K81: ='LABOR SHEET'!C$3 -> 128 | L81: =I81*K81 -> 1088 | M81: =K81*J81 -> 1088 | N81: 1076.44 | O81: =N81*G81 -> 1076.44 | P81: =(I81*K81)+N81 -> 2164.44 | Q81: =P81*G81 -> 2164.44
A82: =IF(F82<>"",1+MAX($A$2:A81),"")
A83: =IF(F83<>"",1+MAX($A$2:A82),"") | D83: EQUIPMENTS
A84: =IF(F84<>"",1+MAX($A$2:A83),"") -> 59 | D84: ATS-S, AUTO TRANSFER SWITCH, 1200A-4P, NEMA 1 | E84: 1 | F84: 0 | G84: =(F84*E84)+E84 -> 1 | H84: EA | I84: 10 | J84: =+I84*G84 -> 10 | K84: ='LABOR SHEET'!C$3 -> 128 | L84: =I84*K84 -> 1280 | M84: =K84*J84 -> 1280 | N84: 15408 | O84: =N84*G84 -> 15408 | P84: =(I84*K84)+N84 -> 16688 | Q84: =P84*G84 -> 16688
A85: =IF(F85<>"",1+MAX($A$2:A84),"") -> 60 | D85: ATS-X, AUTO TRANSFER SWITCH, 1200A-4P, NEMA 1 | E85: 1 | F85: 0 | G85: =(F85*E85)+E85 -> 1 | H85: EA | I85: 10 | J85: =+I85*G85 -> 10 | K85: ='LABOR SHEET'!C$3 -> 128 | L85: =I85*K85 -> 1280 | M85: =K85*J85 -> 1280 | N85: 15408 | O85: =N85*G85 -> 15408 | P85: =(I85*K85)+N85 -> 16688 | Q85: =P85*G85 -> 16688
A86: =IF(F86<>"",1+MAX($A$2:A85),"") -> 61 | D86: DUAL EV CHARGING STATION (DEV) (2) EATON GMEV48CMC1-WC SERIES HARGING STATION MOUNTED TO EATON GMEV-DPED SERIES DUAL PORT PEDESTAL | E86: 2 | F86: 0 | G86: =(F86*E86)+E86 -> 2 | H86: EA | I86: 20 | J86: =+I86*G86 -> 40 | K86: ='LABOR SHEET'!C$3 -> 128 | L86: =I86*K86 -> 2560 | M86: =K86*J86 -> 5120 | N86: =3656.86+1992 -> 5648.86 | O86: =N86*G86 -> 11297.72 | P86: =(I86*K86)+N86 -> 8208.86 | Q86: =P86*G86 -> 16417.72
A87: =IF(F87<>"",1+MAX($A$2:A86),"") -> 62 | D87: EATON 93PM SERIES UPS OR EQUAL WITH MAINTENANCE BYPASS CABINET (MBCh REMOTE MONITORING, AND 15-MINUTE BATTERY RUNTIME | E87: 2 | F87: 0 | G87: =(F87*E87)+E87 -> 2 | H87: EA | I87: 100 | J87: =+I87*G87 -> 200 | K87: ='LABOR SHEET'!C$3 -> 128 | L87: =I87*K87 -> 12800 | M87: =K87*J87 -> 25600 | N87: =21784.99+49903+4252.99 -> 75940.98 | O87: =N87*G87 -> 151881.96 | P87: =(I87*K87)+N87 -> 88740.98 | Q87: =P87*G87 -> 177481.96
A88: =IF(F88<>"",1+MAX($A$2:A87),"") -> 63 | D88: EATON CHARGING NETWORK MANAGEMENT (CNM) SOFTWARE PLATFORM | E88: 2 | F88: 0 | G88: =(F88*E88)+E88 -> 2 | H88: EA | I88: 10 | J88: =+I88*G88 -> 20 | K88: ='LABOR SHEET'!C$3 -> 128 | L88: =I88*K88 -> 1280 | M88: =K88*J88 -> 2560 | N88: 3496.3 | O88: =N88*G88 -> 6992.6 | P88: =(I88*K88)+N88 -> 4776.3 | Q88: =P88*G88 -> 9552.6
A89: =IF(F89<>"",1+MAX($A$2:A88),"") -> 64 | D89: ENERGY METERING CONTROL PANEL | E89: 1 | F89: 0 | G89: =(F89*E89)+E89 -> 1 | H89: EA | I89: 10 | J89: =+I89*G89 -> 10 | K89: ='LABOR SHEET'!C$3 -> 128 | L89: =I89*K89 -> 1280 | M89: =K89*J89 -> 1280 | N89: 2550 | O89: =N89*G89 -> 2550 | P89: =(I89*K89)+N89 -> 3830 | Q89: =P89*G89 -> 3830
A90: =IF(F90<>"",1+MAX($A$2:A89),"") -> 65 | D90: GENERATOR, 400KW/500KVA PAD MOUNTED, NEMA 3R WITH (1) 1600A/3P CIRCUIT BREAKER | E90: 1 | F90: 0 | G90: =(F90*E90)+E90 -> 1 | H90: EA | I90: =(110)+(6.6*1) -> 116.6 | J90: =+I90*G90 -> 116.6 | K90: ='LABOR SHEET'!C$3 -> 128 | L90: =I90*K90 -> 14924.8 | M90: =K90*J90 -> 14924.8 | N90: =(86981.59)+(11600*1) -> 98581.59 | O90: =N90*G90 -> 98581.59 | P90: =(I90*K90)+N90 -> 113506.39 | Q90: =P90*G90 -> 113506.39
A91: =IF(F91<>"",1+MAX($A$2:A90),"") -> 66 | D91: MTS, MANUAL TRANSFER SWITCH, 1600A/3P, 208Y/120V, NEMA 3R | E91: 1 | F91: 0 | G91: =(F91*E91)+E91 -> 1 | H91: EA | I91: 8.5 | J91: =+I91*G91 -> 8.5 | K91: ='LABOR SHEET'!C$3 -> 128 | L91: =I91*K91 -> 1088 | M91: =K91*J91 -> 1088 | N91: 6444.9 | O91: =N91*G91 -> 6444.9 | P91: =(I91*K91)+N91 -> 7532.9 | Q91: =P91*G91 -> 7532.9
A92: =IF(F92<>"",1+MAX($A$2:A91),"") -> 67 | D92: SPD, SURGE PROTECTIVE DEVICE | E92: 10 | F92: 0 | G92: =(F92*E92)+E92 -> 10 | H92: EA | I92: 1.5 | J92: =+I92*G92 -> 15 | K92: ='LABOR SHEET'!C$3 -> 128 | L92: =I92*K92 -> 192 | M92: =K92*J92 -> 1920 | N92: 738.89 | O92: =N92*G92 -> 7388.9 | P92: =(I92*K92)+N92 -> 930.89 | Q92: =P92*G92 -> 9308.9
A93: =IF(F93<>"",1+MAX($A$2:A92),"") -> 68 | D93: SUPER CRITICAL GRADE SOUND ATTENUATED ACOUSTICAL ENCLOSURE WITH 24-HOUR SKID MOUNT DIESEL FUEL TANK | E93: 1 | F93: 0 | G93: =(F93*E93)+E93 -> 1 | H93: EA | I93: 60 | J93: =+I93*G93 -> 60 | K93: ='LABOR SHEET'!C$3 -> 128 | L93: =I93*K93 -> 7680 | M93: =K93*J93 -> 7680 | N93: 30000 | O93: =N93*G93 -> 30000 | P93: =(I93*K93)+N93 -> 37680 | Q93: =P93*G93 -> 37680
A94: =IF(F94<>"",1+MAX($A$2:A93),"") -> 69 | D94: UTILITY PRODUCTION METER (BY UTILITY) | E94: 1 | F94: 0 | G94: =(F94*E94)+E94 -> 1 | H94: EA | I94: 5 | J94: =+I94*G94 -> 5 | K94: ='LABOR SHEET'!C$3 -> 128 | L94: =I94*K94 -> 640 | M94: =K94*J94 -> 640 | N94: 0 | O94: =N94*G94 -> 0 | P94: =(I94*K94)+N94 -> 640 | Q94: =P94*G94 -> 640
A95: =IF(F95<>"",1+MAX($A$2:A94),"")
A96: =IF(F96<>"",1+MAX($A$2:A95),"") | D96: EQUIPMENT CONNECTIONS
A97: =IF(F97<>"",1+MAX($A$2:A96),"") -> 70 | D97: CONNECTION FOR BATTERY CHARGER | E97: 1 | F97: 0 | G97: =(F97*E97)+E97 -> 1 | H97: EA | I97: 0.3 | J97: =+I97*G97 -> 0.3 | K97: ='LABOR SHEET'!C$3 -> 128 | L97: =I97*K97 -> 38.4 | M97: =K97*J97 -> 38.4 | N97: 22 | O97: =N97*G97 -> 22 | P97: =(I97*K97)+N97 -> 60.4 | Q97: =P97*G97 -> 60.4
A98: =IF(F98<>"",1+MAX($A$2:A97),"") -> 71 | D98: CONNECTION FOR BC | E98: 3 | F98: 0 | G98: =(F98*E98)+E98 -> 3 | H98: EA | I98: 0.25 | J98: =+I98*G98 -> 0.75 | K98: ='LABOR SHEET'!C$3 -> 128 | L98: =I98*K98 -> 32 | M98: =K98*J98 -> 96 | N98: 18 | O98: =N98*G98 -> 54 | P98: =(I98*K98)+N98 -> 50 | Q98: =P98*G98 -> 150
A99: =IF(F99<>"",1+MAX($A$2:A98),"") -> 72 | D99: CONNECTION FOR BLOCK HEATER | E99: 1 | F99: 0 | G99: =(F99*E99)+E99 -> 1 | H99: EA | I99: 0.3 | J99: =+I99*G99 -> 0.3 | K99: ='LABOR SHEET'!C$3 -> 128 | L99: =I99*K99 -> 38.4 | M99: =K99*J99 -> 38.4 | N99: 22 | O99: =N99*G99 -> 22 | P99: =(I99*K99)+N99 -> 60.4 | Q99: =P99*G99 -> 60.4
A100: =IF(F100<>"",1+MAX($A$2:A99),"") -> 73 | D100: CONNECTION FOR CARD READER | E100: 2 | F100: 0 | G100: =(F100*E100)+E100 -> 2 | H100: EA | I100: 0.25 | J100: =+I100*G100 -> 0.5 | K100: ='LABOR SHEET'!C$3 -> 128 | L100: =I100*K100 -> 32 | M100: =K100*J100 -> 64 | N100: 18 | O100: =N100*G100 -> 36 | P100: =(I100*K100)+N100 -> 50 | Q100: =P100*G100 -> 100
A101: =IF(F101<>"",1+MAX($A$2:A100),"") -> 74 | D101: CONNECTION FOR CENTURION ALARM | E101: 1 | F101: 0 | G101: =(F101*E101)+E101 -> 1 | H101: EA | I101: 0.3 | J101: =+I101*G101 -> 0.3 | K101: ='LABOR SHEET'!C$3 -> 128 | L101: =I101*K101 -> 38.4 | M101: =K101*J101 -> 38.4 | N101: 22 | O101: =N101*G101 -> 22 | P101: =(I101*K101)+N101 -> 60.4 | Q101: =P101*G101 -> 60.4
...

Sheet Add Alternate
A2: DETAILED BREAKDOWN OF ITEMS
B3: Project Name | D3: Joint Public Safety Facility
B4: Project Address | D4: 2100 w edgewood dr. port angeles, wa 98363
B5: Scope: | D5: Electrical
A6: S# | B6: Dwg. | C6: CSI NO | D6: DESCRIPTION | E6: QTY. | F6: Wastage | G6: Qty w/ Waste | H6: UNIT | I6: UNIT LABOR HOUR | J6: TOTAL LABOR HOUR | K6: LABOR WAGE/ HOUR | L6: UNIT LABOR COST | M6: TOTAL LABOR COST | N6: UNIT MATERIAL COST | O6: TOTAL MATERIAL COST | P6: UNIT PRICE (Labor & Material) | Q6: TRADE TOTAL
C7: 1 | D7: DIVISION 01-GENERAL REQUIREMENTS
A8: =IF(F8<>"",1+MAX($A$2:A7),"") -> 1 | D8: Permits | E8: 1 | F8: 0 | G8: =(F8*E8)+E8 -> 1 | H8: LS | I8: 0 | J8: =+I8*G8 -> 0 | K8: 0 | L8: =I8*K8 -> 0 | M8: =K8*J8 -> 0 | N8: 0 | O8: =N8*G8 -> 0 | P8: =(I8*K8)+N8 -> 0 | Q8: 1500
A9: =IF(F9<>"",1+MAX($A$2:A8),"") -> 2 | D9: Supervision and Coordination | E9: 1 | F9: 0 | G9: =(F9*E9)+E9 -> 1 | H9: LS | I9: 0 | J9: =+I9*G9 -> 0 | K9: 0 | L9: =I9*K9 -> 0 | M9: =K9*J9 -> 0 | N9: 0 | O9: =N9*G9 -> 0 | P9: =(I9*K9)+N9 -> 0
A10: =IF(F10<>"",1+MAX($A$2:A9),"") -> 3 | D10: Submittals and Shop drawings | E10: 1 | F10: 0 | G10: =(F10*E10)+E10 -> 1 | H10: LS | I10: 0 | J10: =+I10*G10 -> 0 | K10: 0 | L10: =I10*K10 -> 0 | M10: =K10*J10 -> 0 | N10: 0 | O10: =N10*G10 -> 0 | P10: =(I10*K10)+N10 -> 0
A11: =IF(F11<>"",1+MAX($A$2:A10),"") -> 4 | D11: Final Cleaning | E11: 1 | F11: 0 | G11: =(F11*E11)+E11 -> 1 | H11: LS | I11: 0 | J11: =+I11*G11 -> 0 | K11: 0 | L11: =I11*K11 -> 0 | M11: =K11*J11 -> 0 | N11: 0 | O11: =N11*G11 -> 0 | P11: =(I11*K11)+N11 -> 0
A12: =IF(F12<>"",1+MAX($A$2:A11),"") -> 5 | D12: Mobilization Costs | E12: 1 | F12: 0 | G12: =(F12*E12)+E12 -> 1 | H12: LS | I12: 0 | J12: =+I12*G12 -> 0 | K12: 0 | L12: =I12*K12 -> 0 | M12: =K12*J12 -> 0 | N12: 0 | O12: =N12*G12 -> 0 | P12: =(I12*K12)+N12 -> 0
A13: =IF(F13<>"",1+MAX($A$2:A12),"") -> 6 | D13: Temporary Control & Facilities | E13: 1 | F13: 0 | G13: =(F13*E13)+E13 -> 1 | H13: LS | I13: 0 | J13: =+I13*G13 -> 0 | K13: 0 | L13: =I13*K13 -> 0 | M13: =K13*J13 -> 0 | N13: 0 | O13: =N13*G13 -> 0 | P13: =(I13*K13)+N13 -> 0
A14: =IF(F14<>"",1+MAX($A$2:A13),"") -> 7 | D14: Scaffolding | E14: 1 | F14: 0 | G14: =(F14*E14)+E14 -> 1 | H14: LS | I14: 0 | J14: =+I14*G14 -> 0 | K14: 0 | L14: =I14*K14 -> 0 | M14: =K14*J14 -> 0 | N14: 0 | O14: =N14*G14 -> 0 | P14: =(I14*K14)+N14 -> 0
A15: =IF(F15<>"",1+MAX($A$2:A14),"") | D15: SUBTOTAL | Q15: =SUM(Q8:Q14) -> 1500
A16: =IF(F16<>"",1+MAX($A$2:A15),"")
A17: =IF(F17<>"",1+MAX($A$2:A16),"") | D17: ADD ALTERNATE (PEDESTRIAN GATE CARD READER)
A18: =IF(F18<>"",1+MAX($A$2:A17),"") | D18: EQUIPMENT CONNECTION
A19: =IF(F19<>"",1+MAX($A$2:A18),"") -> 8 | D19: CONNECTION FOR PEDESTRIAN GATE CARD READER | E19: 2 | F19: 0 | G19: =(F19*E19)+E19 -> 2 | H19: EA | I19: 0.25 | J19: =+I19*G19 -> 0.5 | K19: ='LABOR SHEET'!C$3 -> 128 | L19: =I19*K19 -> 32 | M19: =K19*J19 -> 64 | N19: 18 | O19: =N19*G19 -> 36 | P19: =(I19*K19)+N19 -> 50 | Q19: =P19*G19 -> 100
A20: =IF(F20<>"",1+MAX($A$2:A19),"")
A21: =IF(F21<>"",1+MAX($A$2:A20),"") | D21: MISCELLANEOUS
A22: =IF(F22<>"",1+MAX($A$2:A21),"") -> 9 | D22: TRENCHING AND BACKFILLING | E22: 89.02 | F22: 0 | G22: =(F22*E22)+E22 -> 89.02 | H22: LF | I22: 0.045 | J22: =+I22*G22 -> 4.0059 | K22: ='LABOR SHEET'!C$3 -> 128 | L22: =I22*K22 -> 5.76 | M22: =K22*J22 -> 512.7552 | N22: 1.2 | O22: =N22*G22 -> 106.824 | P22: =(I22*K22)+N22 -> 6.96 | Q22: =P22*G22 -> 619.5792
A23: =IF(F23<>"",1+MAX($A$2:A22),"")
A24: =IF(F24<>"",1+MAX($A$2:A23),"") | D24: POWER CIRCUITS
A25: =IF(F25<>"",1+MAX($A$2:A24),"") | D25: CONDUITS
A26: =IF(F26<>"",1+MAX($A$2:A25),"") -> 10 | D26: 1"C PVC | E26: 390.21 | F26: 0.05 | G26: =(F26*E26)+E26 -> 409.7205 | H26: LF | I26: 0.05 | J26: =+I26*G26 -> 20.486025 | K26: ='LABOR SHEET'!C$3 -> 128 | L26: =I26*K26 -> 6.4 | M26: =K26*J26 -> 2622.2112 | N26: =11.46/10+0.25 -> 1.396 | O26: =N26*G26 -> 571.96982 | P26: =(I26*K26)+N26 -> 7.796 | Q26: =P26*G26 -> 3194.181
A27: =IF(F27<>"",1+MAX($A$2:A26),"") -> 11 | D27: 3/4"C EMT | E27: 5 | F27: 0.05 | G27: =(F27*E27)+E27 -> 5.25 | H27: LF | I27: 0.035 | J27: =+I27*G27 -> 0.18375 | K27: ='LABOR SHEET'!C$3 -> 128 | L27: =I27*K27 -> 4.48 | M27: =K27*J27 -> 23.52 | N27: =9.68/10+0.35 -> 1.318 | O27: =N27*G27 -> 6.9195 | P27: =(I27*K27)+N27 -> 5.798 | Q27: =P27*G27 -> 30.4395
A28: =IF(F28<>"",1+MAX($A$2:A27),"") -> 12 | D28: 3/4"C LFMC | E28: 12.85 | F28: 0.05 | G28: =(F28*E28)+E28 -> 13.4925 | H28: LF | I28: 0.1 | J28: =+I28*G28 -> 1.34925 | K28: ='LABOR SHEET'!C$3 -> 128 | L28: =I28*K28 -> 12.8 | M28: =K28*J28 -> 172.704 | N28: =244.56/100+0.3 -> 2.7456 | O28: =N28*G28 -> 37.045008 | P28: =(I28*K28)+N28 -> 15.5456 | Q28: =P28*G28 -> 209.74901
A29: =IF(F29<>"",1+MAX($A$2:A28),"") -> 13 | D29: 3/4"C RGS | E29: 10.27 | F29: 0.05 | G29: =(F29*E29)+E29 -> 10.7835 | H29: LF | I29: 0.067 | J29: =+I29*G29 -> 0.7224945 | K29: ='LABOR SHEET'!C$3 -> 128 | L29: =I29*K29 -> 8.576 | M29: =K29*J29 -> 92.479296 | N29: =29.67/10+0.35 -> 3.317 | O29: =N29*G29 -> 35.76887 | P29: =(I29*K29)+N29 -> 11.893 | Q29: =P29*G29 -> 128.24817
A30: =IF(F30<>"",1+MAX($A$2:A29),"")
A31: =IF(F31<>"",1+MAX($A$2:A30),"") | D31: CONDUTORS
A32: =IF(F32<>"",1+MAX($A$2:A31),"") -> 14 | D32: #10 THHN SOLID | E32: 1254.99 | F32: 0.05 | G32: =(F32*E32)+E32 -> 1317.7395 | H32: LF | I32: 0.01 | J32: =+I32*G32 -> 13.177395 | K32: ='LABOR SHEET'!C$3 -> 128 | L32: =I32*K32 -> 1.28 | M32: =K32*J32 -> 1686.7066 | N32: 0.38 | O32: =N32*G32 -> 500.74101 | P32: =(I32*K32)+N32 -> 1.66 | Q32: =P32*G32 -> 2187.4476
A33: =IF(F33<>"",1+MAX($A$2:A32),"")
A34: =IF(F34<>"",1+MAX($A$2:A33),"") | D34: SECURITY
A35: =IF(F35<>"",1+MAX($A$2:A34),"") | D35: CONDIUTS
A36: =IF(F36<>"",1+MAX($A$2:A35),"") -> 15 | D36: 1"C PVC | E36: 110.05 | F36: 0.05 | G36: =(F36*E36)+E36 -> 115.5525 | H36: LF | I36: 0.05 | J36: =+I36*G36 -> 5.777625 | K36: ='LABOR SHEET'!C$3 -> 128 | L36: =I36*K36 -> 6.4 | M36: =K36*J36 -> 739.536 | N36: =11.46/10+0.25 -> 1.396 | O36: =N36*G36 -> 161.31129 | P36: =(I36*K36)+N36 -> 7.796 | Q36: =P36*G36 -> 900.84729
A37: =IF(F37<>"",1+MAX($A$2:A36),"") -> 16 | D37: 3/4"C RGS | E37: 14.52 | F37: 0.05 | G37: =(F37*E37)+E37 -> 15.246 | H37: LF | I37: 0.067 | J37: =+I37*G37 -> 1.021482 | K37: ='LABOR SHEET'!C$3 -> 128 | L37: =I37*K37 -> 8.576 | M37: =K37*J37 -> 130.7497 | N37: =29.67/10+0.35 -> 3.317 | O37: =N37*G37 -> 50.570982 | P37: =(I37*K37)+N37 -> 11.893 | Q37: =P37*G37 -> 181.32068
A38: =IF(F38<>"",1+MAX($A$2:A37),"")
A39: =IF(F39<>"",1+MAX($A$2:A38),"") | D39: CONDUCTORS
A40: =IF(F40<>"",1+MAX($A$2:A39),"") -> 17 | D40: CAT 6 | E40: 124.57 | F40: 0.05 | G40: =(F40*E40)+E40 -> 130.7985 | H40: LF | I40: 0.008 | J40: =+I40*G40 -> 1.046388 | K40: ='LABOR SHEET'!C$3 -> 128 | L40: =I40*K40 -> 1.024 | M40: =K40*J40 -> 133.93766 | N40: =7.94/15 -> 0.52933333 | O40: =N40*G40 -> 69.236006 | P40: =(I40*K40)+N40 -> 1.5533333 | Q40: =P40*G40 -> 203.17367
A41: =IF(F41<>"",1+MAX($A$2:A40),"")
A42: =IF(F42<>"",1+MAX($A$2:A41),"") | D42: DEVICES
A43: =IF(F43<>"",1+MAX($A$2:A42),"") -> 18 | D43: CARD READER FOR PEDESTRIAN SECURITY GATE WP | E43: 2 | F43: 0 | G43: =(F43*E43)+E43 -> 2 | H43: EA | I43: 3.5 | J43: =+I43*G43 -> 7 | K43: ='LABOR SHEET'!C$3 -> 128 | L43: =I43*K43 -> 448 | M43: =K43*J43 -> 896 | N43: 791.63 | O43: =N43*G43 -> 1583.26 | P43: =(I43*K43)+N43 -> 1239.63 | Q43: =P43*G43 -> 2479.26
A44: =IF(F44<>"",1+MAX($A$2:A43),"") -> 19 | D44: 4"X4" BACKBOX WP | E44: 2 | F44: 0 | G44: =(F44*E44)+E44 -> 2 | H44: EA | I44: 0.25 | J44: =+I44*G44 -> 0.5 | K44: ='LABOR SHEET'!C$3 -> 128 | L44: =I44*K44 -> 32 | M44: =K44*J44 -> 64 | N44: 20 | O44: =N44*G44 -> 40 | P44: =(I44*K44)+N44 -> 52 | Q44: =P44*G44 -> 104
A45: =IF(F45<>"",1+MAX($A$2:A44),"")
A46: =IF(F46<>"",1+MAX($A$2:A45),"") | D46: SUBTOTAL | Q46: =SUM(Q17:Q45) -> 10338.246
A47: =IF(F47<>"",1+MAX($A$2:A16),"")
H48: TOTAL LABOR HOURS | J48: =SUM(J17:J47) -> 55.77031 | K48: TOTAL LABOR COST | M48: =SUM(M17:M47) -> 7138.5996 | N48: TOTAL MATERIAL COST | O48: =SUM(O17:O47) -> 3199.6465
D49: TOTAL AMOUNT | Q49: =SUM(Q8:Q47)/2 -> 11838.246
D50: CONTIGENCIES (5%) | L50: 0.05 | Q50: =Q49*L50 -> 591.9123
D51: MATERIAL MARKUPS | L51: 0.2 | Q51: =O48*L51 -> 639.9293
D52: LABOR MARKUPS | L52: 0.31 | Q52: =M48*L52 -> 2212.9659
D53: OVERHEAD (10%) | L53: 0.1 | Q53: =Q49*L53 -> 1183.8246
D54: PROFIT (10%) | L54: 0.1 | Q54: =Q49*L54 -> 1183.8246
D55: TAX (9.2%) | L55: 0.092 | Q55: =Q49*L55 -> 1089.1186
D56: PERFORMANCE AND PAYMENT BONDS | L56: 0.015 | Q56: =Q49*L56 -> 177.57369
D57: TOTAL BASEBID | Q57: =SUM(Q49:Q56) -> 18917.395

Sheet LABOR SHEET
B1: Labor Type | C1: Labor Rate
A3: Electrical | B3: Elec | C3: 128
B7: Wastage
A8: Each/Count | B8: EA | C8: 0
A9: Linear Footage | B9: LF | C9: 0.05
A10: Square Footage | B10: SF | C10: 0.1
A11: Square Yard | B11: SY | C11: 0.1
A12: Cubic Yard | B12: CY | C12: 0.1
A13: Lumpsum | B13: LS | C13: 0
A14: Survery | B14: Survey | C14: 0
A15: Stair Riser | B15: RISER | C15: 0
A16: Blocks Count | B16: BLOCKS | C16: 0
A17: Bags of Pre-Mix Mortar | B17: BAGS | C17: 0
A18: Linear Footage of Wall | B18: LF.Wall | C18: 0.1
A19: Pounds | B19: LBS | C19: 0.1
... A30: N/A | B30: N/A | C30: 0
A33: NOTE:
A34: Prevailing wages have been included in this estimate in compliance with the Davis-Bacon Act.
A35: Material pricing is based on current market rates sourced from reputable online platforms and suppliers.
A36: Please note that actual costs may vary depending on site-specific conditions, unforeseen circumstances, or changes in market conditions.
