Workbook

Sheet General Summary
A1: GENERAL SUMMARY
A2: DIVISION NO. | B2: DESCRIPTION | C2: TOTAL DIV. COST
A3: 1000 | B3: General Requirments | C3: ='Base Bid'!R13 -> 54000
A4: 22000 | B4: Plumbing | C4: ='Base Bid'!R362 -> 539602.91
B5: TOTAL COST | C5: =SUM(C3:C4) -> 593602.91
A7: TOTAL COST | D7: =C5 -> 593602.91
A8: CONTIGENCIES | C8: 0.05 | D8: =D7*C8 -> 29680.146
A9: OVERHEAD AND PROFIT | C9: 0.1 | D9: =D7*C9 -> 59360.291
A10: TAX | C10: 0.105 | D10: =D7*C10 -> 62328.306
A11: PERFORMANCE AND PAYMENT BONDS | C11: 0.015 | D11: =D7*C11 -> 8904.0437
A12: TOTAL BASEBID | C12: =SUM(D7:D11) -> 753875.7
A15: GENERAL SUMMARY
A16: DIVISION NO. | B16: DESCRIPTION | C16: TOTAL DIV. COST
A17: 1000 | B17: General Requirments | C17: =Alternate!R13 -> 54000
A18: 22000 | B18: Plumbing | C18: =Alternate!R362 -> 470944.52
B19: TOTAL COST | C19: =SUM(C17:C18) -> 524944.52
A21: TOTAL COST | D21: =C19 -> 524944.52
A22: CONTIGENCIES | C22: 0.05 | D22: =D21*C22 -> 26247.226
A23: OVERHEAD AND PROFIT | C23: 0.1 | D23: =D21*C23 -> 52494.452
A24: TAX | C24: 0.105 | D24: =D21*C24 -> 55119.175
A25: PERFORMANCE AND PAYMENT BONDS | C25: 0.015 | D25: =D21*C25 -> 7874.1678
A26: TOTAL ALTERNATE BID | C26: =SUM(D21:D25) -> 666679.54

Sheet Base Bid
A1: DETAILED BREAKDOWN OF ITEMS
A2: Project Name: CHUZE FITNESS LONG BEACH CA | I2: Address: 2185E. SOUTH STREET LONG BEACH, CA 90805
A3: S# | B3: Dwg. | C3: CSI NO | D3: DESCRIPTION | E3: QTY. | F3: UNIT | G3: WASTAGE | H3: QTY. W/ WASTAGE | I3: UNIT MATERIAL COST | J3: TOTAL MATERIAL COST | K3: UNIT LABOR HOUR | L3: TOTAL LABOR HOUR | M3: LABOR WAGE/ HOUR | N3: UNIT LABOR COST | O3: TOTAL LABOR COST | P3: UNIT COST (Labor + Material) | Q3: TOTAL COST | R3: TRADE TOTAL
C4: 1 | D4: DIVISION 01-GENERAL REQUIREMENTS
A5: =IF(G5<>"",1+MAX($A$3:A4),"") -> 1 | D5: Permits | E5: 1 | F5: LS | G5: 0 | H5: =(G5*E5)+E5 -> 1 | I5: 0 | J5: =I5*H5 -> 0 | K5: 0 | L5: =+K5*H5 -> 0 | M5: 0 | N5: =K5*M5 -> 0 | O5: =M5*L5 -> 0 | P5: =I5+N5 -> 0 | Q5: 54000
A6: =IF(G6<>"",1+MAX($A$3:A5),"") -> 2 | D6: Supervision and Coordination | E6: 1 | F6: LS | G6: 0 | H6: =(G6*E6)+E6 -> 1 | I6: 0 | J6: =I6*H6 -> 0 | K6: 0 | L6: =+K6*H6 -> 0 | M6: 0 | N6: =K6*M6 -> 0 | O6: =M6*L6 -> 0 | P6: =I6+N6 -> 0
A7: =IF(G7<>"",1+MAX($A$3:A6),"") -> 3 | D7: Submittals and Shop drawings | E7: 1 | F7: LS | G7: 0 | H7: =(G7*E7)+E7 -> 1 | I7: 0 | J7: =I7*H7 -> 0 | K7: 0 | L7: =+K7*H7 -> 0 | M7: 0 | N7: =K7*M7 -> 0 | O7: =M7*L7 -> 0 | P7: =I7+N7 -> 0
A8: =IF(G8<>"",1+MAX($A$3:A7),"") -> 4 | D8: Final Cleaning | E8: 1 | F8: LS | G8: 0 | H8: =(G8*E8)+E8 -> 1 | I8: 0 | J8: =I8*H8 -> 0 | K8: 0 | L8: =+K8*H8 -> 0 | M8: 0 | N8: =K8*M8 -> 0 | O8: =M8*L8 -> 0 | P8: =I8+N8 -> 0
A9: =IF(G9<>"",1+MAX($A$3:A8),"") -> 5 | D9: Mobilization Costs | E9: 1 | F9: LS | G9: 0 | H9: =(G9*E9)+E9 -> 1 | I9: 0 | J9: =I9*H9 -> 0 | K9: 0 | L9: =+K9*H9 -> 0 | M9: 0 | N9: =K9*M9 -> 0 | O9: =M9*L9 -> 0 | P9: =I9+N9 -> 0
A10: =IF(G10<>"",1+MAX($A$3:A9),"") -> 6 | D10: Temporary Control & Facilities | E10: 1 | F10: LS | G10: 0 | H10: =(G10*E10)+E10 -> 1 | I10: 0 | J10: =I10*H10 -> 0 | K10: 0 | L10: =+K10*H10 -> 0 | M10: 0 | N10: =K10*M10 -> 0 | O10: =M10*L10 -> 0 | P10: =I10+N10 -> 0
A11: =IF(G11<>"",1+MAX($A$3:A10),"") -> 7 | D11: Scaffolding | E11: 1 | F11: LS | G11: 0 | H11: =(G11*E11)+E11 -> 1 | I11: 0 | J11: =I11*H11 -> 0 | K11: 0 | L11: =+K11*H11 -> 0 | M11: 0 | N11: =K11*M11 -> 0 | O11: =M11*L11 -> 0 | P11: =I11+N11 -> 0
A12: =IF(G12<>"",1+MAX($A$3:A11),"")
A13: =IF(G13<>"",1+MAX($A$3:A12),"") | D13: SUBTOTAL | R13: =SUM(Q4:Q13) -> 54000
A14: =IF(G14<>"",1+MAX($A$3:A13),"")
A15: =IF(G15<>"",1+MAX($A$3:A14),"") | C15: 22 | D15: DIVISION 22- PLUMBING
A16: =IF(G16<>"",1+MAX($A$3:A15),"") | D16: GAS PIPES
A17: =IF(G17<>"",1+MAX($A$3:A16),"") | D17: SCHEDULE 40 BLACK STEEL PIPE ASTM A53, W/ FITTINGS ASME B16.3 W/ WEATHER PROOF COAT
A18: =IF(G18<>"",1+MAX($A$3:A17),"") -> 8 | D18: 3/4" Dia Gas Pipe | E18: 64.85 | F18: LF | G18: 0.05 | H18: =E18*(1+G18) -> 68.0925 | I18: =4/1*0.75 -> 3 | J18: =I18*H18 -> 204.2775 | K18: 0.105 | L18: =+K18*H18 -> 7.1497125 | M18: ='LABOR SHEET'!C$5 -> 57.65 | N18: =K18*M18 -> 6.05325 | O18: =M18*L18 -> 412.18093 | P18: =I18+N18 -> 9.05325 | Q18: =P18*H18 -> 616.45843
A19: =IF(G19<>"",1+MAX($A$3:A18),"") -> 9 | D19: 1" Dia Gas Pipe | E19: 145.27 | F19: LF | G19: 0.05 | H19: =E19*(1+G19) -> 152.5335 | I19: =5.02/1.25 -> 4.016 | J19: =I19*H19 -> 612.57454 | K19: 0.125 | L19: =+K19*H19 -> 19.066688 | M19: ='LABOR SHEET'!C$5 -> 57.65 | N19: =K19*M19 -> 7.20625 | O19: =M19*L19 -> 1099.1945 | P19: =I19+N19 -> 11.22225 | Q19: =P19*H19 -> 1711.7691
A20: =IF(G20<>"",1+MAX($A$3:A19),"") -> 10 | D20: 1-1/4" Dia Gas Pipe | E20: 341.28 | F20: LF | G20: 0.05 | H20: =E20*(1+G20) -> 358.344 | I20: 5.02 | J20: =I20*H20 -> 1798.8869 | K20: 0.18 | L20: =+K20*H20 -> 64.50192 | M20: ='LABOR SHEET'!C$5 -> 57.65 | N20: =K20*M20 -> 10.377 | O20: =M20*L20 -> 3718.5357 | P20: =I20+N20 -> 15.397 | Q20: =P20*H20 -> 5517.4226
A21: =IF(G21<>"",1+MAX($A$3:A20),"") -> 11 | D21: 1-1/2" Dia Gas Pipe | E21: 29.58 | F21: LF | G21: 0.05 | H21: =E21*(1+G21) -> 31.059 | I21: 5.86 | J21: =I21*H21 -> 182.00574 | K21: 0.2 | L21: =+K21*H21 -> 6.2118 | M21: ='LABOR SHEET'!C$5 -> 57.65 | N21: =K21*M21 -> 11.53 | O21: =M21*L21 -> 358.11027 | P21: =I21+N21 -> 17.39 | Q21: =P21*H21 -> 540.11601
A22: =IF(G22<>"",1+MAX($A$3:A21),"") -> 12 | D22: 2" Dia Gas Pipe | E22: 224.28 | F22: LF | G22: 0.05 | H22: =E22*(1+G22) -> 235.494 | I22: 7.25 | J22: =I22*H22 -> 1707.3315 | K22: 0.262 | L22: =+K22*H22 -> 61.699428 | M22: ='LABOR SHEET'!C$5 -> 57.65 | N22: =K22*M22 -> 15.1043 | O22: =M22*L22 -> 3556.972 | P22: =I22+N22 -> 22.3543 | Q22: =P22*H22 -> 5264.3035
A23: =IF(G23<>"",1+MAX($A$3:A22),"") -> 13 | D23: 2-1/2" Dia Gas Pipe | E23: 111.67 | F23: LF | G23: 0.05 | H23: =E23*(1+G23) -> 117.2535 | I23: 15.11 | J23: =I23*H23 -> 1771.7004 | K23: 0.32 | L23: =+K23*H23 -> 37.52112 | M23: ='LABOR SHEET'!C$5 -> 57.65 | N23: =K23*M23 -> 18.448 | O23: =M23*L23 -> 2163.0926 | P23: =I23+N23 -> 33.558 | Q23: =P23*H23 -> 3934.793
A24: =IF(G24<>"",1+MAX($A$3:A23),"") -> 14 | D24: 3" Dia Gas Pipe | E24: 193.04 | F24: LF | G24: 0.05 | H24: =E24*(1+G24) -> 202.692 | I24: =28.82/4*3 -> 21.615 | J24: =I24*H24 -> 4381.1876 | K24: 0.365 | L24: =+K24*H24 -> 73.98258 | M24: ='LABOR SHEET'!C$5 -> 57.65 | N24: =K24*M24 -> 21.04225 | O24: =M24*L24 -> 4265.0957 | P24: =I24+N24 -> 42.65725 | Q24: =P24*H24 -> 8646.2833
A25: =IF(G25<>"",1+MAX($A$3:A24),"") -> 15 | D25: 4" Dia Gas Pipe | E25: 66.58 | F25: LF | G25: 0.05 | H25: =E25*(1+G25) -> 69.909 | I25: 28.82 | J25: =I25*H25 -> 2014.7774 | K25: 0.444 | L25: =+K25*H25 -> 31.039596 | M25: ='LABOR SHEET'!C$5 -> 57.65 | N25: =K25*M25 -> 25.5966 | O25: =M25*L25 -> 1789.4327 | P25: =I25+N25 -> 54.4166 | Q25: =P25*H25 -> 3804.2101
A26: =IF(G26<>"",1+MAX($A$3:A25),"")
A27: =IF(G27<>"",1+MAX($A$3:A26),"") | D27: FITTINGS
A28: =IF(G28<>"",1+MAX($A$3:A27),"") -> 16 | D28: 3/4" Dia Gas Pipe 90 Deg Elbow | E28: 5 | F28: EA | G28: 0 | H28: =E28*(1+G28) -> 5 | I28: 4.59 | J28: =I28*H28 -> 22.95 | K28: 0.55 | L28: =+K28*H28 -> 2.75 | M28: ='LABOR SHEET'!C$5 -> 57.65 | N28: =K28*M28 -> 31.7075 | O28: =M28*L28 -> 158.5375 | P28: =I28+N28 -> 36.2975 | Q28: =P28*H28 -> 181.4875
A29: =IF(G29<>"",1+MAX($A$3:A28),"") -> 17 | D29: 1" Dia Gas Pipe 90 Deg Elbow | E29: 12 | F29: EA | G29: 0 | H29: =E29*(1+G29) -> 12 | I29: 8.5 | J29: =I29*H29 -> 102 | K29: 0.56 | L29: =+K29*H29 -> 6.72 | M29: ='LABOR SHEET'!C$5 -> 57.65 | N29: =K29*M29 -> 32.284 | O29: =M29*L29 -> 387.408 | P29: =I29+N29 -> 40.784 | Q29: =P29*H29 -> 489.408
A30: =IF(G30<>"",1+MAX($A$3:A29),"") -> 18 | D30: 1-1/4" Dia Gas Pipe 90 Deg Elbow | E30: 25 | F30: EA | G30: 0 | H30: =E30*(1+G30) -> 25 | I30: 9.1 | J30: =I30*H30 -> 227.5 | K30: 0.57 | L30: =+K30*H30 -> 14.25 | M30: ='LABOR SHEET'!C$5 -> 57.65 | N30: =K30*M30 -> 32.8605 | O30: =M30*L30 -> 821.5125 | P30: =I30+N30 -> 41.9605 | Q30: =P30*H30 -> 1049.0125
A31: =IF(G31<>"",1+MAX($A$3:A30),"") -> 19 | D31: 1-1/2" Dia Gas Pipe 90 Deg Elbow | E31: 1 | F31: EA | G31: 0 | H31: =E31*(1+G31) -> 1 | I31: 12.1 | J31: =I31*H31 -> 12.1 | K31: 0.58 | L31: =+K31*H31 -> 0.58 | M31: ='LABOR SHEET'!C$5 -> 57.65 | N31: =K31*M31 -> 33.437 | O31: =M31*L31 -> 33.437 | P31: =I31+N31 -> 45.537 | Q31: =P31*H31 -> 45.537
A32: =IF(G32<>"",1+MAX($A$3:A31),"") -> 20 | D32: 2" Dia Gas Pipe 90 Deg Elbow | E32: 5 | F32: EA | G32: 0 | H32: =E32*(1+G32) -> 5 | I32: 15.2 | J32: =I32*H32 -> 76 | K32: 0.59 | L32: =+K32*H32 -> 2.95 | M32: ='LABOR SHEET'!C$5 -> 57.65 | N32: =K32*M32 -> 34.0135 | O32: =M32*L32 -> 170.0675 | P32: =I32+N32 -> 49.2135 | Q32: =P32*H32 -> 246.0675
A33: =IF(G33<>"",1+MAX($A$3:A32),"") -> 21 | D33: 2-1/2" Dia Gas Pipe 90 Deg Elbow | E33: 4 | F33: EA | G33: 0 | H33: =E33*(1+G33) -> 4 | I33: 22.5 | J33: =I33*H33 -> 90 | K33: 0.6 | L33: =+K33*H33 -> 2.4 | M33: ='LABOR SHEET'!C$5 -> 57.65 | N33: =K33*M33 -> 34.59 | O33: =M33*L33 -> 138.36 | P33: =I33+N33 -> 57.09 | Q33: =P33*H33 -> 228.36
A34: =IF(G34<>"",1+MAX($A$3:A33),"") -> 22 | D34: 3" Dia Gas Pipe 90 Deg Elbow | E34: 2 | F34: EA | G34: 0 | H34: =E34*(1+G34) -> 2 | I34: 32.53 | J34: =I34*H34 -> 65.06 | K34: 0.61 | L34: =+K34*H34 -> 1.22 | M34: ='LABOR SHEET'!C$5 -> 57.65 | N34: =K34*M34 -> 35.1665 | O34: =M34*L34 -> 70.333 | P34: =I34+N34 -> 67.6965 | Q34: =P34*H34 -> 135.393
A35: =IF(G35<>"",1+MAX($A$3:A34),"") -> 23 | D35: 3/4" Dia Gas Pipe Tee | E35: 2 | F35: EA | G35: 0 | H35: =E35*(1+G35) -> 2 | I35: 6.45 | J35: =I35*H35 -> 12.9 | K35: 0.65 | L35: =+K35*H35 -> 1.3 | M35: ='LABOR SHEET'!C$5 -> 57.65 | N35: =K35*M35 -> 37.4725 | O35: =M35*L35 -> 74.945 | P35: =I35+N35 -> 43.9225 | Q35: =P35*H35 -> 87.845
A36: =IF(G36<>"",1+MAX($A$3:A35),"") -> 24 | D36: 1" Dia Gas Pipe Tee | E36: 4 | F36: EA | G36: 0 | H36: =E36*(1+G36) -> 4 | I36: 12.5 | J36: =I36*H36 -> 50 | K36: 0.67 | L36: =+K36*H36 -> 2.68 | M36: ='LABOR SHEET'!C$5 -> 57.65 | N36: =K36*M36 -> 38.6255 | O36: =M36*L36 -> 154.502 | P36: =I36+N36 -> 51.1255 | Q36: =P36*H36 -> 204.502
A37: =IF(G37<>"",1+MAX($A$3:A36),"") -> 25 | D37: 1-1/4" / 1" Dia Gas Pipe Tee | E37: 1 | F37: EA | G37: 0 | H37: =E37*(1+G37) -> 1 | I37: 18.25 | J37: =I37*H37 -> 18.25 | K37: 0.68 | L37: =+K37*H37 -> 0.68 | M37: ='LABOR SHEET'!C$5 -> 57.65 | N37: =K37*M37 -> 39.202 | O37: =M37*L37 -> 39.202 | P37: =I37+N37 -> 57.452 | Q37: =P37*H37 -> 57.452
A38: =IF(G38<>"",1+MAX($A$3:A37),"") -> 26 | D38: 1-1/4" Dia Gas Pipe Tee | E38: 7 | F38: EA | G38: 0 | H38: =E38*(1+G38) -> 7 | I38: 25.5 | J38: =I38*H38 -> 178.5 | K38: 0.69 | L38: =+K38*H38 -> 4.83 | M38: ='LABOR SHEET'!C$5 -> 57.65 | N38: =K38*M38 -> 39.7785 | O38: =M38*L38 -> 278.4495 | P38: =I38+N38 -> 65.2785 | Q38: =P38*H38 -> 456.9495
A39: =IF(G39<>"",1+MAX($A$3:A38),"") -> 27 | D39: 2" / 3/4" Dia Gas Pipe Tee | E39: 2 | F39: EA | G39: 0 | H39: =E39*(1+G39) -> 2 | I39: 30.5 | J39: =I39*H39 -> 61 | K39: 0.7 | L39: =+K39*H39 -> 1.4 | M39: ='LABOR SHEET'!C$5 -> 57.65 | N39: =K39*M39 -> 40.355 | O39: =M39*L39 -> 80.71 | P39: =I39+N39 -> 70.855 | Q39: =P39*H39 -> 141.71
... A56: =IF(G56<>"",1+MAX($A$3:A55),"") -> 44 | D56: 4" / 3" Dia Gas Pipe Reducer | E56: 1 | F56: EA | G56: 0 | H56: =E56*(1+G56) -> 1 | I56: 70.34 | J56: =I56*H56 -> 70.34 | K56: 0.53 | L56: =+K56*H56 -> 0.53 | M56: ='LABOR SHEET'!C$5 -> 57.65 | N56: =K56*M56 -> 30.5545 | O56: =M56*L56 -> 30.5545 | P56: =I56+N56 -> 100.8945 | Q56: =P56*H56 -> 100.8945
A57: =IF(G57<>"",1+MAX($A$3:A56),"")
A58: =IF(G58<>"",1+MAX($A$3:A57),"") | D58: ACCESSORIES
A59: =IF(G59<>"",1+MAX($A$3:A58),"") -> 45 | D59: 3/4" Dia Flexible Connector | E59: 2 | F59: EA | G59: 0 | H59: =E59*(1+G59) -> 2 | I59: 5.12 | J59: =I59*H59 -> 10.24 | K59: 0.4 | L59: =+K59*H59 -> 0.8 | M59: ='LABOR SHEET'!C$5 -> 57.65 | N59: =K59*M59 -> 23.06 | O59: =M59*L59 -> 46.12 | P59: =I59+N59 -> 28.18 | Q59: =P59*H59 -> 56.36
A60: =IF(G60<>"",1+MAX($A$3:A59),"") -> 46 | D60: 3/4" Dia Gas Shut-Off Valve | E60: 2 | F60: EA | G60: 0 | H60: =E60*(1+G60) -> 2 | I60: 35.5 | J60: =I60*H60 -> 71 | K60: 0.65 | L60: =+K60*H60 -> 1.3 | M60: ='LABOR SHEET'!C$5 -> 57.65 | N60: =K60*M60 -> 37.4725 | O60: =M60*L60 -> 74.945 | P60: =I60+N60 -> 72.9725 | Q60: =P60*H60 -> 145.945
A61: =IF(G61<>"",1+MAX($A$3:A60),"") -> 47 | D61: 3/4" Dia Gas Union | E61: 2 | F61: EA | G61: 0 | H61: =E61*(1+G61) -> 2 | I61: 15.45 | J61: =I61*H61 -> 30.9 | K61: 0.6 | L61: =+K61*H61 -> 1.2 | M61: ='LABOR SHEET'!C$5 -> 57.65 | N61: =K61*M61 -> 34.59 | O61: =M61*L61 -> 69.18 | P61: =I61+N61 -> 50.04 | Q61: =P61*H61 -> 100.08
A62: =IF(G62<>"",1+MAX($A$3:A61),"") -> 48 | D62: 3/4" Dia Sediment Trap W/ Cap | E62: 2 | F62: EA | G62: 0 | H62: =E62*(1+G62) -> 2 | I62: 90.45 | J62: =I62*H62 -> 180.9 | K62: 0.65 | L62: =+K62*H62 -> 1.3 | M62: ='LABOR SHEET'!C$5 -> 57.65 | N62: =K62*M62 -> 37.4725 | O62: =M62*L62 -> 74.945 | P62: =I62+N62 -> 127.9225 | Q62: =P62*H62 -> 255.845
A63: =IF(G63<>"",1+MAX($A$3:A62),"") -> 49 | D63: 1" Dia Flexible Connector | E63: 4 | F63: EA | G63: 0 | H63: =E63*(1+G63) -> 4 | I63: 10.45 | J63: =I63*H63 -> 41.8 | K63: 0.45 | L63: =+K63*H63 -> 1.8 | M63: ='LABOR SHEET'!C$5 -> 57.65 | N63: =K63*M63 -> 25.9425 | O63: =M63*L63 -> 103.77 | P63: =I63+N63 -> 36.3925 | Q63: =P63*H63 -> 145.57
A64: =IF(G64<>"",1+MAX($A$3:A63),"") -> 50 | D64: 1" Dia Gas Shut-Off Valve | E64: 4 | F64: EA | G64: 0 | H64: =E64*(1+G64) -> 4 | I64: =35/0.75 -> 46.666667 | J64: =I64*H64 -> 186.66667 | K64: 0.68 | L64: =+K64*H64 -> 2.72 | M64: ='LABOR SHEET'!C$5 -> 57.65 | N64: =K64*M64 -> 39.202 | O64: =M64*L64 -> 156.808 | P64: =I64+N64 -> 85.868667 | Q64: =P64*H64 -> 343.47467
A65: =IF(G65<>"",1+MAX($A$3:A64),"") -> 51 | D65: 1" Dia Gas Union | E65: 4 | F65: EA | G65: 0 | H65: =E65*(1+G65) -> 4 | I65: 20.25 | J65: =I65*H65 -> 81 | K65: 0.62 | L65: =+K65*H65 -> 2.48 | M65: ='LABOR SHEET'!C$5 -> 57.65 | N65: =K65*M65 -> 35.743 | O65: =M65*L65 -> 142.972 | P65: =I65+N65 -> 55.993 | Q65: =P65*H65 -> 223.972
A66: =IF(G66<>"",1+MAX($A$3:A65),"") -> 52 | D66: 1" Dia Sediment Trap W/ Cap | E66: 4 | F66: EA | G66: 0 | H66: =E66*(1+G66) -> 4 | I66: 110 | J66: =I66*H66 -> 440 | K66: 0.4772 | L66: =+K66*H66 -> 1.9088 | M66: ='LABOR SHEET'!C$5 -> 57.65 | N66: =K66*M66 -> 27.51058 | O66: =M66*L66 -> 110.04232 | P66: =I66+N66 -> 137.51058 | Q66: =P66*H66 -> 550.04232
A67: =IF(G67<>"",1+MAX($A$3:A66),"") -> 53 | D67: 1-1/4" Dia Flexible Connector | E67: 7 | F67: EA | G67: 0 | H67: =E67*(1+G67) -> 7 | I67: 15.5 | J67: =I67*H67 -> 108.5 | K67: 0.46 | L67: =+K67*H67 -> 3.22 | M67: ='LABOR SHEET'!C$5 -> 57.65 | N67: =K67*M67 -> 26.519 | O67: =M67*L67 -> 185.633 | P67: =I67+N67 -> 42.019 | Q67: =P67*H67 -> 294.133
A68: =IF(G68<>"",1+MAX($A$3:A67),"") -> 54 | D68: 1-1/4" Dia Gas Shut-Off Valve | E68: 7 | F68: EA | G68: 0 | H68: =E68*(1+G68) -> 7 | I68: 55.2 | J68: =I68*H68 -> 386.4 | K68: 0.69 | L68: =+K68*H68 -> 4.83 | M68: ='LABOR SHEET'!C$5 -> 57.65 | N68: =K68*M68 -> 39.7785 | O68: =M68*L68 -> 278.4495 | P68: =I68+N68 -> 94.9785 | Q68: =P68*H68 -> 664.8495
A69: =IF(G69<>"",1+MAX($A$3:A68),"") -> 55 | D69: 1-1/4" Dia Gas Union | E69: 7 | F69: EA | G69: 0 | H69: =E69*(1+G69) -> 7 | I69: 25.2 | J69: =I69*H69 -> 176.4 | K69: 0.63 | L69: =+K69*H69 -> 4.41 | M69: ='LABOR SHEET'!C$5 -> 57.65 | N69: =K69*M69 -> 36.3195 | O69: =M69*L69 -> 254.2365 | P69: =I69+N69 -> 61.5195 | Q69: =P69*H69 -> 430.6365
A70: =IF(G70<>"",1+MAX($A$3:A69),"") -> 56 | D70: 1-1/4" Dia Sediment Trap W/ Cap | E70: 7 | F70: EA | G70: 0 | H70: =E70*(1+G70) -> 7 | I70: 125 | J70: =I70*H70 -> 875 | K70: 0.55 | L70: =+K70*H70 -> 3.85 | M70: ='LABOR SHEET'!C$5 -> 57.65 | N70: =K70*M70 -> 31.7075 | O70: =M70*L70 -> 221.9525 | P70: =I70+N70 -> 156.7075 | Q70: =P70*H70 -> 1096.9525
A71: =IF(G71<>"",1+MAX($A$3:A70),"") -> 57 | D71: 2" Dia Flexible Connector | E71: 2 | F71: EA | G71: 0 | H71: =E71*(1+G71) -> 2 | I71: 25.5 | J71: =I71*H71 -> 51 | K71: 0.51 | L71: =+K71*H71 -> 1.02 | M71: ='LABOR SHEET'!C$5 -> 57.65 | N71: =K71*M71 -> 29.4015 | O71: =M71*L71 -> 58.803 | P71: =I71+N71 -> 54.9015 | Q71: =P71*H71 -> 109.803
A72: =IF(G72<>"",1+MAX($A$3:A71),"") -> 58 | D72: 2" Dia Gas Shut-Off Valve | E72: 2 | F72: EA | G72: 0 | H72: =E72*(1+G72) -> 2 | I72: 69.5 | J72: =I72*H72 -> 139 | K72: 0.72 | L72: =+K72*H72 -> 1.44 | M72: ='LABOR SHEET'!C$5 -> 57.65 | N72: =K72*M72 -> 41.508 | O72: =M72*L72 -> 83.016 | P72: =I72+N72 -> 111.008 | Q72: =P72*H72 -> 222.016
A73: =IF(G73<>"",1+MAX($A$3:A72),"") -> 59 | D73: 2" Dia Gas Union | E73: 2 | F73: EA | G73: 0 | H73: =E73*(1+G73) -> 2 | I73: 30.5 | J73: =I73*H73 -> 61 | K73: 0.68 | L73: =+K73*H73 -> 1.36 | M73: ='LABOR SHEET'!C$5 -> 57.65 | N73: =K73*M73 -> 39.202 | O73: =M73*L73 -> 78.404 | P73: =I73+N73 -> 69.702 | Q73: =P73*H73 -> 139.404
A74: =IF(G74<>"",1+MAX($A$3:A73),"") -> 60 | D74: 2" Dia Sediment Trap W/ Cap | E74: 2 | F74: EA | G74: 0 | H74: =E74*(1+G74) -> 2 | I74: 150 | J74: =I74*H74 -> 300 | K74: 0.72 | L74: =+K74*H74 -> 1.44 | M74: ='LABOR SHEET'!C$5 -> 57.65 | N74: =K74*M74 -> 41.508 | O74: =M74*L74 -> 83.016 | P74: =I74+N74 -> 191.508 | Q74: =P74*H74 -> 383.016
A75: =IF(G75<>"",1+MAX($A$3:A74),"")
A76: =IF(G76<>"",1+MAX($A$3:A75),"") | D76: VENT PIPES
A77: =IF(G77<>"",1+MAX($A$3:A76),"") | D77: SCHEDULE 40 PVC PIPE ASTM A53, W/ FITTINGS ASTM D2665
A78: =IF(G78<>"",1+MAX($A$3:A77),"") -> 61 | D78: 1-1/2" Dia Vent Pipe | E78: 313.25 | F78: LF | G78: 0.05 | H78: =E78*(1+G78) -> 328.9125 | I78: 4.41 | J78: =I78*H78 -> 1450.5041 | K78: 0.222 | L78: =+K78*H78 -> 73.018575 | M78: ='LABOR SHEET'!C$5 -> 57.65 | N78: =K78*M78 -> 12.7983 | O78: =M78*L78 -> 4209.5208 | P78: =I78+N78 -> 17.2083 | Q78: =P78*H78 -> 5660.025
A79: =IF(G79<>"",1+MAX($A$3:A78),"") -> 62 | D79: 2" Dia Vent Pipe | E79: 392.27 | F79: LF | G79: 0.05 | H79: =E79*(1+G79) -> 411.8835 | I79: 5 | J79: =I79*H79 -> 2059.4175 | K79: 0.271 | L79: =+K79*H79 -> 111.62043 | M79: ='LABOR SHEET'!C$5 -> 57.65 | N79: =K79*M79 -> 15.62315 | O79: =M79*L79 -> 6434.9177 | P79: =I79+N79 -> 20.62315 | Q79: =P79*H79 -> 8494.3352
A80: =IF(G80<>"",1+MAX($A$3:A79),"") -> 63 | D80: 3" Dia Vent Pipe | E80: 96.29 | F80: LF | G80: 0.05 | H80: =E80*(1+G80) -> 101.1045 | I80: 8.15 | J80: =I80*H80 -> 824.00167 | K80: 0.302 | L80: =+K80*H80 -> 30.533559 | M80: ='LABOR SHEET'!C$5 -> 57.65 | N80: =K80*M80 -> 17.4103 | O80: =M80*L80 -> 1760.2597 | P80: =I80+N80 -> 25.5603 | Q80: =P80*H80 -> 2584.2614
A81: =IF(G81<>"",1+MAX($A$3:A80),"") -> 64 | D81: 4" Dia Vent Pipe | E81: 6.37 | F81: LF | G81: 0.05 | H81: =E81*(1+G81) -> 6.6885 | I81: 10.45 | J81: =I81*H81 -> 69.894825 | K81: 0.333 | L81: =+K81*H81 -> 2.2272705 | M81: ='LABOR SHEET'!C$5 -> 57.65 | N81: =K81*M81 -> 19.19745 | O81: =M81*L81 -> 128.40214 | P81: =I81+N81 -> 29.64745 | Q81: =P81*H81 -> 198.29697
A82: =IF(G82<>"",1+MAX($A$3:A81),"")
A83: =IF(G83<>"",1+MAX($A$3:A82),"") | D83: FITTINGS
A84: =IF(G84<>"",1+MAX($A$3:A83),"") -> 65 | D84: 1-1/2" Dia Vent Pipe 45 Deg Elbow | E84: 9 | F84: EA | G84: 0 | H84: =E84*(1+G84) -> 9 | I84: 2.5 | J84: =I84*H84 -> 22.5 | K84: 0.45 | L84: =+K84*H84 -> 4.05 | M84: ='LABOR SHEET'!C$5 -> 57.65 | N84: =K84*M84 -> 25.9425 | O84: =M84*L84 -> 233.4825 | P84: =I84+N84 -> 28.4425 | Q84: =P84*H84 -> 255.9825
A85: =IF(G85<>"",1+MAX($A$3:A84),"") -> 66 | D85: 2" Dia Vent Pipe 45 Deg Elbow | E85: 4 | F85: EA | G85: 0 | H85: =E85*(1+G85) -> 4 | I85: 4.54 | J85: =I85*H85 -> 18.16 | K85: 0.46 | L85: =+K85*H85 -> 1.84 | M85: ='LABOR SHEET'!C$5 -> 57.65 | N85: =K85*M85 -> 26.519 | O85: =M85*L85 -> 106.076 | P85: =I85+N85 -> 31.059 | Q85: =P85*H85 -> 124.236
A86: =IF(G86<>"",1+MAX($A$3:A85),"") -> 67 | D86: 1-1/2" Dia Vent Pipe 90 Deg Elbow | E86: 35 | F86: EA | G86: 0 | H86: =E86*(1+G86) -> 35 | I86: 7.5 | J86: =I86*H86 -> 262.5 | K86: 0.47 | L86: =+K86*H86 -> 16.45 | M86: ='LABOR SHEET'!C$5 -> 57.65 | N86: =K86*M86 -> 27.0955 | O86: =M86*L86 -> 948.3425 | P86: =I86+N86 -> 34.5955 | Q86: =P86*H86 -> 1210.8425
A87: =IF(G87<>"",1+MAX($A$3:A86),"") -> 68 | D87: 2" Dia Vent Pipe 90 Deg Elbow | E87: 35 | F87: EA | G87: 0 | H87: =E87*(1+G87) -> 35 | I87: 10.5 | J87: =I87*H87 -> 367.5 | K87: 0.48 | L87: =+K87*H87 -> 16.8 | M87: ='LABOR SHEET'!C$5 -> 57.65 | N87: =K87*M87 -> 27.672 | O87: =M87*L87 -> 968.52 | P87: =I87+N87 -> 38.172 | Q87: =P87*H87 -> 1336.02
A88: =IF(G88<>"",1+MAX($A$3:A87),"") -> 69 | D88: 1-1/2" Dia Vent Pipe Tee | E88: 3 | F88: EA | G88: 0 | H88: =E88*(1+G88) -> 3 | I88: 13.09 | J88: =I88*H88 -> 39.27 | K88: 0.5 | L88: =+K88*H88 -> 1.5 | M88: ='LABOR SHEET'!C$5 -> 57.65 | N88: =K88*M88 -> 28.825 | O88: =M88*L88 -> 86.475 | P88: =I88+N88 -> 41.915 | Q88: =P88*H88 -> 125.745
A89: =IF(G89<>"",1+MAX($A$3:A88),"") -> 70 | D89: 2" / 1-1/2" Dia Vent Pipe Tee | E89: 10 | F89: EA | G89: 0 | H89: =E89*(1+G89) -> 10 | I89: 19.2 | J89: =I89*H89 -> 192 | K89: 0.51 | L89: =+K89*H89 -> 5.1 | M89: ='LABOR SHEET'!C$5 -> 57.65 | N89: =K89*M89 -> 29.4015 | O89: =M89*L89 -> 294.015 | P89: =I89+N89 -> 48.6015 | Q89: =P89*H89 -> 486.015
A90: =IF(G90<>"",1+MAX($A$3:A89),"") -> 71 | D90: 2" Dia Vent Pipe Tee | E90: 18 | F90: EA | G90: 0 | H90: =E90*(1+G90) -> 18 | I90: 25.2 | J90: =I90*H90 -> 453.6 | K90: 0.52 | L90: =+K90*H90 -> 9.36 | M90: ='LABOR SHEET'!C$5 -> 57.65 | N90: =K90*M90 -> 29.978 | O90: =M90*L90 -> 539.604 | P90: =I90+N90 -> 55.178 | Q90: =P90*H90 -> 993.204
A91: =IF(G91<>"",1+MAX($A$3:A90),"") -> 72 | D91: 3" / 1-1/2" Dia Vent Pipe Tee | E91: 3 | F91: EA | G91: 0 | H91: =E91*(1+G91) -> 3 | I91: 29.5 | J91: =I91*H91 -> 88.5 | K91: 0.53 | L91: =+K91*H91 -> 1.59 | M91: ='LABOR SHEET'!C$5 -> 57.65 | N91: =K91*M91 -> 30.5545 | O91: =M91*L91 -> 91.6635 | P91: =I91+N91 -> 60.0545 | Q91: =P91*H91 -> 180.1635
A92: =IF(G92<>"",1+MAX($A$3:A91),"") -> 73 | D92: 3" / 2" Dia Vent Pipe Tee | E92: 9 | F92: EA | G92: 0 | H92: =E92*(1+G92) -> 9 | I92: 34.5 | J92: =I92*H92 -> 310.5 | K92: 0.54 | L92: =+K92*H92 -> 4.86 | M92: ='LABOR SHEET'!C$5 -> 57.65 | N92: =K92*M92 -> 31.131 | O92: =M92*L92 -> 280.179 | P92: =I92+N92 -> 65.631 | Q92: =P92*H92 -> 590.679
A93: =IF(G93<>"",1+MAX($A$3:A92),"") -> 74 | D93: 3" Dia Vent Pipe Tee | E93: 5 | F93: EA | G93: 0 | H93: =E93*(1+G93) -> 5 | I93: 38.5 | J93: =I93*H93 -> 192.5 | K93: 0.55 | L93: =+K93*H93 -> 2.75 | M93: ='LABOR SHEET'!C$5 -> 57.65 | N93: =K93*M93 -> 31.7075 | O93: =M93*L93 -> 158.5375 | P93: =I93+N93 -> 70.2075 | Q93: =P93*H93 -> 351.0375
A94: =IF(G94<>"",1+MAX($A$3:A93),"") -> 75 | D94: 4" Dia Vent Pipe Tee | E94: 1 | F94: EA | G94: 0 | H94: =E94*(1+G94) -> 1 | I94: 43.73 | J94: =I94*H94 -> 43.73 | K94: 0.56 | L94: =+K94*H94 -> 0.56 | M94: ='LABOR SHEET'!C$5 -> 57.65 | N94: =K94*M94 -> 32.284 | O94: =M94*L94 -> 32.284 | P94: =I94+N94 -> 76.014 | Q94: =P94*H94 -> 76.014
A95: =IF(G95<>"",1+MAX($A$3:A94),"") -> 76 | D95: 2" / 1-1/2" Dia Vent Pipe Reducer | E95: 9 | F95: EA | G95: 0 | H95: =E95*(1+G95) -> 9 | I95: 13.5 | J95: =I95*H95 -> 121.5 | K95: 0.38 | L95: =+K95*H95 -> 3.42 | M95: ='LABOR SHEET'!C$5 -> 57.65 | N95: =K95*M95 -> 21.907 | O95: =M95*L95 -> 197.163 | P95: =I95+N95 -> 35.407 | Q95: =P95*H95 -> 318.663
... A99: =IF(G99<>"",1+MAX($A$3:A98),"") -> 80 | D99: 4" / 3" Dia Vent Pipe Reducer | E99: 1 | F99: EA | G99: 0 | H99: =E99*(1+G99) -> 1 | I99: 55.2 | J99: =I99*H99 -> 55.2 | K99: 0.42 | L99: =+K99*H99 -> 0.42 | M99: ='LABOR SHEET'!C$5 -> 57.65 | N99: =K99*M99 -> 24.213 | O99: =M99*L99 -> 24.213 | P99: =I99+N99 -> 79.413 | Q99: =P99*H99 -> 79.413
A100: =IF(G100<>"",1+MAX($A$3:A99),"")
A101: =IF(G101<>"",1+MAX($A$3:A100),"") | D101: SANITARY PIPES - BELOW GRADE
A102: =IF(G102<>"",1+MAX($A$3:A101),"") | D102: SCHEDULE 40 PVC PIPE ASTM A53, W/ FITTINGS ASTM D2665
A103: =IF(G103<>"",1+MAX($A$3:A102),"") -> 81 | D103: 2" Dia Sanitary Pipe | E103: 250.47 | F103: LF | G103: 0.05 | H103: =E103*(1+G103) -> 262.9935 | I103: 5 | J103: =I103*H103 -> 1314.9675 | K103: 0.271 | L103: =+K103*H103 -> 71.271238 | M103: ='LABOR SHEET'!C$5 -> 57.65 | N103: =K103*M103 -> 15.62315 | O103: =M103*L103 -> 4108.7869 | P103: =I103+N103 -> 20.62315 | Q103: =P103*H103 -> 5423.7544
A104: =IF(G104<>"",1+MAX($A$3:A103),"") -> 82 | D104: 3" Dia Sanitary Pipe | E104: 280.51 | F104: LF | G104: 0.05 | H104: =E104*(1+G104) -> 294.5355 | I104: 8.15 | J104: =I104*H104 -> 2400.4643 | K104: 0.302 | L104: =+K104*H104 -> 88.949721 | M104: ='LABOR SHEET'!C$5 -> 57.65 | N104: =K104*M104 -> 17.4103 | O104: =M104*L104 -> 5127.9514 | P104: =I104+N104 -> 25.5603 | Q104: =P104*H104 -> 7528.4157
A105: =IF(G105<>"",1+MAX($A$3:A104),"") -> 83 | D105: 4" Dia Sanitary Pipe | E105: 348.47 | F105: LF | G105: 0.05 | H105: =E105*(1+G105) -> 365.8935 | I105: 10.45 | J105: =I105*H105 -> 3823.5871 | K105: 0.333 | L105: =+K105*H105 -> 121.84254 | M105: ='LABOR SHEET'!C$5 -> 57.65 | N105: =K105*M105 -> 19.19745 | O105: =M105*L105 -> 7024.2222 | P105: =I105+N105 -> 29.64745 | Q105: =P105*H105 -> 10847.809
A106: =IF(G106<>"",1+MAX($A$3:A105),"") -> 84 | D106: 6" Dia Sanitary Pipe | E106: 136.79 | F106: LF | G106: 0.05 | H106: =E106*(1+G106) -> 143.6295 | I106: 17.95 | J106: =I106*H106 -> 2578.1495 | K106: 0.41 | L106: =+K106*H106 -> 58.888095 | M106: ='LABOR SHEET'!C$5 -> 57.65 | N106: =K106*M106 -> 23.6365 | O106: =M106*L106 -> 3394.8987 | P106: =I106+N106 -> 41.5865 | Q106: =P106*H106 -> 5973.0482
A107: =IF(G107<>"",1+MAX($A$3:A106),"") -> 85 | D107: 1-1/2" Dia Vent Pipe | E107: 11.56 | F107: LF | G107: 0.05 | H107: =E107*(1+G107) -> 12.138 | I107: 4.41 | J107: =I107*H107 -> 53.52858 | K107: 0.222 | L107: =+K107*H107 -> 2.694636 | M107: ='LABOR SHEET'!C$5 -> 57.65 | N107: =K107*M107 -> 12.7983 | O107: =M107*L107 -> 155.34577 | P107: =I107+N107 -> 17.2083 | Q107: =P107*H107 -> 208.87435
A108: =IF(G108<>"",1+MAX($A$3:A107),"")
A109: =IF(G109<>"",1+MAX($A$3:A108),"") | D109: FITTINGS
A110: =IF(G110<>"",1+MAX($A$3:A109),"") -> 86 | D110: 2" Dia PVC Pipe 90 Deg Elbow | E110: 34 | F110: EA | G110: 0 | H110: =E110*(1+G110) -> 34 | I110: 8.96 | J110: =I110*H110 -> 304.64 | K110: 0.36 | L110: =+K110*H110 -> 12.24 | M110: ='LABOR SHEET'!C$5 -> 57.65 | N110: =K110*M110 -> 20.754 | O110: =M110*L110 -> 705.636 | P110: =I110+N110 -> 29.714 | Q110: =P110*H110 -> 1010.276
A111: =IF(G111<>"",1+MAX($A$3:A110),"") -> 87 | D111: 3" Dia PVC Pipe 90 Deg Elbow | E111: 20 | F111: EA | G111: 0 | H111: =E111*(1+G111) -> 20 | I111: 15.5 | J111: =I111*H111 -> 310 | K111: 0.37 | L111: =+K111*H111 -> 7.4 | M111: ='LABOR SHEET'!C$5 -> 57.65 | N111: =K111*M111 -> 21.3305 | O111: =M111*L111 -> 426.61 | P111: =I111+N111 -> 36.8305 | Q111: =P111*H111 -> 736.61
A112: =IF(G112<>"",1+MAX($A$3:A111),"") -> 88 | D112: 4" Dia PVC Pipe 90 Deg Elbow | E112: 24 | F112: EA | G112: 0 | H112: =E112*(1+G112) -> 24 | I112: 19.5 | J112: =I112*H112 -> 468 | K112: 0.38 | L112: =+K112*H112 -> 9.12 | M112: ='LABOR SHEET'!C$5 -> 57.65 | N112: =K112*M112 -> 21.907 | O112: =M112*L112 -> 525.768 | P112: =I112+N112 -> 41.407 | Q112: =P112*H112 -> 993.768
A113: =IF(G113<>"",1+MAX($A$3:A112),"") -> 89 | D113: 2" Dia PVC Pipe 45 Deg Elbow | E113: 10 | F113: EA | G113: 0 | H113: =E113*(1+G113) -> 10 | I113: 10.5 | J113: =I113*H113 -> 105 | K113: 0.37 | L113: =+K113*H113 -> 3.7 | M113: ='LABOR SHEET'!C$5 -> 57.65 | N113: =K113*M113 -> 21.3305 | O113: =M113*L113 -> 213.305 | P113: =I113+N113 -> 31.8305 | Q113: =P113*H113 -> 318.305
A114: =IF(G114<>"",1+MAX($A$3:A113),"") -> 90 | D114: 3" Dia PVC Pipe 45 Deg Elbow | E114: 20 | F114: EA | G114: 0 | H114: =E114*(1+G114) -> 20 | I114: 16.5 | J114: =I114*H114 -> 330 | K114: 0.39 | L114: =+K114*H114 -> 7.8 | M114: ='LABOR SHEET'!C$5 -> 57.65 | N114: =K114*M114 -> 22.4835 | O114: =M114*L114 -> 449.67 | P114: =I114+N114 -> 38.9835 | Q114: =P114*H114 -> 779.67
A115: =IF(G115<>"",1+MAX($A$3:A114),"") -> 91 | D115: 4" Dia PVC Pipe 45 Deg Elbow | E115: 8 | F115: EA | G115: 0 | H115: =E115*(1+G115) -> 8 | I115: 22.5 | J115: =I115*H115 -> 180 | K115: 0.4 | L115: =+K115*H115 -> 3.2 | M115: ='LABOR SHEET'!C$5 -> 57.65 | N115: =K115*M115 -> 23.06 | O115: =M115*L115 -> 184.48 | P115: =I115+N115 -> 45.56 | Q115: =P115*H115 -> 364.48
A116: =IF(G116<>"",1+MAX($A$3:A115),"") -> 92 | D116: 2" Dia PVC Pipe Combination Wye | E116: 30 | F116: EA | G116: 0 | H116: =E116*(1+G116) -> 30 | I116: 19.87 | J116: =I116*H116 -> 596.1 | K116: 0.45 | L116: =+K116*H116 -> 13.5 | M116: ='LABOR SHEET'!C$5 -> 57.65 | N116: =K116*M116 -> 25.9425 | O116: =M116*L116 -> 778.275 | P116: =I116+N116 -> 45.8125 | Q116: =P116*H116 -> 1374.375
A117: =IF(G117<>"",1+MAX($A$3:A116),"") -> 93 | D117: 3" / 1-1/2" Dia PVC Pipe Combination Wye | E117: 1 | F117: EA | G117: 0 | H117: =E117*(1+G117) -> 1 | I117: 30.3 | J117: =I117*H117 -> 30.3 | K117: 0.46 | L117: =+K117*H117 -> 0.46 | M117: ='LABOR SHEET'!C$5 -> 57.65 | N117: =K117*M117 -> 26.519 | O117: =M117*L117 -> 26.519 | P117: =I117+N117 -> 56.819 | Q117: =P117*H117 -> 56.819
A118: =IF(G118<>"",1+MAX($A$3:A117),"") -> 94 | D118: 3" / 2" Dia PVC Pipe Wye | E118: 8 | F118: EA | G118: 0 | H118: =E118*(1+G118) -> 8 | I118: 50.2 | J118: =I118*H118 -> 401.6 | K118: 0.47 | L118: =+K118*H118 -> 3.76 | M118: ='LABOR SHEET'!C$5 -> 57.65 | N118: =K118*M118 -> 27.0955 | O118: =M118*L118 -> 216.764 | P118: =I118+N118 -> 77.2955 | Q118: =P118*H118 -> 618.364
A119: =IF(G119<>"",1+MAX($A$3:A118),"") -> 95 | D119: 3" Dia PVC Pipe Wye | E119: 5 | F119: EA | G119: 0 | H119: =E119*(1+G119) -> 5 | I119: 65.5 | J119: =I119*H119 -> 327.5 | K119: 0.48 | L119: =+K119*H119 -> 2.4 | M119: ='LABOR SHEET'!C$5 -> 57.65 | N119: =K119*M119 -> 27.672 | O119: =M119*L119 -> 138.36 | P119: =I119+N119 -> 93.172 | Q119: =P119*H119 -> 465.86
...

Sheet Alternate
A1: DETAILED BREAKDOWN OF ITEMS
A2: Project Name: CHUZE FITNESS LONG BEACH CA | I2: Address: 2185E. SOUTH STREET LONG BEACH, CA 90805
A3: S# | B3: Dwg. | C3: CSI NO | D3: DESCRIPTION | E3: QTY. | F3: UNIT | G3: WASTAGE | H3: QTY. W/ WASTAGE | I3: UNIT MATERIAL COST | J3: TOTAL MATERIAL COST | K3: UNIT LABOR HOUR | L3: TOTAL LABOR HOUR | M3: LABOR WAGE/ HOUR | N3: UNIT LABOR COST | O3: TOTAL LABOR COST | P3: UNIT COST (Labor + Material) | Q3: TOTAL COST | R3: TRADE TOTAL
C4: 1 | D4: DIVISION 01-GENERAL REQUIREMENTS
A5: =IF(G5<>"",1+MAX($A$3:A4),"") -> 1 | D5: Permits | E5: 1 | F5: LS | G5: 0 | H5: =(G5*E5)+E5 -> 1 | I5: 0 | J5: =I5*H5 -> 0 | K5: 0 | L5: =+K5*H5 -> 0 | M5: 0 | N5: =K5*M5 -> 0 | O5: =M5*L5 -> 0 | P5: =I5+N5 -> 0 | Q5: 54000
A6: =IF(G6<>"",1+MAX($A$3:A5),"") -> 2 | D6: Supervision and Coordination | E6: 1 | F6: LS | G6: 0 | H6: =(G6*E6)+E6 -> 1 | I6: 0 | J6: =I6*H6 -> 0 | K6: 0 | L6: =+K6*H6 -> 0 | M6: 0 | N6: =K6*M6 -> 0 | O6: =M6*L6 -> 0 | P6: =I6+N6 -> 0
A7: =IF(G7<>"",1+MAX($A$3:A6),"") -> 3 | D7: Submittals and Shop drawings | E7: 1 | F7: LS | G7: 0 | H7: =(G7*E7)+E7 -> 1 | I7: 0 | J7: =I7*H7 -> 0 | K7: 0 | L7: =+K7*H7 -> 0 | M7: 0 | N7: =K7*M7 -> 0 | O7: =M7*L7 -> 0 | P7: =I7+N7 -> 0
A8: =IF(G8<>"",1+MAX($A$3:A7),"") -> 4 | D8: Final Cleaning | E8: 1 | F8: LS | G8: 0 | H8: =(G8*E8)+E8 -> 1 | I8: 0 | J8: =I8*H8 -> 0 | K8: 0 | L8: =+K8*H8 -> 0 | M8: 0 | N8: =K8*M8 -> 0 | O8: =M8*L8 -> 0 | P8: =I8+N8 -> 0
A9: =IF(G9<>"",1+MAX($A$3:A8),"") -> 5 | D9: Mobilization Costs | E9: 1 | F9: LS | G9: 0 | H9: =(G9*E9)+E9 -> 1 | I9: 0 | J9: =I9*H9 -> 0 | K9: 0 | L9: =+K9*H9 -> 0 | M9: 0 | N9: =K9*M9 -> 0 | O9: =M9*L9 -> 0 | P9: =I9+N9 -> 0
A10: =IF(G10<>"",1+MAX($A$3:A9),"") -> 6 | D10: Temporary Control & Facilities | E10: 1 | F10: LS | G10: 0 | H10: =(G10*E10)+E10 -> 1 | I10: 0 | J10: =I10*H10 -> 0 | K10: 0 | L10: =+K10*H10 -> 0 | M10: 0 | N10: =K10*M10 -> 0 | O10: =M10*L10 -> 0 | P10: =I10+N10 -> 0
A11: =IF(G11<>"",1+MAX($A$3:A10),"") -> 7 | D11: Scaffolding | E11: 1 | F11: LS | G11: 0 | H11: =(G11*E11)+E11 -> 1 | I11: 0 | J11: =I11*H11 -> 0 | K11: 0 | L11: =+K11*H11 -> 0 | M11: 0 | N11: =K11*M11 -> 0 | O11: =M11*L11 -> 0 | P11: =I11+N11 -> 0
A12: =IF(G12<>"",1+MAX($A$3:A11),"")
A13: =IF(G13<>"",1+MAX($A$3:A12),"") | D13: SUBTOTAL | R13: =SUM(Q4:Q13) -> 54000
A14: =IF(G14<>"",1+MAX($A$3:A13),"")
A15: =IF(G15<>"",1+MAX($A$3:A14),"") | C15: 22 | D15: DIVISION 22- PLUMBING
A16: =IF(G16<>"",1+MAX($A$3:A15),"") | D16: GAS PIPES
A17: =IF(G17<>"",1+MAX($A$3:A16),"") | D17: SCHEDULE 40 BLACK STEEL PIPE ASTM A53, W/ FITTINGS ASME B16.3 W/ WEATHER PROOF COAT
A18: =IF(G18<>"",1+MAX($A$3:A17),"") -> 8 | D18: 3/4" Dia Gas Pipe | E18: 64.85 | F18: LF | G18: 0.05 | H18: =E18*(1+G18) -> 68.0925 | I18: =4/1*0.75 -> 3 | J18: =I18*H18 -> 204.2775 | K18: 0.105 | L18: =+K18*H18 -> 7.1497125 | M18: ='LABOR SHEET'!C$5 -> 57.65 | N18: =K18*M18 -> 6.05325 | O18: =M18*L18 -> 412.18093 | P18: =I18+N18 -> 9.05325 | Q18: =P18*H18 -> 616.45843
A19: =IF(G19<>"",1+MAX($A$3:A18),"") -> 9 | D19: 1" Dia Gas Pipe | E19: 145.27 | F19: LF | G19: 0.05 | H19: =E19*(1+G19) -> 152.5335 | I19: =5.02/1.25 -> 4.016 | J19: =I19*H19 -> 612.57454 | K19: 0.125 | L19: =+K19*H19 -> 19.066688 | M19: ='LABOR SHEET'!C$5 -> 57.65 | N19: =K19*M19 -> 7.20625 | O19: =M19*L19 -> 1099.1945 | P19: =I19+N19 -> 11.22225 | Q19: =P19*H19 -> 1711.7691
A20: =IF(G20<>"",1+MAX($A$3:A19),"") -> 10 | D20: 1-1/4" Dia Gas Pipe | E20: 341.28 | F20: LF | G20: 0.05 | H20: =E20*(1+G20) -> 358.344 | I20: 5.02 | J20: =I20*H20 -> 1798.8869 | K20: 0.18 | L20: =+K20*H20 -> 64.50192 | M20: ='LABOR SHEET'!C$5 -> 57.65 | N20: =K20*M20 -> 10.377 | O20: =M20*L20 -> 3718.5357 | P20: =I20+N20 -> 15.397 | Q20: =P20*H20 -> 5517.4226
A21: =IF(G21<>"",1+MAX($A$3:A20),"") -> 11 | D21: 1-1/2" Dia Gas Pipe | E21: 29.58 | F21: LF | G21: 0.05 | H21: =E21*(1+G21) -> 31.059 | I21: 5.86 | J21: =I21*H21 -> 182.00574 | K21: 0.2 | L21: =+K21*H21 -> 6.2118 | M21: ='LABOR SHEET'!C$5 -> 57.65 | N21: =K21*M21 -> 11.53 | O21: =M21*L21 -> 358.11027 | P21: =I21+N21 -> 17.39 | Q21: =P21*H21 -> 540.11601
A22: =IF(G22<>"",1+MAX($A$3:A21),"") -> 12 | D22: 2" Dia Gas Pipe | E22: 224.28 | F22: LF | G22: 0.05 | H22: =E22*(1+G22) -> 235.494 | I22: 7.25 | J22: =I22*H22 -> 1707.3315 | K22: 0.262 | L22: =+K22*H22 -> 61.699428 | M22: ='LABOR SHEET'!C$5 -> 57.65 | N22: =K22*M22 -> 15.1043 | O22: =M22*L22 -> 3556.972 | P22: =I22+N22 -> 22.3543 | Q22: =P22*H22 -> 5264.3035
A23: =IF(G23<>"",1+MAX($A$3:A22),"") -> 13 | D23: 2-1/2" Dia Gas Pipe | E23: 111.67 | F23: LF | G23: 0.05 | H23: =E23*(1+G23) -> 117.2535 | I23: 15.11 | J23: =I23*H23 -> 1771.7004 | K23: 0.32 | L23: =+K23*H23 -> 37.52112 | M23: ='LABOR SHEET'!C$5 -> 57.65 | N23: =K23*M23 -> 18.448 | O23: =M23*L23 -> 2163.0926 | P23: =I23+N23 -> 33.558 | Q23: =P23*H23 -> 3934.793
A24: =IF(G24<>"",1+MAX($A$3:A23),"") -> 14 | D24: 3" Dia Gas Pipe | E24: 193.04 | F24: LF | G24: 0.05 | H24: =E24*(1+G24) -> 202.692 | I24: =28.82/4*3 -> 21.615 | J24: =I24*H24 -> 4381.1876 | K24: 0.365 | L24: =+K24*H24 -> 73.98258 | M24: ='LABOR SHEET'!C$5 -> 57.65 | N24: =K24*M24 -> 21.04225 | O24: =M24*L24 -> 4265.0957 | P24: =I24+N24 -> 42.65725 | Q24: =P24*H24 -> 8646.2833
A25: =IF(G25<>"",1+MAX($A$3:A24),"") -> 15 | D25: 4" Dia Gas Pipe | E25: 66.58 | F25: LF | G25: 0.05 | H25: =E25*(1+G25) -> 69.909 | I25: 28.82 | J25: =I25*H25 -> 2014.7774 | K25: 0.444 | L25: =+K25*H25 -> 31.039596 | M25: ='LABOR SHEET'!C$5 -> 57.65 | N25: =K25*M25 -> 25.5966 | O25: =M25*L25 -> 1789.4327 | P25: =I25+N25 -> 54.4166 | Q25: =P25*H25 -> 3804.2101
A26: =IF(G26<>"",1+MAX($A$3:A25),"")
A27: =IF(G27<>"",1+MAX($A$3:A26),"") | D27: FITTINGS
A28: =IF(G28<>"",1+MAX($A$3:A27),"") -> 16 | D28: 3/4" Dia Gas Pipe 90 Deg Elbow | E28: 5 | F28: EA | G28: 0 | H28: =E28*(1+G28) -> 5 | I28: 4.59 | J28: =I28*H28 -> 22.95 | K28: 0.55 | L28: =+K28*H28 -> 2.75 | M28: ='LABOR SHEET'!C$5 -> 57.65 | N28: =K28*M28 -> 31.7075 | O28: =M28*L28 -> 158.5375 | P28: =I28+N28 -> 36.2975 | Q28: =P28*H28 -> 181.4875
A29: =IF(G29<>"",1+MAX($A$3:A28),"") -> 17 | D29: 1" Dia Gas Pipe 90 Deg Elbow | E29: 12 | F29: EA | G29: 0 | H29: =E29*(1+G29) -> 12 | I29: 8.5 | J29: =I29*H29 -> 102 | K29: 0.56 | L29: =+K29*H29 -> 6.72 | M29: ='LABOR SHEET'!C$5 -> 57.65 | N29: =K29*M29 -> 32.284 | O29: =M29*L29 -> 387.408 | P29: =I29+N29 -> 40.784 | Q29: =P29*H29 -> 489.408
A30: =IF(G30<>"",1+MAX($A$3:A29),"") -> 18 | D30: 1-1/4" Dia Gas Pipe 90 Deg Elbow | E30: 25 | F30: EA | G30: 0 | H30: =E30*(1+G30) -> 25 | I30: 9.1 | J30: =I30*H30 -> 227.5 | K30: 0.57 | L30: =+K30*H30 -> 14.25 | M30: ='LABOR SHEET'!C$5 -> 57.65 | N30: =K30*M30 -> 32.8605 | O30: =M30*L30 -> 821.5125 | P30: =I30+N30 -> 41.9605 | Q30: =P30*H30 -> 1049.0125
A31: =IF(G31<>"",1+MAX($A$3:A30),"") -> 19 | D31: 1-1/2" Dia Gas Pipe 90 Deg Elbow | E31: 1 | F31: EA | G31: 0 | H31: =E31*(1+G31) -> 1 | I31: 12.1 | J31: =I31*H31 -> 12.1 | K31: 0.58 | L31: =+K31*H31 -> 0.58 | M31: ='LABOR SHEET'!C$5 -> 57.65 | N31: =K31*M31 -> 33.437 | O31: =M31*L31 -> 33.437 | P31: =I31+N31 -> 45.537 | Q31: =P31*H31 -> 45.537
A32: =IF(G32<>"",1+MAX($A$3:A31),"") -> 20 | D32: 2" Dia Gas Pipe 90 Deg Elbow | E32: 5 | F32: EA | G32: 0 | H32: =E32*(1+G32) -> 5 | I32: 15.2 | J32: =I32*H32 -> 76 | K32: 0.59 | L32: =+K32*H32 -> 2.95 | M32: ='LABOR SHEET'!C$5 -> 57.65 | N32: =K32*M32 -> 34.0135 | O32: =M32*L32 -> 170.0675 | P32: =I32+N32 -> 49.2135 | Q32: =P32*H32 -> 246.0675
A33: =IF(G33<>"",1+MAX($A$3:A32),"") -> 21 | D33: 2-1/2" Dia Gas Pipe 90 Deg Elbow | E33: 4 | F33: EA | G33: 0 | H33: =E33*(1+G33) -> 4 | I33: 22.5 | J33: =I33*H33 -> 90 | K33: 0.6 | L33: =+K33*H33 -> 2.4 | M33: ='LABOR SHEET'!C$5 -> 57.65 | N33: =K33*M33 -> 34.59 | O33: =M33*L33 -> 138.36 | P33: =I33+N33 -> 57.09 | Q33: =P33*H33 -> 228.36
A34: =IF(G34<>"",1+MAX($A$3:A33),"") -> 22 | D34: 3" Dia Gas Pipe 90 Deg Elbow | E34: 2 | F34: EA | G34: 0 | H34: =E34*(1+G34) -> 2 | I34: 32.53 | J34: =I34*H34 -> 65.06 | K34: 0.61 | L34: =+K34*H34 -> 1.22 | M34: ='LABOR SHEET'!C$5 -> 57.65 | N34: =K34*M34 -> 35.1665 | O34: =M34*L34 -> 70.333 | P34: =I34+N34 -> 67.6965 | Q34: =P34*H34 -> 135.393
A35: =IF(G35<>"",1+MAX($A$3:A34),"") -> 23 | D35: 3/4" Dia Gas Pipe Tee | E35: 2 | F35: EA | G35: 0 | H35: =E35*(1+G35) -> 2 | I35: 6.45 | J35: =I35*H35 -> 12.9 | K35: 0.65 | L35: =+K35*H35 -> 1.3 | M35: ='LABOR SHEET'!C$5 -> 57.65 | N35: =K35*M35 -> 37.4725 | O35: =M35*L35 -> 74.945 | P35: =I35+N35 -> 43.9225 | Q35: =P35*H35 -> 87.845
A36: =IF(G36<>"",1+MAX($A$3:A35),"") -> 24 | D36: 1" Dia Gas Pipe Tee | E36: 4 | F36: EA | G36: 0 | H36: =E36*(1+G36) -> 4 | I36: 12.5 | J36: =I36*H36 -> 50 | K36: 0.67 | L36: =+K36*H36 -> 2.68 | M36: ='LABOR SHEET'!C$5 -> 57.65 | N36: =K36*M36 -> 38.6255 | O36: =M36*L36 -> 154.502 | P36: =I36+N36 -> 51.1255 | Q36: =P36*H36 -> 204.502
A37: =IF(G37<>"",1+MAX($A$3:A36),"") -> 25 | D37: 1-1/4" / 1" Dia Gas Pipe Tee | E37: 1 | F37: EA | G37: 0 | H37: =E37*(1+G37) -> 1 | I37: 18.25 | J37: =I37*H37 -> 18.25 | K37: 0.68 | L37: =+K37*H37 -> 0.68 | M37: ='LABOR SHEET'!C$5 -> 57.65 | N37: =K37*M37 -> 39.202 | O37: =M37*L37 -> 39.202 | P37: =I37+N37 -> 57.452 | Q37: =P37*H37 -> 57.452
A38: =IF(G38<>"",1+MAX($A$3:A37),"") -> 26 | D38: 1-1/4" Dia Gas Pipe Tee | E38: 7 | F38: EA | G38: 0 | H38: =E38*(1+G38) -> 7 | I38: 25.5 | J38: =I38*H38 -> 178.5 | K38: 0.69 | L38: =+K38*H38 -> 4.83 | M38: ='LABOR SHEET'!C$5 -> 57.65 | N38: =K38*M38 -> 39.7785 | O38: =M38*L38 -> 278.4495 | P38: =I38+N38 -> 65.2785 | Q38: =P38*H38 -> 456.9495
A39: =IF(G39<>"",1+MAX($A$3:A38),"") -> 27 | D39: 2" / 3/4" Dia Gas Pipe Tee | E39: 2 | F39: EA | G39: 0 | H39: =E39*(1+G39) -> 2 | I39: 30.5 | J39: =I39*H39 -> 61 | K39: 0.7 | L39: =+K39*H39 -> 1.4 | M39: ='LABOR SHEET'!C$5 -> 57.65 | N39: =K39*M39 -> 40.355 | O39: =M39*L39 -> 80.71 | P39: =I39+N39 -> 70.855 | Q39: =P39*H39 -> 141.71
... A56: =IF(G56<>"",1+MAX($A$3:A55),"") -> 44 | D56: 4" / 3" Dia Gas Pipe Reducer | E56: 1 | F56: EA | G56: 0 | H56: =E56*(1+G56) -> 1 | I56: 70.34 | J56: =I56*H56 -> 70.34 | K56: 0.53 | L56: =+K56*H56 -> 0.53 | M56: ='LABOR SHEET'!C$5 -> 57.65 | N56: =K56*M56 -> 30.5545 | O56: =M56*L56 -> 30.5545 | P56: =I56+N56 -> 100.8945 | Q56: =P56*H56 -> 100.8945
A57: =IF(G57<>"",1+MAX($A$3:A56),"")
A58: =IF(G58<>"",1+MAX($A$3:A57),"") | D58: ACCESSORIES
A59: =IF(G59<>"",1+MAX($A$3:A58),"") -> 45 | D59: 3/4" Dia Flexible Connector | E59: 2 | F59: EA | G59: 0 | H59: =E59*(1+G59) -> 2 | I59: 5.12 | J59: =I59*H59 -> 10.24 | K59: 0.4 | L59: =+K59*H59 -> 0.8 | M59: ='LABOR SHEET'!C$5 -> 57.65 | N59: =K59*M59 -> 23.06 | O59: =M59*L59 -> 46.12 | P59: =I59+N59 -> 28.18 | Q59: =P59*H59 -> 56.36
A60: =IF(G60<>"",1+MAX($A$3:A59),"") -> 46 | D60: 3/4" Dia Gas Shut-Off Valve | E60: 2 | F60: EA | G60: 0 | H60: =E60*(1+G60) -> 2 | I60: 35.5 | J60: =I60*H60 -> 71 | K60: 0.65 | L60: =+K60*H60 -> 1.3 | M60: ='LABOR SHEET'!C$5 -> 57.65 | N60: =K60*M60 -> 37.4725 | O60: =M60*L60 -> 74.945 | P60: =I60+N60 -> 72.9725 | Q60: =P60*H60 -> 145.945
A61: =IF(G61<>"",1+MAX($A$3:A60),"") -> 47 | D61: 3/4" Dia Gas Union | E61: 2 | F61: EA | G61: 0 | H61: =E61*(1+G61) -> 2 | I61: 15.45 | J61: =I61*H61 -> 30.9 | K61: 0.6 | L61: =+K61*H61 -> 1.2 | M61: ='LABOR SHEET'!C$5 -> 57.65 | N61: =K61*M61 -> 34.59 | O61: =M61*L61 -> 69.18 | P61: =I61+N61 -> 50.04 | Q61: =P61*H61 -> 100.08
A62: =IF(G62<>"",1+MAX($A$3:A61),"") -> 48 | D62: 3/4" Dia Sediment Trap W/ Cap | E62: 2 | F62: EA | G62: 0 | H62: =E62*(1+G62) -> 2 | I62: 90.45 | J62: =I62*H62 -> 180.9 | K62: 0.65 | L62: =+K62*H62 -> 1.3 | M62: ='LABOR SHEET'!C$5 -> 57.65 | N62: =K62*M62 -> 37.4725 | O62: =M62*L62 -> 74.945 | P62: =I62+N62 -> 127.9225 | Q62: =P62*H62 -> 255.845
A63: =IF(G63<>"",1+MAX($A$3:A62),"") -> 49 | D63: 1" Dia Flexible Connector | E63: 4 | F63: EA | G63: 0 | H63: =E63*(1+G63) -> 4 | I63: 10.45 | J63: =I63*H63 -> 41.8 | K63: 0.45 | L63: =+K63*H63 -> 1.8 | M63: ='LABOR SHEET'!C$5 -> 57.65 | N63: =K63*M63 -> 25.9425 | O63: =M63*L63 -> 103.77 | P63: =I63+N63 -> 36.3925 | Q63: =P63*H63 -> 145.57
A64: =IF(G64<>"",1+MAX($A$3:A63),"") -> 50 | D64: 1" Dia Gas Shut-Off Valve | E64: 4 | F64: EA | G64: 0 | H64: =E64*(1+G64) -> 4 | I64: =35/0.75 -> 46.666667 | J64: =I64*H64 -> 186.66667 | K64: 0.68 | L64: =+K64*H64 -> 2.72 | M64: ='LABOR SHEET'!C$5 -> 57.65 | N64: =K64*M64 -> 39.202 | O64: =M64*L64 -> 156.808 | P64: =I64+N64 -> 85.868667 | Q64: =P64*H64 -> 343.47467
A65: =IF(G65<>"",1+MAX($A$3:A64),"") -> 51 | D65: 1" Dia Gas Union | E65: 4 | F65: EA | G65: 0 | H65: =E65*(1+G65) -> 4 | I65: 20.25 | J65: =I65*H65 -> 81 | K65: 0.62 | L65: =+K65*H65 -> 2.48 | M65: ='LABOR SHEET'!C$5 -> 57.65 | N65: =K65*M65 -> 35.743 | O65: =M65*L65 -> 142.972 | P65: =I65+N65 -> 55.993 | Q65: =P65*H65 -> 223.972
A66: =IF(G66<>"",1+MAX($A$3:A65),"") -> 52 | D66: 1" Dia Sediment Trap W/ Cap | E66: 4 | F66: EA | G66: 0 | H66: =E66*(1+G66) -> 4 | I66: 110 | J66: =I66*H66 -> 440 | K66: 0.4772 | L66: =+K66*H66 -> 1.9088 | M66: ='LABOR SHEET'!C$5 -> 57.65 | N66: =K66*M66 -> 27.51058 | O66: =M66*L66 -> 110.04232 | P66: =I66+N66 -> 137.51058 | Q66: =P66*H66 -> 550.04232
A67: =IF(G67<>"",1+MAX($A$3:A66),"") -> 53 | D67: 1-1/4" Dia Flexible Connector | E67: 7 | F67: EA | G67: 0 | H67: =E67*(1+G67) -> 7 | I67: 15.5 | J67: =I67*H67 -> 108.5 | K67: 0.46 | L67: =+K67*H67 -> 3.22 | M67: ='LABOR SHEET'!C$5 -> 57.65 | N67: =K67*M67 -> 26.519 | O67: =M67*L67 -> 185.633 | P67: =I67+N67 -> 42.019 | Q67: =P67*H67 -> 294.133
A68: =IF(G68<>"",1+MAX($A$3:A67),"") -> 54 | D68: 1-1/4" Dia Gas Shut-Off Valve | E68: 7 | F68: EA | G68: 0 | H68: =E68*(1+G68) -> 7 | I68: 55.2 | J68: =I68*H68 -> 386.4 | K68: 0.69 | L68: =+K68*H68 -> 4.83 | M68: ='LABOR SHEET'!C$5 -> 57.65 | N68: =K68*M68 -> 39.7785 | O68: =M68*L68 -> 278.4495 | P68: =I68+N68 -> 94.9785 | Q68: =P68*H68 -> 664.8495
A69: =IF(G69<>"",1+MAX($A$3:A68),"") -> 55 | D69: 1-1/4" Dia Gas Union | E69: 7 | F69: EA | G69: 0 | H69: =E69*(1+G69) -> 7 | I69: 25.2 | J69: =I69*H69 -> 176.4 | K69: 0.63 | L69: =+K69*H69 -> 4.41 | M69: ='LABOR SHEET'!C$5 -> 57.65 | N69: =K69*M69 -> 36.3195 | O69: =M69*L69 -> 254.2365 | P69: =I69+N69 -> 61.5195 | Q69: =P69*H69 -> 430.6365
A70: =IF(G70<>"",1+MAX($A$3:A69),"") -> 56 | D70: 1-1/4" Dia Sediment Trap W/ Cap | E70: 7 | F70: EA | G70: 0 | H70: =E70*(1+G70) -> 7 | I70: 125 | J70: =I70*H70 -> 875 | K70: 0.55 | L70: =+K70*H70 -> 3.85 | M70: ='LABOR SHEET'!C$5 -> 57.65 | N70: =K70*M70 -> 31.7075 | O70: =M70*L70 -> 221.9525 | P70: =I70+N70 -> 156.7075 | Q70: =P70*H70 -> 1096.9525
A71: =IF(G71<>"",1+MAX($A$3:A70),"") -> 57 | D71: 2" Dia Flexible Connector | E71: 2 | F71: EA | G71: 0 | H71: =E71*(1+G71) -> 2 | I71: 25.5 | J71: =I71*H71 -> 51 | K71: 0.51 | L71: =+K71*H71 -> 1.02 | M71: ='LABOR SHEET'!C$5 -> 57.65 | N71: =K71*M71 -> 29.4015 | O71: =M71*L71 -> 58.803 | P71: =I71+N71 -> 54.9015 | Q71: =P71*H71 -> 109.803
A72: =IF(G72<>"",1+MAX($A$3:A71),"") -> 58 | D72: 2" Dia Gas Shut-Off Valve | E72: 2 | F72: EA | G72: 0 | H72: =E72*(1+G72) -> 2 | I72: 69.5 | J72: =I72*H72 -> 139 | K72: 0.72 | L72: =+K72*H72 -> 1.44 | M72: ='LABOR SHEET'!C$5 -> 57.65 | N72: =K72*M72 -> 41.508 | O72: =M72*L72 -> 83.016 | P72: =I72+N72 -> 111.008 | Q72: =P72*H72 -> 222.016
A73: =IF(G73<>"",1+MAX($A$3:A72),"") -> 59 | D73: 2" Dia Gas Union | E73: 2 | F73: EA | G73: 0 | H73: =E73*(1+G73) -> 2 | I73: 30.5 | J73: =I73*H73 -> 61 | K73: 0.68 | L73: =+K73*H73 -> 1.36 | M73: ='LABOR SHEET'!C$5 -> 57.65 | N73: =K73*M73 -> 39.202 | O73: =M73*L73 -> 78.404 | P73: =I73+N73 -> 69.702 | Q73: =P73*H73 -> 139.404
A74: =IF(G74<>"",1+MAX($A$3:A73),"") -> 60 | D74: 2" Dia Sediment Trap W/ Cap | E74: 2 | F74: EA | G74: 0 | H74: =E74*(1+G74) -> 2 | I74: 150 | J74: =I74*H74 -> 300 | K74: 0.72 | L74: =+K74*H74 -> 1.44 | M74: ='LABOR SHEET'!C$5 -> 57.65 | N74: =K74*M74 -> 41.508 | O74: =M74*L74 -> 83.016 | P74: =I74+N74 -> 191.508 | Q74: =P74*H74 -> 383.016
A75: =IF(G75<>"",1+MAX($A$3:A74),"")
A76: =IF(G76<>"",1+MAX($A$3:A75),"") | D76: VENT PIPES
A77: =IF(G77<>"",1+MAX($A$3:A76),"") | D77: SCHEDULE 40 PVC PIPE ASTM A53, W/ FITTINGS ASTM D2665
A78: =IF(G78<>"",1+MAX($A$3:A77),"") -> 61 | D78: 1-1/2" Dia Vent Pipe | E78: 313.25 | F78: LF | G78: 0.05 | H78: =E78*(1+G78) -> 328.9125 | I78: 4.41 | J78: =I78*H78 -> 1450.5041 | K78: 0.222 | L78: =+K78*H78 -> 73.018575 | M78: ='LABOR SHEET'!C$5 -> 57.65 | N78: =K78*M78 -> 12.7983 | O78: =M78*L78 -> 4209.5208 | P78: =I78+N78 -> 17.2083 | Q78: =P78*H78 -> 5660.025
A79: =IF(G79<>"",1+MAX($A$3:A78),"") -> 62 | D79: 2" Dia Vent Pipe | E79: 392.27 | F79: LF | G79: 0.05 | H79: =E79*(1+G79) -> 411.8835 | I79: 5 | J79: =I79*H79 -> 2059.4175 | K79: 0.271 | L79: =+K79*H79 -> 111.62043 | M79: ='LABOR SHEET'!C$5 -> 57.65 | N79: =K79*M79 -> 15.62315 | O79: =M79*L79 -> 6434.9177 | P79: =I79+N79 -> 20.62315 | Q79: =P79*H79 -> 8494.3352
A80: =IF(G80<>"",1+MAX($A$3:A79),"") -> 63 | D80: 3" Dia Vent Pipe | E80: 96.29 | F80: LF | G80: 0.05 | H80: =E80*(1+G80) -> 101.1045 | I80: 8.15 | J80: =I80*H80 -> 824.00167 | K80: 0.302 | L80: =+K80*H80 -> 30.533559 | M80: ='LABOR SHEET'!C$5 -> 57.65 | N80: =K80*M80 -> 17.4103 | O80: =M80*L80 -> 1760.2597 | P80: =I80+N80 -> 25.5603 | Q80: =P80*H80 -> 2584.2614
A81: =IF(G81<>"",1+MAX($A$3:A80),"") -> 64 | D81: 4" Dia Vent Pipe | E81: 6.37 | F81: LF | G81: 0.05 | H81: =E81*(1+G81) -> 6.6885 | I81: 10.45 | J81: =I81*H81 -> 69.894825 | K81: 0.333 | L81: =+K81*H81 -> 2.2272705 | M81: ='LABOR SHEET'!C$5 -> 57.65 | N81: =K81*M81 -> 19.19745 | O81: =M81*L81 -> 128.40214 | P81: =I81+N81 -> 29.64745 | Q81: =P81*H81 -> 198.29697
A82: =IF(G82<>"",1+MAX($A$3:A81),"")
A83: =IF(G83<>"",1+MAX($A$3:A82),"") | D83: FITTINGS
A84: =IF(G84<>"",1+MAX($A$3:A83),"") -> 65 | D84: 1-1/2" Dia Vent Pipe 45 Deg Elbow | E84: 9 | F84: EA | G84: 0 | H84: =E84*(1+G84) -> 9 | I84: 2.5 | J84: =I84*H84 -> 22.5 | K84: 0.45 | L84: =+K84*H84 -> 4.05 | M84: ='LABOR SHEET'!C$5 -> 57.65 | N84: =K84*M84 -> 25.9425 | O84: =M84*L84 -> 233.4825 | P84: =I84+N84 -> 28.4425 | Q84: =P84*H84 -> 255.9825
A85: =IF(G85<>"",1+MAX($A$3:A84),"") -> 66 | D85: 2" Dia Vent Pipe 45 Deg Elbow | E85: 4 | F85: EA | G85: 0 | H85: =E85*(1+G85) -> 4 | I85: 4.54 | J85: =I85*H85 -> 18.16 | K85: 0.46 | L85: =+K85*H85 -> 1.84 | M85: ='LABOR SHEET'!C$5 -> 57.65 | N85: =K85*M85 -> 26.519 | O85: =M85*L85 -> 106.076 | P85: =I85+N85 -> 31.059 | Q85: =P85*H85 -> 124.236
A86: =IF(G86<>"",1+MAX($A$3:A85),"") -> 67 | D86: 1-1/2" Dia Vent Pipe 90 Deg Elbow | E86: 35 | F86: EA | G86: 0 | H86: =E86*(1+G86) -> 35 | I86: 7.5 | J86: =I86*H86 -> 262.5 | K86: 0.47 | L86: =+K86*H86 -> 16.45 | M86: ='LABOR SHEET'!C$5 -> 57.65 | N86: =K86*M86 -> 27.0955 | O86: =M86*L86 -> 948.3425 | P86: =I86+N86 -> 34.5955 | Q86: =P86*H86 -> 1210.8425
A87: =IF(G87<>"",1+MAX($A$3:A86),"") -> 68 | D87: 2" Dia Vent Pipe 90 Deg Elbow | E87: 35 | F87: EA | G87: 0 | H87: =E87*(1+G87) -> 35 | I87: 10.5 | J87: =I87*H87 -> 367.5 | K87: 0.48 | L87: =+K87*H87 -> 16.8 | M87: ='LABOR SHEET'!C$5 -> 57.65 | N87: =K87*M87 -> 27.672 | O87: =M87*L87 -> 968.52 | P87: =I87+N87 -> 38.172 | Q87: =P87*H87 -> 1336.02
A88: =IF(G88<>"",1+MAX($A$3:A87),"") -> 69 | D88: 1-1/2" Dia Vent Pipe Tee | E88: 3 | F88: EA | G88: 0 | H88: =E88*(1+G88) -> 3 | I88: 13.09 | J88: =I88*H88 -> 39.27 | K88: 0.5 | L88: =+K88*H88 -> 1.5 | M88: ='LABOR SHEET'!C$5 -> 57.65 | N88: =K88*M88 -> 28.825 | O88: =M88*L88 -> 86.475 | P88: =I88+N88 -> 41.915 | Q88: =P88*H88 -> 125.745
A89: =IF(G89<>"",1+MAX($A$3:A88),"") -> 70 | D89: 2" / 1-1/2" Dia Vent Pipe Tee | E89: 10 | F89: EA | G89: 0 | H89: =E89*(1+G89) -> 10 | I89: 19.2 | J89: =I89*H89 -> 192 | K89: 0.51 | L89: =+K89*H89 -> 5.1 | M89: ='LABOR SHEET'!C$5 -> 57.65 | N89: =K89*M89 -> 29.4015 | O89: =M89*L89 -> 294.015 | P89: =I89+N89 -> 48.6015 | Q89: =P89*H89 -> 486.015
A90: =IF(G90<>"",1+MAX($A$3:A89),"") -> 71 | D90: 2" Dia Vent Pipe Tee | E90: 18 | F90: EA | G90: 0 | H90: =E90*(1+G90) -> 18 | I90: 25.2 | J90: =I90*H90 -> 453.6 | K90: 0.52 | L90: =+K90*H90 -> 9.36 | M90: ='LABOR SHEET'!C$5 -> 57.65 | N90: =K90*M90 -> 29.978 | O90: =M90*L90 -> 539.604 | P90: =I90+N90 -> 55.178 | Q90: =P90*H90 -> 993.204
A91: =IF(G91<>"",1+MAX($A$3:A90),"") -> 72 | D91: 3" / 1-1/2" Dia Vent Pipe Tee | E91: 3 | F91: EA | G91: 0 | H91: =E91*(1+G91) -> 3 | I91: 29.5 | J91: =I91*H91 -> 88.5 | K91: 0.53 | L91: =+K91*H91 -> 1.59 | M91: ='LABOR SHEET'!C$5 -> 57.65 | N91: =K91*M91 -> 30.5545 | O91: =M91*L91 -> 91.6635 | P91: =I91+N91 -> 60.0545 | Q91: =P91*H91 -> 180.1635
A92: =IF(G92<>"",1+MAX($A$3:A91),"") -> 73 | D92: 3" / 2" Dia Vent Pipe Tee | E92: 9 | F92: EA | G92: 0 | H92: =E92*(1+G92) -> 9 | I92: 34.5 | J92: =I92*H92 -> 310.5 | K92: 0.54 | L92: =+K92*H92 -> 4.86 | M92: ='LABOR SHEET'!C$5 -> 57.65 | N92: =K92*M92 -> 31.131 | O92: =M92*L92 -> 280.179 | P92: =I92+N92 -> 65.631 | Q92: =P92*H92 -> 590.679
A93: =IF(G93<>"",1+MAX($A$3:A92),"") -> 74 | D93: 3" Dia Vent Pipe Tee | E93: 5 | F93: EA | G93: 0 | H93: =E93*(1+G93) -> 5 | I93: 38.5 | J93: =I93*H93 -> 192.5 | K93: 0.55 | L93: =+K93*H93 -> 2.75 | M93: ='LABOR SHEET'!C$5 -> 57.65 | N93: =K93*M93 -> 31.7075 | O93: =M93*L93 -> 158.5375 | P93: =I93+N93 -> 70.2075 | Q93: =P93*H93 -> 351.0375
A94: =IF(G94<>"",1+MAX($A$3:A93),"") -> 75 | D94: 4" Dia Vent Pipe Tee | E94: 1 | F94: EA | G94: 0 | H94: =E94*(1+G94) -> 1 | I94: 43.73 | J94: =I94*H94 -> 43.73 | K94: 0.56 | L94: =+K94*H94 -> 0.56 | M94: ='LABOR SHEET'!C$5 -> 57.65 | N94: =K94*M94 -> 32.284 | O94: =M94*L94 -> 32.284 | P94: =I94+N94 -> 76.014 | Q94: =P94*H94 -> 76.014
A95: =IF(G95<>"",1+MAX($A$3:A94),"") -> 76 | D95: 2" / 1-1/2" Dia Vent Pipe Reducer | E95: 9 | F95: EA | G95: 0 | H95: =E95*(1+G95) -> 9 | I95: 13.5 | J95: =I95*H95 -> 121.5 | K95: 0.38 | L95: =+K95*H95 -> 3.42 | M95: ='LABOR SHEET'!C$5 -> 57.65 | N95: =K95*M95 -> 21.907 | O95: =M95*L95 -> 197.163 | P95: =I95+N95 -> 35.407 | Q95: =P95*H95 -> 318.663
... A99: =IF(G99<>"",1+MAX($A$3:A98),"") -> 80 | D99: 4" / 3" Dia Vent Pipe Reducer | E99: 1 | F99: EA | G99: 0 | H99: =E99*(1+G99) -> 1 | I99: 55.2 | J99: =I99*H99 -> 55.2 | K99: 0.42 | L99: =+K99*H99 -> 0.42 | M99: ='LABOR SHEET'!C$5 -> 57.65 | N99: =K99*M99 -> 24.213 | O99: =M99*L99 -> 24.213 | P99: =I99+N99 -> 79.413 | Q99: =P99*H99 -> 79.413
A100: =IF(G100<>"",1+MAX($A$3:A99),"")
A101: =IF(G101<>"",1+MAX($A$3:A100),"") | D101: SANITARY PIPES - BELOW GRADE
A102: =IF(G102<>"",1+MAX($A$3:A101),"") | D102: SCHEDULE 40 PVC PIPE ASTM A53, W/ FITTINGS ASTM D2665
A103: =IF(G103<>"",1+MAX($A$3:A102),"") -> 81 | D103: 2" Dia Sanitary Pipe | E103: 250.47 | F103: LF | G103: 0.05 | H103: =E103*(1+G103) -> 262.9935 | I103: 5 | J103: =I103*H103 -> 1314.9675 | K103: 0.271 | L103: =+K103*H103 -> 71.271238 | M103: ='LABOR SHEET'!C$5 -> 57.65 | N103: =K103*M103 -> 15.62315 | O103: =M103*L103 -> 4108.7869 | P103: =I103+N103 -> 20.62315 | Q103: =P103*H103 -> 5423.7544
A104: =IF(G104<>"",1+MAX($A$3:A103),"") -> 82 | D104: 3" Dia Sanitary Pipe | E104: 280.51 | F104: LF | G104: 0.05 | H104: =E104*(1+G104) -> 294.5355 | I104: 8.15 | J104: =I104*H104 -> 2400.4643 | K104: 0.302 | L104: =+K104*H104 -> 88.949721 | M104: ='LABOR SHEET'!C$5 -> 57.65 | N104: =K104*M104 -> 17.4103 | O104: =M104*L104 -> 5127.9514 | P104: =I104+N104 -> 25.5603 | Q104: =P104*H104 -> 7528.4157
A105: =IF(G105<>"",1+MAX($A$3:A104),"") -> 83 | D105: 4" Dia Sanitary Pipe | E105: 348.47 | F105: LF | G105: 0.05 | H105: =E105*(1+G105) -> 365.8935 | I105: 10.45 | J105: =I105*H105 -> 3823.5871 | K105: 0.333 | L105: =+K105*H105 -> 121.84254 | M105: ='LABOR SHEET'!C$5 -> 57.65 | N105: =K105*M105 -> 19.19745 | O105: =M105*L105 -> 7024.2222 | P105: =I105+N105 -> 29.64745 | Q105: =P105*H105 -> 10847.809
A106: =IF(G106<>"",1+MAX($A$3:A105),"") -> 84 | D106: 6" Dia Sanitary Pipe | E106: 136.79 | F106: LF | G106: 0.05 | H106: =E106*(1+G106) -> 143.6295 | I106: 17.95 | J106: =I106*H106 -> 2578.1495 | K106: 0.41 | L106: =+K106*H106 -> 58.888095 | M106: ='LABOR SHEET'!C$5 -> 57.65 | N106: =K106*M106 -> 23.6365 | O106: =M106*L106 -> 3394.8987 | P106: =I106+N106 -> 41.5865 | Q106: =P106*H106 -> 5973.0482
A107: =IF(G107<>"",1+MAX($A$3:A106),"") -> 85 | D107: 1-1/2" Dia Vent Pipe | E107: 11.56 | F107: LF | G107: 0.05 | H107: =E107*(1+G107) -> 12.138 | I107: 4.41 | J107: =I107*H107 -> 53.52858 | K107: 0.222 | L107: =+K107*H107 -> 2.694636 | M107: ='LABOR SHEET'!C$5 -> 57.65 | N107: =K107*M107 -> 12.7983 | O107: =M107*L107 -> 155.34577 | P107: =I107+N107 -> 17.2083 | Q107: =P107*H107 -> 208.87435
A108: =IF(G108<>"",1+MAX($A$3:A107),"")
A109: =IF(G109<>"",1+MAX($A$3:A108),"") | D109: FITTINGS
A110: =IF(G110<>"",1+MAX($A$3:A109),"") -> 86 | D110: 2" Dia PVC Pipe 90 Deg Elbow | E110: 34 | F110: EA | G110: 0 | H110: =E110*(1+G110) -> 34 | I110: 8.96 | J110: =I110*H110 -> 304.64 | K110: 0.36 | L110: =+K110*H110 -> 12.24 | M110: ='LABOR SHEET'!C$5 -> 57.65 | N110: =K110*M110 -> 20.754 | O110: =M110*L110 -> 705.636 | P110: =I110+N110 -> 29.714 | Q110: =P110*H110 -> 1010.276
A111: =IF(G111<>"",1+MAX($A$3:A110),"") -> 87 | D111: 3" Dia PVC Pipe 90 Deg Elbow | E111: 20 | F111: EA | G111: 0 | H111: =E111*(1+G111) -> 20 | I111: 15.5 | J111: =I111*H111 -> 310 | K111: 0.37 | L111: =+K111*H111 -> 7.4 | M111: ='LABOR SHEET'!C$5 -> 57.65 | N111: =K111*M111 -> 21.3305 | O111: =M111*L111 -> 426.61 | P111: =I111+N111 -> 36.8305 | Q111: =P111*H111 -> 736.61
A112: =IF(G112<>"",1+MAX($A$3:A111),"") -> 88 | D112: 4" Dia PVC Pipe 90 Deg Elbow | E112: 24 | F112: EA | G112: 0 | H112: =E112*(1+G112) -> 24 | I112: 19.5 | J112: =I112*H112 -> 468 | K112: 0.38 | L112: =+K112*H112 -> 9.12 | M112: ='LABOR SHEET'!C$5 -> 57.65 | N112: =K112*M112 -> 21.907 | O112: =M112*L112 -> 525.768 | P112: =I112+N112 -> 41.407 | Q112: =P112*H112 -> 993.768
A113: =IF(G113<>"",1+MAX($A$3:A112),"") -> 89 | D113: 2" Dia PVC Pipe 45 Deg Elbow | E113: 10 | F113: EA | G113: 0 | H113: =E113*(1+G113) -> 10 | I113: 10.5 | J113: =I113*H113 -> 105 | K113: 0.37 | L113: =+K113*H113 -> 3.7 | M113: ='LABOR SHEET'!C$5 -> 57.65 | N113: =K113*M113 -> 21.3305 | O113: =M113*L113 -> 213.305 | P113: =I113+N113 -> 31.8305 | Q113: =P113*H113 -> 318.305
A114: =IF(G114<>"",1+MAX($A$3:A113),"") -> 90 | D114: 3" Dia PVC Pipe 45 Deg Elbow | E114: 20 | F114: EA | G114: 0 | H114: =E114*(1+G114) -> 20 | I114: 16.5 | J114: =I114*H114 -> 330 | K114: 0.39 | L114: =+K114*H114 -> 7.8 | M114: ='LABOR SHEET'!C$5 -> 57.65 | N114: =K114*M114 -> 22.4835 | O114: =M114*L114 -> 449.67 | P114: =I114+N114 -> 38.9835 | Q114: =P114*H114 -> 779.67
A115: =IF(G115<>"",1+MAX($A$3:A114),"") -> 91 | D115: 4" Dia PVC Pipe 45 Deg Elbow | E115: 8 | F115: EA | G115: 0 | H115: =E115*(1+G115) -> 8 | I115: 22.5 | J115: =I115*H115 -> 180 | K115: 0.4 | L115: =+K115*H115 -> 3.2 | M115: ='LABOR SHEET'!C$5 -> 57.65 | N115: =K115*M115 -> 23.06 | O115: =M115*L115 -> 184.48 | P115: =I115+N115 -> 45.56 | Q115: =P115*H115 -> 364.48
A116: =IF(G116<>"",1+MAX($A$3:A115),"") -> 92 | D116: 2" Dia PVC Pipe Combination Wye | E116: 30 | F116: EA | G116: 0 | H116: =E116*(1+G116) -> 30 | I116: 19.87 | J116: =I116*H116 -> 596.1 | K116: 0.45 | L116: =+K116*H116 -> 13.5 | M116: ='LABOR SHEET'!C$5 -> 57.65 | N116: =K116*M116 -> 25.9425 | O116: =M116*L116 -> 778.275 | P116: =I116+N116 -> 45.8125 | Q116: =P116*H116 -> 1374.375
A117: =IF(G117<>"",1+MAX($A$3:A116),"") -> 93 | D117: 3" / 1-1/2" Dia PVC Pipe Combination Wye | E117: 1 | F117: EA | G117: 0 | H117: =E117*(1+G117) -> 1 | I117: 30.3 | J117: =I117*H117 -> 30.3 | K117: 0.46 | L117: =+K117*H117 -> 0.46 | M117: ='LABOR SHEET'!C$5 -> 57.65 | N117: =K117*M117 -> 26.519 | O117: =M117*L117 -> 26.519 | P117: =I117+N117 -> 56.819 | Q117: =P117*H117 -> 56.819
A118: =IF(G118<>"",1+MAX($A$3:A117),"") -> 94 | D118: 3" / 2" Dia PVC Pipe Wye | E118: 8 | F118: EA | G118: 0 | H118: =E118*(1+G118) -> 8 | I118: 50.2 | J118: =I118*H118 -> 401.6 | K118: 0.47 | L118: =+K118*H118 -> 3.76 | M118: ='LABOR SHEET'!C$5 -> 57.65 | N118: =K118*M118 -> 27.0955 | O118: =M118*L118 -> 216.764 | P118: =I118+N118 -> 77.2955 | Q118: =P118*H118 -> 618.364
A119: =IF(G119<>"",1+MAX($A$3:A118),"") -> 95 | D119: 3" Dia PVC Pipe Wye | E119: 5 | F119: EA | G119: 0 | H119: =E119*(1+G119) -> 5 | I119: 65.5 | J119: =I119*H119 -> 327.5 | K119: 0.48 | L119: =+K119*H119 -> 2.4 | M119: ='LABOR SHEET'!C$5 -> 57.65 | N119: =K119*M119 -> 27.672 | O119: =M119*L119 -> 138.36 | P119: =I119+N119 -> 93.172 | Q119: =P119*H119 -> 465.86
...

Sheet LABOR SHEET
B3: Labor Type | C3: Labor Rate
A5: Plumbing | B5: Plum | C5: 57.65
B9: Wastage
A10: Each/Count | B10: EA | C10: 0
A11: Linear Footage | B11: LF | C11: 0.05
A12: Square Footage | B12: SF | C12: 0.1
A13: Square Yard | B13: SY | C13: 0.1
A14: Cubic Yard | B14: CY | C14: 0.1
A15: Lumpsum | B15: LS | C15: 0
A16: Survery | B16: Survey | C16: 0
A17: Stair Riser | B17: RISER | C17: 0
A18: Blocks Count | B18: BLOCKS | C18: 0
A19: Bags of Pre-Mix Mortar | B19: BAGS | C19: 0
A20: Linear Footage of Wall | B20: LF.Wall | C20: 0.1
A21: Pounds | B21: LBS | C21: 0.1
... A32: N/A | B32: N/A | C32: 0
