Workbook

Sheet Takeoff Breakdown
A2: DETAILED BREAKDOWN OF ITEMS
B3: Project Name | D3: HERFF ROAD COMMERCIAL PHASE I IMPROVEMENTS
B4: Project Address | D4: 10-18 HERFF ROAD, BOERNE, TX 78006
B5: Scope: | D5: SITEWORK
A6: S# | B6: Dwg. | C6: CSI NO | D6: DESCRIPTION | E6: QTY. | F6: Wastage | G6: Qty w/ Waste | H6: UNIT | I6: UNIT LABOR HOUR | J6: TOTAL LABOR HOUR | K6: LABOR WAGE/ HOUR | L6: UNIT LABOR COST | M6: TOTAL LABOR COST | N6: UNIT MATERIAL COST | O6: TOTAL MATERIAL COST | P6: UNIT PRICE (Labor & Material) | Q6: TRADE TOTAL
C7: 1 | D7: DIVISION 01-GENERAL REQUIREMENTS
A8: =IF(F8<>"",1+MAX($A$2:A7),"") -> 1 | D8: Permits | E8: 1 | F8: 0 | G8: =(F8*E8)+E8 -> 1 | H8: LS | I8: 0 | J8: =+I8*G8 -> 0 | K8: 0 | L8: =I8*K8 -> 0 | M8: =K8*J8 -> 0 | N8: 0 | O8: =N8*G8 -> 0 | P8: =(I8*K8)+N8 -> 0 | Q8: 117000
A9: =IF(F9<>"",1+MAX($A$2:A8),"") -> 2 | D9: Supervision and Coordination | E9: 1 | F9: 0 | G9: =(F9*E9)+E9 -> 1 | H9: LS | I9: 0 | J9: =+I9*G9 -> 0 | K9: 0 | L9: =I9*K9 -> 0 | M9: =K9*J9 -> 0 | N9: 0 | O9: =N9*G9 -> 0 | P9: =(I9*K9)+N9 -> 0
A10: =IF(F10<>"",1+MAX($A$2:A9),"") -> 3 | D10: Submittals and Shop drawings | E10: 1 | F10: 0 | G10: =(F10*E10)+E10 -> 1 | H10: LS | I10: 0 | J10: =+I10*G10 -> 0 | K10: 0 | L10: =I10*K10 -> 0 | M10: =K10*J10 -> 0 | N10: 0 | O10: =N10*G10 -> 0 | P10: =(I10*K10)+N10 -> 0
A11: =IF(F11<>"",1+MAX($A$2:A10),"") -> 4 | D11: Final Cleaning | E11: 1 | F11: 0 | G11: =(F11*E11)+E11 -> 1 | H11: LS | I11: 0 | J11: =+I11*G11 -> 0 | K11: 0 | L11: =I11*K11 -> 0 | M11: =K11*J11 -> 0 | N11: 0 | O11: =N11*G11 -> 0 | P11: =(I11*K11)+N11 -> 0
A12: =IF(F12<>"",1+MAX($A$2:A11),"") -> 5 | D12: Mobilization Costs | E12: 1 | F12: 0 | G12: =(F12*E12)+E12 -> 1 | H12: LS | I12: 0 | J12: =+I12*G12 -> 0 | K12: 0 | L12: =I12*K12 -> 0 | M12: =K12*J12 -> 0 | N12: 0 | O12: =N12*G12 -> 0 | P12: =(I12*K12)+N12 -> 0
A13: =IF(F13<>"",1+MAX($A$2:A12),"") -> 6 | D13: Temporary Control & Facilities | E13: 1 | F13: 0 | G13: =(F13*E13)+E13 -> 1 | H13: LS | I13: 0 | J13: =+I13*G13 -> 0 | K13: 0 | L13: =I13*K13 -> 0 | M13: =K13*J13 -> 0 | N13: 0 | O13: =N13*G13 -> 0 | P13: =(I13*K13)+N13 -> 0
A14: =IF(F14<>"",1+MAX($A$2:A13),"") -> 7 | D14: Scaffolding | E14: 1 | F14: 0 | G14: =(F14*E14)+E14 -> 1 | H14: LS | I14: 0 | J14: =+I14*G14 -> 0 | K14: 0 | L14: =I14*K14 -> 0 | M14: =K14*J14 -> 0 | N14: 0 | O14: =N14*G14 -> 0 | P14: =(I14*K14)+N14 -> 0
A15: =IF(F15<>"",1+MAX($A$2:A14),"") | D15: SUBTOTAL | Q15: =SUM(Q8:Q14) -> 117000
A16: =IF(F16<>"",1+MAX($A$2:A15),"")
A17: =IF(F17<>"",1+MAX($A$2:A16),"") | C17: 2 | D17: DIVISION 02- EXISTING CONDITIONS
A18: =IF(F18<>"",1+MAX($A$2:A17),"") | D18: SITE DEMOLITION
A19: =IF(F19<>"",1+MAX($A$2:A18),"") -> 8 | B19: C2.0 | D19: Existing Structure To Be Removed | E19: 955 | F19: 0 | G19: =(F19*E19)+E19 -> 955 | H19: SF | I19: 0.028 | J19: =+I19*G19 -> 26.74 | K19: ='LABOR SHEET'!$C$5 -> 45 | L19: =I19*K19 -> 1.26 | M19: =K19*J19 -> 1203.3 | N19: 0 | O19: =N19*G19 -> 0 | P19: =(I19*K19)+N19 -> 1.26 | Q19: =P19*G19 -> 1203.3
A20: =IF(F20<>"",1+MAX($A$2:A19),"") -> 9 | D20: Existing Fence & Walls & Gate To Be Removed | E20: 355 | F20: 0 | G20: =(F20*E20)+E20 -> 355 | H20: LF | I20: 0.122 | J20: =+I20*G20 -> 43.31 | K20: ='LABOR SHEET'!$C$5 -> 45 | L20: =I20*K20 -> 5.49 | M20: =K20*J20 -> 1948.95 | N20: 0 | O20: =N20*G20 -> 0 | P20: =(I20*K20)+N20 -> 5.49 | Q20: =P20*G20 -> 1948.95
A21: =IF(F21<>"",1+MAX($A$2:A20),"") -> 10 | D21: Existing Side Walk To Be Removed | E21: 675 | F21: 0 | G21: =(F21*E21)+E21 -> 675 | H21: SF | I21: 0.024 | J21: =+I21*G21 -> 16.2 | K21: ='LABOR SHEET'!$C$5 -> 45 | L21: =I21*K21 -> 1.08 | M21: =K21*J21 -> 729 | N21: 0 | O21: =N21*G21 -> 0 | P21: =(I21*K21)+N21 -> 1.08 | Q21: =P21*G21 -> 729
A22: =IF(F22<>"",1+MAX($A$2:A21),"") -> 11 | D22: Existing Wire Fence To Be Removed | E22: 636 | F22: 0 | G22: =(F22*E22)+E22 -> 636 | H22: LF | I22: 0.1 | J22: =+I22*G22 -> 63.6 | K22: ='LABOR SHEET'!$C$5 -> 45 | L22: =I22*K22 -> 4.5 | M22: =K22*J22 -> 2862 | N22: 0 | O22: =N22*G22 -> 0 | P22: =(I22*K22)+N22 -> 4.5 | Q22: =P22*G22 -> 2862
A23: =IF(F23<>"",1+MAX($A$2:A22),"") -> 12 | D23: Existing Asphalt Pavement To Be Removed | E23: 7205 | F23: 0 | G23: =(F23*E23)+E23 -> 7205 | H23: SF | I23: 0.028 | J23: =+I23*G23 -> 201.74 | K23: ='LABOR SHEET'!$C$5 -> 45 | L23: =I23*K23 -> 1.26 | M23: =K23*J23 -> 9078.3 | N23: 0 | O23: =N23*G23 -> 0 | P23: =(I23*K23)+N23 -> 1.26 | Q23: =P23*G23 -> 9078.3
A24: =IF(F24<>"",1+MAX($A$2:A23),"") -> 13 | D24: Sawcut For Pavement Removal | E24: 49 | F24: 0 | G24: =(F24*E24)+E24 -> 49 | H24: LF | I24: 0.045 | J24: =+I24*G24 -> 2.205 | K24: ='LABOR SHEET'!$C$5 -> 45 | L24: =I24*K24 -> 2.025 | M24: =K24*J24 -> 99.225 | N24: 0 | O24: =N24*G24 -> 0 | P24: =(I24*K24)+N24 -> 2.025 | Q24: =P24*G24 -> 99.225
A26: =IF(F26<>"",1+MAX($A$2:A24),"") | D26: Landscaping Demolition | M26: =K26*J26 -> 0
A27: =IF(F27<>"",1+MAX($A$2:A26),"") -> 14 | D27: Existing Oak Trees To Be Removed | E27: =44*2 -> 88 | F27: 0 | G27: =(F27*E27)+E27 -> 88 | H27: EA | I27: 2.85 | J27: =+I27*G27 -> 250.8 | K27: ='LABOR SHEET'!$C$5 -> 45 | L27: =I27*K27 -> 128.25 | M27: =K27*J27 -> 11286 | N27: 0 | O27: =N27*G27 -> 0 | P27: =(I27*K27)+N27 -> 128.25 | Q27: =P27*G27 -> 11286
A28: =IF(F28<>"",1+MAX($A$2:A27),"") -> 15 | D28: Existing Oak Trees To Be Removed | E28: 41 | F28: 0 | G28: =(F28*E28)+E28 -> 41 | H28: EA | I28: 2.85 | J28: =+I28*G28 -> 116.85 | K28: ='LABOR SHEET'!$C$5 -> 45 | L28: =I28*K28 -> 128.25 | M28: =K28*J28 -> 5258.25 | N28: 0 | O28: =N28*G28 -> 0 | P28: =(I28*K28)+N28 -> 128.25 | Q28: =P28*G28 -> 5258.25
A29: =IF(F29<>"",1+MAX($A$2:A28),"") -> 16 | D29: Existing Oak Trees To Be Removed | E29: 53 | F29: 0 | G29: =(F29*E29)+E29 -> 53 | H29: EA | I29: 2.85 | J29: =+I29*G29 -> 151.05 | K29: ='LABOR SHEET'!$C$5 -> 45 | L29: =I29*K29 -> 128.25 | M29: =K29*J29 -> 6797.25 | N29: 0 | O29: =N29*G29 -> 0 | P29: =(I29*K29)+N29 -> 128.25 | Q29: =P29*G29 -> 6797.25
A30: =IF(F30<>"",1+MAX($A$2:A29),"") -> 17 | D30: Existing Oak Trees To Be Removed | E30: 50 | F30: 0 | G30: =(F30*E30)+E30 -> 50 | H30: EA | I30: 2.85 | J30: =+I30*G30 -> 142.5 | K30: ='LABOR SHEET'!$C$5 -> 45 | L30: =I30*K30 -> 128.25 | M30: =K30*J30 -> 6412.5 | N30: 0 | O30: =N30*G30 -> 0 | P30: =(I30*K30)+N30 -> 128.25 | Q30: =P30*G30 -> 6412.5
A31: =IF(F31<>"",1+MAX($A$2:A30),"") -> 18 | D31: Existing Oak Trees To Be Removed | E31: 49 | F31: 0 | G31: =(F31*E31)+E31 -> 49 | H31: EA | I31: 2.85 | J31: =+I31*G31 -> 139.65 | K31: ='LABOR SHEET'!$C$5 -> 45 | L31: =I31*K31 -> 128.25 | M31: =K31*J31 -> 6284.25 | N31: 0 | O31: =N31*G31 -> 0 | P31: =(I31*K31)+N31 -> 128.25 | Q31: =P31*G31 -> 6284.25
A32: =IF(F32<>"",1+MAX($A$2:A31),"") -> 19 | D32: Existing Oak Trees To Be Removed | E32: 61 | F32: 0 | G32: =(F32*E32)+E32 -> 61 | H32: EA | I32: 2.85 | J32: =+I32*G32 -> 173.85 | K32: ='LABOR SHEET'!$C$5 -> 45 | L32: =I32*K32 -> 128.25 | M32: =K32*J32 -> 7823.25 | N32: 0 | O32: =N32*G32 -> 0 | P32: =(I32*K32)+N32 -> 128.25 | Q32: =P32*G32 -> 7823.25
A33: =IF(F33<>"",1+MAX($A$2:A32),"") -> 20 | D33: Existing Oak Trees To Be Removed | E33: =90+1401 -> 1491 | F33: 0 | G33: =(F33*E33)+E33 -> 1491 | H33: EA | I33: 2.85 | J33: =+I33*G33 -> 4249.35 | K33: ='LABOR SHEET'!$C$5 -> 45 | L33: =I33*K33 -> 128.25 | M33: =K33*J33 -> 191220.75 | N33: 0 | O33: =N33*G33 -> 0 | P33: =(I33*K33)+N33 -> 128.25 | Q33: =P33*G33 -> 191220.75
A34: =IF(F34<>"",1+MAX($A$2:A33),"") -> 21 | D34: Existing Pecan Trees To Be Removed | E34: 50 | F34: 0 | G34: =(F34*E34)+E34 -> 50 | H34: EA | I34: 2.85 | J34: =+I34*G34 -> 142.5 | K34: ='LABOR SHEET'!$C$5 -> 45 | L34: =I34*K34 -> 128.25 | M34: =K34*J34 -> 6412.5 | N34: 0 | O34: =N34*G34 -> 0 | P34: =(I34*K34)+N34 -> 128.25 | Q34: =P34*G34 -> 6412.5
A36: =IF(F36<>"",1+MAX($A$2:A34),"") -> 22 | D36: Hauling Of demolation Materials | E36: 1 | F36: 0 | G36: =(F36*E36)+E36 -> 1 | H36: LS | I36: 0 | J36: =+I36*G36 -> 0 | K36: ='LABOR SHEET'!$C$5 -> 45 | L36: =I36*K36 -> 0 | M36: =K36*J36 -> 0 | N36: =1250*4 -> 5000 | O36: =N36*G36 -> 5000 | P36: =(I36*K36)+N36 -> 5000 | Q36: =P36*G36 -> 5000
A37: =IF(F37<>"",1+MAX($A$2:A36),"") | D37: SUBTOTAL | Q37: =SUM(Q19:Q36) -> 262415.53
A38: =IF(F38<>"",1+MAX($A$2:A37),"")
A39: =IF(F39<>"",1+MAX($A$2:A38),"") | C39: 31 | D39: DIVISION 31- EARTHWORK
A40: =IF(F40<>"",1+MAX($A$2:A39),"") | D40: GRADING
A41: =IF(F41<>"",1+MAX($A$2:A40),"") -> 23 | B41: C2.0-C9 | D41: Total Cut | E41: 1685.98 | F41: 0 | G41: =E41*(1+F41) -> 1685.98 | H41: CY | I41: 0.22 | J41: =+I41*G41 -> 370.9156 | K41: ='LABOR SHEET'!$C$4 -> 45 | L41: =I41*K41 -> 9.9 | M41: =K41*J41 -> 16691.202 | N41: 5 | O41: =N41*G41 -> 8429.9 | P41: =(I41*K41)+N41 -> 14.9 | Q41: =P41*G41 -> 25121.102
A42: =IF(F42<>"",1+MAX($A$2:A41),"") -> 24 | D42: Total Fill | E42: 6718.51 | F42: 0 | G42: =E42*(1+F42) -> 6718.51 | H42: CY | I42: 0.2 | J42: =+I42*G42 -> 1343.702 | K42: ='LABOR SHEET'!$C$4 -> 45 | L42: =I42*K42 -> 9 | M42: =K42*J42 -> 60466.59 | N42: 5 | O42: =N42*G42 -> 33592.55 | P42: =(I42*K42)+N42 -> 14 | Q42: =P42*G42 -> 94059.14
A43: =IF(F43<>"",1+MAX($A$2:A42),"") -> 25 | D43: Soil To Be Import | E43: =6718.51-1685.98-1475+704 -> 4261.53 | F43: 0 | G43: =E43*(1+F43) -> 4261.53 | H43: CY | I43: 0.44 | J43: =+I43*G43 -> 1875.0732 | K43: ='LABOR SHEET'!$C$4 -> 45 | L43: =I43*K43 -> 19.8 | M43: =K43*J43 -> 84378.294 | N43: 10 | O43: =N43*G43 -> 42615.3 | P43: =(I43*K43)+N43 -> 29.8 | Q43: =P43*G43 -> 126993.59
A44: =IF(F44<>"",1+MAX($A$2:A43),"")
A45: =IF(F45<>"",1+MAX($A$2:A44),"") | D45: SUBTOTAL | Q45: =SUM(Q40:Q43) -> 246173.84
A46: =IF(F46<>"",1+MAX($A$2:A45),"")
A47: =IF(F47<>"",1+MAX($A$2:A46),"") | C47: 32 | D47: DIVISION 32- EXTERIOR IMPROVEMENTS
A48: =IF(F48<>"",1+MAX($A$2:A47),"") | D48: EXTERIOR IMPROVEMENTS
A49: =IF(F49<>"",1+MAX($A$2:A48),"") | B49: C2.0-F1.1 | D49: Wood Fence
A50: =IF(F50<>"",1+MAX($A$2:A49),"") -> 26 | D50: "G" Wood Fence (8' H ) | E50: 46 | F50: 0.05 | G50: =E50*(1+F50) -> 48.3 | H50: LF | I50: =0.024*8 -> 0.192 | J50: =+I50*G50 -> 9.2736 | K50: ='LABOR SHEET'!$C$5 -> 45 | L50: =I50*K50 -> 8.64 | M50: =K50*J50 -> 417.312 | N50: =2.7*8 -> 21.6 | O50: =N50*G50 -> 1043.28 | P50: =(I50*K50)+N50 -> 30.24 | Q50: =P50*G50 -> 1460.592
A52: =IF(F52<>"",1+MAX($A$2:A50),"") | D52: (Light Duty) - Asphalt Pavement
A53: =IF(F53<>"",1+MAX($A$2:A52),"") -> 27 | D53: "A1" 1.5" Thick Type "D" Hot Asphalt Mix Pavement (Light Duty) | E53: 14989 | F53: 0.1 | G53: =E53*(1+F53) -> 16487.9 | H53: SF | I53: 0.032 | J53: =+I53*G53 -> 527.6128 | K53: ='LABOR SHEET'!$C$5 -> 45 | L53: =I53*K53 -> 1.44 | M53: =K53*J53 -> 23742.576 | N53: 1 | O53: =N53*G53 -> 16487.9 | P53: =(I53*K53)+N53 -> 2.44 | Q53: =P53*G53 -> 40230.476
A54: =IF(F54<>"",1+MAX($A$2:A53),"") -> 28 | D54: 9" Thick Compacted Flexible Base | E54: =0.75*14989/27 -> 416.36111 | F54: 0.1 | G54: =E54*(1+F54) -> 457.99722 | H54: CY | I54: 1 | J54: =+I54*G54 -> 457.99722 | K54: ='LABOR SHEET'!$C$5 -> 45 | L54: =I54*K54 -> 45 | M54: =K54*J54 -> 20609.875 | N54: 68.2 | O54: =N54*G54 -> 31235.411 | P54: =(I54*K54)+N54 -> 113.2 | Q54: =P54*G54 -> 51845.286
A55: =IF(F55<>"",1+MAX($A$2:A54),"") -> 29 | D55: 6" Thick Compacted Sub-Grade | E55: 14989 | F55: 0.1 | G55: =E55*(1+F55) -> 16487.9 | H55: SF | I55: 0.007 | J55: =+I55*G55 -> 115.4153 | K55: ='LABOR SHEET'!$C$5 -> 45 | L55: =I55*K55 -> 0.315 | M55: =K55*J55 -> 5193.6885 | N55: 0.4 | O55: =N55*G55 -> 6595.16 | P55: =(I55*K55)+N55 -> 0.715 | Q55: =P55*G55 -> 11788.849
A57: =IF(F57<>"",1+MAX($A$2:A55),"") | D57: Heavy-Duty Concrete Pavement
A58: =IF(F58<>"",1+MAX($A$2:A57),"") -> 30 | D58: "A3" 6" Thick Heavy-Duty Concrete Pavement W/ Reinforcement | E58: =0.5*2148/27 -> 39.777778 | F58: 0.1 | G58: =E58*(1+F58) -> 43.755556 | H58: CY | I58: 2.7 | J58: =+I58*G58 -> 118.14 | K58: ='LABOR SHEET'!$C$5 -> 45 | L58: =I58*K58 -> 121.5 | M58: =K58*J58 -> 5316.3 | N58: 235 | O58: =N58*G58 -> 10282.556 | P58: =(I58*K58)+N58 -> 356.5 | Q58: =P58*G58 -> 15598.856
A59: =IF(F59<>"",1+MAX($A$2:A58),"") -> 31 | D59: 6" Thick Compacted Sub-Grade | E59: 2148 | F59: 0.1 | G59: =E59*(1+F59) -> 2362.8 | H59: SF | I59: 0.007 | J59: =+I59*G59 -> 16.5396 | K59: ='LABOR SHEET'!$C$5 -> 45 | L59: =I59*K59 -> 0.315 | M59: =K59*J59 -> 744.282 | N59: 0.4 | O59: =N59*G59 -> 945.12 | P59: =(I59*K59)+N59 -> 0.715 | Q59: =P59*G59 -> 1689.402
A60: =IF(F60<>"",1+MAX($A$2:A59),"") -> 32 | D60: 1/2" Expansion Joint 1/2" X3/8" Sealant | E60: =2148/30*2 -> 143.2 | F60: 0.05 | G60: =E60*(1+F60) -> 150.36 | H60: LF | I60: 0.018 | J60: =+I60*G60 -> 2.70648 | K60: ='LABOR SHEET'!$C$5 -> 45 | L60: =I60*K60 -> 0.81 | M60: =K60*J60 -> 121.7916 | N60: 0.82 | O60: =N60*G60 -> 123.2952 | P60: =(I60*K60)+N60 -> 1.63 | Q60: =P60*G60 -> 245.0868
A61: =IF(F61<>"",1+MAX($A$2:A60),"") -> 33 | D61: 1/2"X1/8" Bond Breaker Material | E61: =2148/30*2 -> 143.2 | F61: 0.05 | G61: =E61*(1+F61) -> 150.36 | H61: LF | I61: 0.01 | J61: =+I61*G61 -> 1.5036 | K61: ='LABOR SHEET'!$C$5 -> 45 | L61: =I61*K61 -> 0.45 | M61: =K61*J61 -> 67.662 | N61: 0.22 | O61: =N61*G61 -> 33.0792 | P61: =(I61*K61)+N61 -> 0.67 | Q61: =P61*G61 -> 100.7412
A62: =IF(F62<>"",1+MAX($A$2:A61),"") -> 34 | D62: 1/2" X 6" Resilient Filler | E62: =2148/30*2 -> 143.2 | F62: 0.05 | G62: =E62*(1+F62) -> 150.36 | H62: LF | I62: 0.02 | J62: =+I62*G62 -> 3.0072 | K62: ='LABOR SHEET'!$C$5 -> 45 | L62: =I62*K62 -> 0.9 | M62: =K62*J62 -> 135.324 | N62: 1.25 | O62: =N62*G62 -> 187.95 | P62: =(I62*K62)+N62 -> 2.15 | Q62: =P62*G62 -> 323.274
A63: =IF(F63<>"",1+MAX($A$2:A62),"") -> 35 | D63: 1/2" Construction Joint 1/2" X3/8" Sealant | E63: =2148/20*2 -> 214.8 | F63: 0.05 | G63: =E63*(1+F63) -> 225.54 | H63: LF | I63: 0.018 | J63: =+I63*G63 -> 4.05972 | K63: ='LABOR SHEET'!$C$5 -> 45 | L63: =I63*K63 -> 0.81 | M63: =K63*J63 -> 182.6874 | N63: 0.82 | O63: =N63*G63 -> 184.9428 | P63: =(I63*K63)+N63 -> 1.63 | Q63: =P63*G63 -> 367.6302
A64: =IF(F64<>"",1+MAX($A$2:A63),"") -> 36 | D64: Formwork | E64: =327*0.5 -> 163.5 | F64: 0.1 | G64: =E64*(1+F64) -> 179.85 | H64: SF | I64: 0.018 | J64: =+I64*G64 -> 3.2373 | K64: ='LABOR SHEET'!$C$5 -> 45 | L64: =I64*K64 -> 0.81 | M64: =K64*J64 -> 145.6785 | N64: 3 | O64: =N64*G64 -> 539.55 | P64: =(I64*K64)+N64 -> 3.81 | Q64: =P64*G64 -> 685.2285
A66: =IF(F66<>"",1+MAX($A$2:A64),"") | D66: Concrete Sidewalk
A67: =IF(F67<>"",1+MAX($A$2:A66),"") -> 37 | D67: "B1" 4" Thick Concrete Sidewalk W/ Welded Wire Flat | E67: =0.34*5346/27 -> 67.32 | F67: 0.1 | G67: =E67*(1+F67) -> 74.052 | H67: CY | I67: 2.6 | J67: =+I67*G67 -> 192.5352 | K67: ='LABOR SHEET'!$C$5 -> 45 | L67: =I67*K67 -> 117 | M67: =K67*J67 -> 8664.084 | N67: 198 | O67: =N67*G67 -> 14662.296 | P67: =(I67*K67)+N67 -> 315 | Q67: =P67*G67 -> 23326.38
A68: =IF(F68<>"",1+MAX($A$2:A67),"") -> 38 | D68: Sheets 6" X 6" W2.9 X W2.9 Or #3 Bars @ 12" O.C.B.W. Centered In Slab | E68: 5346 | F68: 0.1 | G68: =E68*(1+F68) -> 5880.6 | H68: SF | I68: 0.008 | J68: =+I68*G68 -> 47.0448 | K68: ='LABOR SHEET'!$C$5 -> 45 | L68: =I68*K68 -> 0.36 | M68: =K68*J68 -> 2117.016 | N68: 0.55 | O68: =N68*G68 -> 3234.33 | P68: =(I68*K68)+N68 -> 0.91 | Q68: =P68*G68 -> 5351.346
A69: =IF(F69<>"",1+MAX($A$2:A68),"") -> 39 | D69: 1" Thick Sand Cushion | E69: =0.084*5346/27 -> 16.632 | F69: 0.1 | G69: =E69*(1+F69) -> 18.2952 | H69: CY | I69: 0.8 | J69: =+I69*G69 -> 14.63616 | K69: ='LABOR SHEET'!$C$5 -> 45 | L69: =I69*K69 -> 36 | M69: =K69*J69 -> 658.6272 | N69: 63 | O69: =N69*G69 -> 1152.5976 | P69: =(I69*K69)+N69 -> 99 | Q69: =P69*G69 -> 1811.2248
A70: =IF(F70<>"",1+MAX($A$2:A69),"") -> 40 | D70: Compacted Sub-Grade | E70: 5346 | F70: 0.1 | G70: =E70*(1+F70) -> 5880.6 | H70: SF | I70: 0.007 | J70: =+I70*G70 -> 41.1642 | K70: ='LABOR SHEET'!$C$5 -> 45 | L70: =I70*K70 -> 0.315 | M70: =K70*J70 -> 1852.389 | N70: 0.4 | O70: =N70*G70 -> 2352.24 | P70: =(I70*K70)+N70 -> 0.715 | Q70: =P70*G70 -> 4204.629
A71: =IF(F71<>"",1+MAX($A$2:A70),"") -> 41 | D71: Formwork | E71: =2162*0.5 -> 1081 | F71: 0.1 | G71: =E71*(1+F71) -> 1189.1 | H71: SF | I71: 0.018 | J71: =+I71*G71 -> 21.4038 | K71: ='LABOR SHEET'!$C$5 -> 45 | L71: =I71*K71 -> 0.81 | M71: =K71*J71 -> 963.171 | N71: 3 | O71: =N71*G71 -> 3567.3 | P71: =(I71*K71)+N71 -> 3.81 | Q71: =P71*G71 -> 4530.471
A73: =IF(F73<>"",1+MAX($A$2:A72),"") -> 42 | D73: "B2" 4" Thick Concrete Sidewalk W/ Welded Wire Flat | E73: =834*0.34/27 -> 10.502222 | F73: 0.1 | G73: =E73*(1+F73) -> 11.552444 | H73: CY | I73: 2.6 | J73: =+I73*G73 -> 30.036356 | K73: ='LABOR SHEET'!$C$5 -> 45 | L73: =I73*K73 -> 117 | M73: =K73*J73 -> 1351.636 | N73: 198 | O73: =N73*G73 -> 2287.384 | P73: =(I73*K73)+N73 -> 315 | Q73: =P73*G73 -> 3639.02
A74: =IF(F74<>"",1+MAX($A$2:A73),"") -> 43 | D74: #3 Bars @ 12" O.C Centered In Slab | E74: =834*0.376 -> 313.584 | F74: 0.05 | G74: =E74*(1+F74) -> 329.2632 | H74: LBS | I74: 0.011 | J74: =+I74*G74 -> 3.6218952 | K74: ='LABOR SHEET'!$C$5 -> 45 | L74: =I74*K74 -> 0.495 | M74: =K74*J74 -> 162.98528 | N74: 1 | O74: =N74*G74 -> 329.2632 | P74: =(I74*K74)+N74 -> 1.495 | Q74: =P74*G74 -> 492.24848
A75: =IF(F75<>"",1+MAX($A$2:A74),"") -> 44 | D75: #3 Bars @ 8" O.C Centered In Slab | E75: =0.376*834 -> 313.584 | F75: 0.05 | G75: =E75*(1+F75) -> 329.2632 | H75: LBS | I75: 0.011 | J75: =+I75*G75 -> 3.6218952 | K75: ='LABOR SHEET'!$C$5 -> 45 | L75: =I75*K75 -> 0.495 | M75: =K75*J75 -> 162.98528 | N75: 1 | O75: =N75*G75 -> 329.2632 | P75: =(I75*K75)+N75 -> 1.495 | Q75: =P75*G75 -> 492.24848
A76: =IF(F76<>"",1+MAX($A$2:A75),"") -> 45 | D76: 2" Thick Sand Cushion | E76: =0.16*834/27 -> 4.9422222 | F76: 0.1 | G76: =E76*(1+F76) -> 5.4364444 | H76: CY | I76: 0.8 | J76: =+I76*G76 -> 4.3491556 | K76: ='LABOR SHEET'!$C$5 -> 45 | L76: =I76*K76 -> 36 | M76: =K76*J76 -> 195.712 | N76: 63 | O76: =N76*G76 -> 342.496 | P76: =(I76*K76)+N76 -> 99 | Q76: =P76*G76 -> 538.208
A77: =IF(F77<>"",1+MAX($A$2:A76),"") -> 46 | D77: Compacted Sub-Grade | E77: 834 | F77: 0.1 | G77: =E77*(1+F77) -> 917.4 | H77: SF | I77: 0.007 | J77: =+I77*G77 -> 6.4218 | K77: ='LABOR SHEET'!$C$5 -> 45 | L77: =I77*K77 -> 0.315 | M77: =K77*J77 -> 288.981 | N77: 0.4 | O77: =N77*G77 -> 366.96 | P77: =(I77*K77)+N77 -> 0.715 | Q77: =P77*G77 -> 655.941
A78: =IF(F78<>"",1+MAX($A$2:A77),"") -> 47 | D78: Formwork | E78: =310*0.5 -> 155 | F78: 0.1 | G78: =E78*(1+F78) -> 170.5 | H78: SF | I78: 0.018 | J78: =+I78*G78 -> 3.069 | K78: ='LABOR SHEET'!$C$5 -> 45 | L78: =I78*K78 -> 0.81 | M78: =K78*J78 -> 138.105 | N78: 3 | O78: =N78*G78 -> 511.5 | P78: =(I78*K78)+N78 -> 3.81 | Q78: =P78*G78 -> 649.605
A80: =IF(F80<>"",1+MAX($A$2:A78),"") | D80: Concrete Curb
A81: =IF(F81<>"",1+MAX($A$2:A80),"") -> 48 | D81: "C1" (6"X9") Concrete Curb (2390 Lf) | E81: =0.5*0.75*2390/27 -> 33.194444 | F81: 0.1 | G81: =E81*(1+F81) -> 36.513889 | H81: CY | I81: 2.7 | J81: =+I81*G81 -> 98.5875 | K81: ='LABOR SHEET'!$C$5 -> 45 | L81: =I81*K81 -> 121.5 | M81: =K81*J81 -> 4436.4375 | N81: 180 | O81: =N81*G81 -> 6572.5 | P81: =(I81*K81)+N81 -> 301.5 | Q81: =P81*G81 -> 11008.938
A82: =IF(F82<>"",1+MAX($A$2:A81),"") -> 49 | D82: 2#3 Bar | E82: =2*2390*0.376 -> 1797.28 | F82: 0.05 | G82: =E82*(1+F82) -> 1887.144 | H82: LBS | I82: 0.011 | J82: =+I82*G82 -> 20.758584 | K82: ='LABOR SHEET'!$C$5 -> 45 | L82: =I82*K82 -> 0.495 | M82: =K82*J82 -> 934.13628 | N82: 1 | O82: =N82*G82 -> 1887.144 | P82: =(I82*K82)+N82 -> 1.495 | Q82: =P82*G82 -> 2821.2803
A83: =IF(F83<>"",1+MAX($A$2:A82),"") -> 50 | D83: Formwork | E83: =2390*0.5*2 -> 2390 | F83: 0.1 | G83: =E83*(1+F83) -> 2629 | H83: SF | I83: 0.018 | J83: =+I83*G83 -> 47.322 | K83: ='LABOR SHEET'!$C$5 -> 45 | L83: =I83*K83 -> 0.81 | M83: =K83*J83 -> 2129.49 | N83: 3 | O83: =N83*G83 -> 7887 | P83: =(I83*K83)+N83 -> 3.81 | Q83: =P83*G83 -> 10016.49
A85: =IF(F85<>"",1+MAX($A$2:A83),"") -> 51 | D85: "C2" (20"X9") Standard / Flush Concrete Curb (150 Lf) | E85: =150*1.67*0.75/27 -> 6.9583333 | F85: 0.1 | G85: =E85*(1+F85) -> 7.6541667 | H85: CY | I85: 2.7 | J85: =+I85*G85 -> 20.66625 | K85: ='LABOR SHEET'!$C$5 -> 45 | L85: =I85*K85 -> 121.5 | M85: =K85*J85 -> 929.98125 | N85: 180 | O85: =N85*G85 -> 1377.75 | P85: =(I85*K85)+N85 -> 301.5 | Q85: =P85*G85 -> 2307.7312
A86: =IF(F86<>"",1+MAX($A$2:A85),"") -> 52 | D86: 3#3 Bar | E86: =150*2*0.376 -> 112.8 | F86: 0.05 | G86: =E86*(1+F86) -> 118.44 | H86: LBS | I86: 0.011 | J86: =+I86*G86 -> 1.30284 | K86: ='LABOR SHEET'!$C$5 -> 45 | L86: =I86*K86 -> 0.495 | M86: =K86*J86 -> 58.6278 | N86: 0.9 | O86: =N86*G86 -> 106.596 | P86: =(I86*K86)+N86 -> 1.395 | Q86: =P86*G86 -> 165.2238
A87: =IF(F87<>"",1+MAX($A$2:A86),"") -> 53 | D87: Formwork | E87: =150*1.67*2 -> 501 | F87: 0.1 | G87: =E87*(1+F87) -> 551.1 | H87: SF | I87: 0.018 | J87: =+I87*G87 -> 9.9198 | K87: ='LABOR SHEET'!$C$5 -> 45 | L87: =I87*K87 -> 0.81 | M87: =K87*J87 -> 446.391 | N87: 3 | O87: =N87*G87 -> 1653.3 | P87: =(I87*K87)+N87 -> 3.81 | Q87: =P87*G87 -> 2099.691
A89: =IF(F89<>"",1+MAX($A$2:A88),"") -> 54 | D89: "C3" (9"X12") Concrete Curb (156 Lf) | E89: =0.75*1*156/27 -> 4.3333333 | F89: 0.1 | G89: =E89*(1+F89) -> 4.7666667 | H89: CY | I89: 2.7 | J89: =+I89*G89 -> 12.87 | K89: ='LABOR SHEET'!$C$5 -> 45 | L89: =I89*K89 -> 121.5 | M89: =K89*J89 -> 579.15 | N89: 180 | O89: =N89*G89 -> 858 | P89: =(I89*K89)+N89 -> 301.5 | Q89: =P89*G89 -> 1437.15
A90: =IF(F90<>"",1+MAX($A$2:A89),"") -> 55 | D90: 18" Bar @ 18" O.C | E90: =156/1.5*1.5 -> 156 | F90: 0.05 | G90: =E90*(1+F90) -> 163.8 | H90: LF | I90: 0.011 | J90: =+I90*G90 -> 1.8018 | K90: ='LABOR SHEET'!$C$5 -> 45 | L90: =I90*K90 -> 0.495 | M90: =K90*J90 -> 81.081 | N90: 1 | O90: =N90*G90 -> 163.8 | P90: =(I90*K90)+N90 -> 1.495 | Q90: =P90*G90 -> 244.881
A91: =IF(F91<>"",1+MAX($A$2:A90),"") -> 56 | D91: Formwork | E91: =156*1*2 -> 312 | F91: 0.1 | G91: =E91*(1+F91) -> 343.2 | H91: SF | I91: 0.018 | J91: =+I91*G91 -> 6.1776 | K91: ='LABOR SHEET'!$C$5 -> 45 | L91: =I91*K91 -> 0.81 | M91: =K91*J91 -> 277.992 | N91: 3 | O91: =N91*G91 -> 1029.6 | P91: =(I91*K91)+N91 -> 3.81 | Q91: =P91*G91 -> 1307.592
A93: =IF(F93<>"",1+MAX($A$2:A91),"") | D93: Concrete Wheel stop
A94: =IF(F94<>"",1+MAX($A$2:A93),"") -> 57 | D94: "F" (10" X6'-0") Precast Concrete Wheel stop W/ 2 #4 Bars | E94: 87 | F94: 0 | G94: =E94*(1+F94) -> 87 | H94: EA | I94: 1.285 | J94: =+I94*G94 -> 111.795 | K94: ='LABOR SHEET'!$C$5 -> 45 | L94: =I94*K94 -> 57.825 | M94: =K94*J94 -> 5030.775 | N94: 124 | O94: =N94*G94 -> 10788 | P94: =(I94*K94)+N94 -> 181.825 | Q94: =P94*G94 -> 15818.775
A95: =IF(F95<>"",1+MAX($A$2:A94),"") -> 58 | D95: "A2" 2" Thick Type "D" Hot Asphalt Mix Pavement (Medium Duty) | E95: 34116 | F95: 0.1 | G95: =E95*(1+F95) -> 37527.6 | H95: SF | I95: 0.038 | J95: =+I95*G95 -> 1426.0488 | K95: ='LABOR SHEET'!$C$5 -> 45 | L95: =I95*K95 -> 1.71 | M95: =K95*J95 -> 64172.196 | N95: 1.24 | O95: =N95*G95 -> 46534.224 | P95: =(I95*K95)+N95 -> 2.95 | Q95: =P95*G95 -> 110706.42
A96: =IF(F96<>"",1+MAX($A$2:A95),"") -> 59 | D96: 12" Thick Compacted Flexible Base | E96: =34116*1/27 -> 1263.5556 | F96: 0.1 | G96: =E96*(1+F96) -> 1389.9111 | H96: CY | I96: 1 | J96: =+I96*G96 -> 1389.9111 | K96: ='LABOR SHEET'!$C$5 -> 45 | L96: =I96*K96 -> 45 | M96: =K96*J96 -> 62546 | N96: 62 | O96: =N96*G96 -> 86174.489 | P96: =(I96*K96)+N96 -> 107 | Q96: =P96*G96 -> 148720.49
A97: =IF(F97<>"",1+MAX($A$2:A96),"") -> 60 | D97: 6" Thick Compacted Sub-Grade | E97: 34116 | F97: 0.1 | G97: =E97*(1+F97) -> 37527.6 | H97: SF | I97: 0.007 | J97: =+I97*G97 -> 262.6932 | K97: ='LABOR SHEET'!$C$5 -> 45 | L97: =I97*K97 -> 0.315 | M97: =K97*J97 -> 11821.194 | N97: 0.4 | O97: =N97*G97 -> 15011.04 | P97: =(I97*K97)+N97 -> 0.715 | Q97: =P97*G97 -> 26832.234
A99: =IF(F99<>"",1+MAX($A$2:A97),"") | D99: Parking Paint
A100: =IF(F100<>"",1+MAX($A$2:A99),"") -> 61 | D100: "E1" Pavement Marking International Handicap Symbol | E100: 6 | F100: 0 | G100: =E100*(1+F100) -> 6 | H100: EA | I100: 0.5 | J100: =+I100*G100 -> 3 | K100: ='LABOR SHEET'!$C$5 -> 45 | L100: =I100*K100 -> 22.5 | M100: =K100*J100 -> 135 | N100: 72 | O100: =N100*G100 -> 432 | P100: =(I100*K100)+N100 -> 94.5 | Q100: =P100*G100 -> 567
A101: =IF(F101<>"",1+MAX($A$2:A100),"") -> 62 | D101: "E2" Pavement Marking Pvmt Mrkg: 12" Height Letter At 2" Stroke Width "No Parking" | E101: 3 | F101: 0 | G101: =E101*(1+F101) -> 3 | H101: EA | I101: 0.72 | J101: =+I101*G101 -> 2.16 | K101: ='LABOR SHEET'!$C$5 -> 45 | L101: =I101*K101 -> 32.4 | M101: =K101*J101 -> 97.2 | N101: 88 | O101: =N101*G101 -> 264 | P101: =(I101*K101)+N101 -> 120.4 | Q101: =P101*G101 -> 361.2
A102: =IF(F102<>"",1+MAX($A$2:A101),"") -> 63 | D102: "E5" Pvmt Mrkg: Bus Parking (White) | E102: 2 | F102: 0 | G102: =E102*(1+F102) -> 2 | H102: EA | I102: 0.5 | J102: =+I102*G102 -> 1 | K102: ='LABOR SHEET'!$C$5 -> 45 | L102: =I102*K102 -> 22.5 | M102: =K102*J102 -> 45 | N102: 72 | O102: =N102*G102 -> 144 | P102: =(I102*K102)+N102 -> 94.5 | Q102: =P102*G102 -> 189
A103: =IF(F103<>"",1+MAX($A$2:A102),"") -> 64 | D103: "E6" Pvmt Mrkg: 4" Wide Painted Stripe (White) | E103: 2408 | F103: 0.05 | G103: =E103*(1+F103) -> 2528.4 | H103: LF | I103: 0.032 | J103: =+I103*G103 -> 80.9088 | K103: ='LABOR SHEET'!$C$5 -> 45 | L103: =I103*K103 -> 1.44 | M103: =K103*J103 -> 3640.896 | N103: 2.1 | O103: =N103*G103 -> 5309.64 | P103: =(I103*K103)+N103 -> 3.54 | Q103: =P103*G103 -> 8950.536
A104: =IF(F104<>"",1+MAX($A$2:A103),"") -> 65 | D104: "E3" Pvmt Mrkg: 12" Height Letter At 2" Stroke Width "No Parking" | E104: 1638 | F104: 0.05 | G104: =E104*(1+F104) -> 1719.9 | H104: LF | I104: 0.048 | J104: =+I104*G104 -> 82.5552 | K104: ='LABOR SHEET'!$C$5 -> 45 | L104: =I104*K104 -> 2.16 | M104: =K104*J104 -> 3714.984 | N104: 2.4 | O104: =N104*G104 -> 4127.76 | P104: =(I104*K104)+N104 -> 4.56 | Q104: =P104*G104 -> 7842.744
A105: =IF(F105<>"",1+MAX($A$2:A104),"") -> 66 | D105: "E4" Pvmt Mrkg: Exit Only (White) | E105: 1 | F105: 0 | G105: =E105*(1+F105) -> 1 | H105: EA | I105: 0.5 | J105: =+I105*G105 -> 0.5 | K105: ='LABOR SHEET'!$C$5 -> 45 | L105: =I105*K105 -> 22.5 | M105: =K105*J105 -> 22.5 | N105: 72 | O105: =N105*G105 -> 72 | P105: =(I105*K105)+N105 -> 94.5 | Q105: =P105*G105 -> 94.5
A107: =IF(F107<>"",1+MAX($A$2:A105),"") | D107: Concrete Flum
A108: =IF(F108<>"",1+MAX($A$2:A107),"") -> 67 | D108: "K" 6" Thick Concrete Flum | E108: =0.5*863/27 -> 15.981481 | F108: 0.1 | G108: =E108*(1+F108) -> 17.57963 | H108: CY | I108: 2.4 | J108: =+I108*G108 -> 42.191111 | K108: ='LABOR SHEET'!$C$5 -> 45 | L108: =I108*K108 -> 108 | M108: =K108*J108 -> 1898.6 | N108: 180 | O108: =N108*G108 -> 3164.3333 | P108: =(I108*K108)+N108 -> 288 | Q108: =P108*G108 -> 5062.9333
A109: =IF(F109<>"",1+MAX($A$2:A108),"") -> 68 | D109: "K" (12"X6") Concrete Thicken Edge | E109: =343*1*0.5/27 -> 6.3518519 | F109: 0.1 | G109: =E109*(1+F109) -> 6.987037 | H109: CY | I109: 2.6 | J109: =+I109*G109 -> 18.166296 | K109: ='LABOR SHEET'!$C$5 -> 45 | L109: =I109*K109 -> 117 | M109: =K109*J109 -> 817.48333 | N109: 180 | O109: =N109*G109 -> 1257.6667 | P109: =(I109*K109)+N109 -> 297 | Q109: =P109*G109 -> 2075.15
A110: =IF(F110<>"",1+MAX($A$2:A109),"") -> 69 | D110: #4 Bar Each Way | E110: =863/1*2*0.668 -> 1152.968 | F110: 0.05 | G110: =E110*(1+F110) -> 1210.6164 | H110: LBS | I110: 0.011 | J110: =+I110*G110 -> 13.31678 | K110: ='LABOR SHEET'!$C$5 -> 45 | L110: =I110*K110 -> 0.495 | M110: =K110*J110 -> 599.25512 | N110: 0.9 | O110: =N110*G110 -> 1089.5548 | P110: =(I110*K110)+N110 -> 1.395 | Q110: =P110*G110 -> 1688.8099
A111: =IF(F111<>"",1+MAX($A$2:A110),"") -> 70 | D111: #4 Bar @ 12" O.C | E111: =0.668*343 -> 229.124 | F111: 0.05 | G111: =E111*(1+F111) -> 240.5802 | H111: LBS | I111: 0.011 | J111: =+I111*G111 -> 2.6463822 | K111: ='LABOR SHEET'!$C$5 -> 45 | L111: =I111*K111 -> 0.495 | M111: =K111*J111 -> 119.0872 | N111: 0.9 | O111: =N111*G111 -> 216.52218 | P111: =(I111*K111)+N111 -> 1.395 | Q111: =P111*G111 -> 335.60938
A113: =IF(F113<>"",1+MAX($A$2:A111),"") | D113: Sediment Control Trap
A114: =IF(F114<>"",1+MAX($A$2:A113),"") -> 71 | D114: Sediment Control Trap That Needs To Be Installed | E114: 38 | F114: 0.05 | G114: =E114*(1+F114) -> 39.9 | H114: LF | I114: 0.052 | J114: =+I114*G114 -> 2.0748 | K114: ='LABOR SHEET'!$C$5 -> 45 | L114: =I114*K114 -> 2.34 | M114: =K114*J114 -> 93.366 | N114: 12 | O114: =N114*G114 -> 478.8 | P114: =(I114*K114)+N114 -> 14.34 | Q114: =P114*G114 -> 572.166
...

Sheet LABOR SHEET
B1: Labor Type | C1: Labor Rate
A3: Plumbing | B3: Plum | C3: 70
A4: Earthwork | B4: Q14C | C4: 45
A5: Exterior Improvement | B5: B15S | C5: 45
A8: Manhour Increase Factor | B8: 0
B10: Wastage
A11: Each/Count | B11: EA | C11: 0
A12: Linear Footage | B12: LF | C12: 0.05
A13: Square Footage | B13: SF | C13: 0.1
A14: Square Yard | B14: SY | C14: 0.1
A15: Cubic Yard | B15: CY | C15: 0.1
A16: Lumpsum | B16: LS | C16: 0
A17: Survery | B17: Survey | C17: 0
A18: Stair Riser | B18: RISER | C18: 0
A19: Blocks Count | B19: BLOCKS | C19: 0
A20: Bags of Pre-Mix Mortar | B20: BAGS | C20: 0
A21: Linear Footage of Wall | B21: LF.Wall | C21: 0.1
A22: Pounds | B22: LBS | C22: 0.1
... A33: N/A | B33: N/A | C33: 0
A36: NOTE:
A37: Prevailing wages have been included in this estimate in compliance with the Davis-Bacon Act.
A38: Material pricing is based on current market rates sourced from reputable online platforms and suppliers.
A39: Please note that actual costs may vary depending on site-specific conditions, unforeseen circumstances, or changes in market conditions.
